Workbook

Sheet Legend
C2: data missing
C3: different GEM information
C4: needs verification
C5: not in IESR data
B7: Summary | C7: IESR data | D7: GEM
B8: Operating | C8: =SUMIF('PLN & IPP'!N:N,B8,'PLN & IPP'!C:C) -> 31481 | D8: =SUMIF(GEM!M:M,B8,GEM!L:L) -> 30767
B9: Construction | C9: =SUMIF('PLN & IPP'!N:N,B9,'PLN & IPP'!C:C)+SUMIF('PLN & IPP'!N:N,"On going construction",'PLN & IPP'!C:C) -> 10629 | D9: =SUMIF(GEM!M:M,B9,GEM!L:L) -> 10339
B10: Permitted | C10: =SUMIF('PLN & IPP'!N:N,B10,'PLN & IPP'!C:C) -> 700 | D10: =SUMIF(GEM!M:M,B10,GEM!L:L) -> 700
B11: pre-permit | C11: =SUMIF('PLN & IPP'!N:N,B11,'PLN & IPP'!C:C) -> 900 | D11: =SUMIF(GEM!M:M,B11,GEM!L:L) -> 1700
B12: shelved | C12: =SUMIF('PLN & IPP'!N:N,B12,'PLN & IPP'!C:C) -> 2320 | D12: =SUMIF(GEM!M:M,B12,GEM!L:L) -> 3820
B16: Progress as of March 2022
B17: Projects with AMDALs | C17: Notes
B18: Bengkulu U1&2
B19: Celukan Bawang Unit 1-3
B20: Cilacap Unit 1-3 | C20: Not complete
B21: Cirebon 1
B22: Indramayu Unit 1-3
B23: Jawa-1 / Cirebon-2
B24: Jawa-4/Tanjung Jati B Unit 5&6
B25: Tanjung Jati B Unit 3&4
B26: Paiton Unit 3

Sheet all_status
A1: CFPP name | B1: GEM ID | C1: Owner | D1: Captive industry | E1: Capacity (MW) | F1: COD | G1: Status Jul 2024 | H1: Status Jan 2024 | I1: Status Jun 2023 | J1: Latitude | K1: Longitude | L1: Parent | M1: Province_EN | N1: Provinsi_ID
A2: Adaro Aluminum Smelter Phase I | B2: G115748 | C2: Captive | D2: Aluminum | E2: 1100 | F2: 2025 | G2: pre-permit | H2: pre-permit | I2: pre-permit | J2: 2.528 | K2: 117.858 | L2: PT Adaro Power | M2: North Kalimantan | N2: Kalimantan Utara
A3: Adaro Aluminum Smelter Phase II | B3: G115905 | C3: Captive | D3: Aluminum | E3: 1100 | F3: 2026 | G3: announced | H3: announced | I3: announced | J3: 2.528 | K3: 117.858 | L3: PT Adaro Power | M3: North Kalimantan | N3: Kalimantan Utara
A4: Ketapang Smelter Phase I, Unit 3 | B4: G105679 | C4: Captive | D4: Aluminum | E4: 30 | F4: 2016 | G4: operating | H4: operating | I4: operating | J4: -2.366182 | K4: 110.15727 | L4: China Hongqiao Group; Harita Group | M4: West Kalimantan | N4: Kalimantan Barat
A5: Ketapang Smelter Phase II, Unit 1 | B5: G114899 | C5: Captive | D5: Aluminum | E5: 80 | F5: 2021 | G5: operating | H5: operating | I5: operating | J5: -2.366182 | K5: 110.15727 | L5: China Hongqiao Group; Harita Group | M5: West Kalimantan | N5: Kalimantan Barat
A6: Ketapang Smelter Phase II, Unit 2 | B6: G114900 | C6: Captive | D6: Aluminum | E6: 80 | F6: 2021 | G6: operating | H6: operating | I6: operating | J6: -2.366182 | K6: 110.15727 | L6: China Hongqiao Group; Harita Group | M6: West Kalimantan | N6: Kalimantan Barat
A7: Ketapang Smelter Phase II, Unit 3 | B7: G105680 | C7: Captive | D7: Aluminum | E7: 30 | F7: 2021 | G7: operating | H7: operating | I7: operating | J7: -2.366182 | K7: 110.15727 | L7: China Hongqiao Group; Harita Group | M7: West Kalimantan | N7: Kalimantan Barat
A8: Kuala Tanjung Inalum captive / Sumut-2 Unit 1 | B8: G105993 | C8: Captive | D8: Aluminum | E8: 300 | F8: 2023 | G8: cancelled | H8: cancelled | I8: cancelled | J8: 3.3506353 | K8: 99.451332 | L8: PT Bukit Asam [100.0%] | M8: North Sumatra | N8: Sumatra Utara
A9: Kuala Tanjung Inalum captive / Sumut-2 Unit 2 | B9: G105994 | C9: Captive | D9: Aluminum | E9: 300 | F9: 2024 | G9: cancelled | H9: cancelled | I9: cancelled | J9: 3.3506353 | K9: 99.451332 | L9: PT Bukit Asam [100.0%] | M9: North Sumatra | N9: Sumatra Utara
A10: Kuala Tanjung Inalum captive Unit 3 | B10: G105995 | C10: Captive | D10: Aluminum | E10: 350 | F10: 0 | G10: cancelled | H10: cancelled | I10: cancelled | J10: 3.3506353 | K10: 99.451332 | L10: PT Bukit Asam; PT Indonesia Asahan Aluminium | M10: North Sumatra | N10: Sumatra Utara
A11: NALCO East Kutai Unit 1 | B11: G107201 | C11: Captive | D11: Aluminum | E11: 250 | F11: 0 | G11: cancelled | H11: cancelled | I11: cancelled | J11: 1.254 | K11: 116.682 | L11: MEC Coal; Nalco Holding Co | M11: East Kalimantan | N11: Kalimantan Timur
A12: NALCO East Kutai Unit 2 | B12: G107202 | C12: Captive | D12: Aluminum | E12: 250 | F12: 0 | G12: cancelled | H12: cancelled | I12: cancelled | J12: 1.254 | K12: 116.682 | L12: MEC Coal; Nalco Holding Co | M12: East Kalimantan | N12: Kalimantan Timur
A13: NALCO East Kutai Unit 3 | B13: G107203 | C13: Captive | D13: Aluminum | E13: 250 | F13: 0 | G13: cancelled | H13: cancelled | I13: cancelled | J13: 1.254 | K13: 116.682 | L13: MEC Coal; Nalco Holding Co | M13: East Kalimantan | N13: Kalimantan Timur
... A52: Adaro East Kalimantan Unit 2 | B52: G100038 | C52: Captive | D52: Coal mining - Power generation | E52: 300 | F52: 0 | G52: cancelled | H52: cancelled | I52: cancelled | J52: 0.1 | K52: 116.4 | L52: China Energy Investment Corp; PT Adaro Power | M52: East Kalimantan | N52: Kalimantan Timur
A53: Astratel Phase I | B53: G100391 | C53: Captive | D53: Coal mining - Power generation | E53: 100 | F53: 0 | G53: cancelled | H53: cancelled | I53: cancelled | J53: -2.75 | K53: 103.83333 | L53: Astra International | M53: 0 | N53: 0
A54: DSS Serang Unit 1 | B54: G115073 | C54: Captive | D54: Coal mining - Power generation | E54: 35 | F54: 2016 | G54: operating | H54: operating | I54: operating | J54: -6.125435 | K54: 106.2892 | L54: PT Dian Swastatika Sentosa [100.0%] | M54: Banten | N54: Banten
A55: DSS Serang Unit 2 | B55: G115074 | C55: Captive | D55: Coal mining - Power generation | E55: 35 | F55: 2016 | G55: operating | H55: operating | I55: operating | J55: -6.125435 | K55: 106.2892 | L55: PT Dian Swastatika Sentosa [100.0%] | M55: Banten | N55: Banten
A56: DSS Serang Unit 3 | B56: G115075 | C56: Captive | D56: Coal mining - Power generation | E56: 35 | F56: 2016 | G56: operating | H56: operating | I56: operating | J56: -6.125435 | K56: 106.2892 | L56: PT Dian Swastatika Sentosa [100.0%] | M56: Banten | N56: Banten
A57: DSS Serang Unit 4 | B57: G115076 | C57: Captive | D57: Coal mining - Power generation | E57: 70 | F57: 2016 | G57: operating | H57: operating | I57: operating | J57: -6.125435 | K57: 106.2892 | L57: PT Dian Swastatika Sentosa [100.0%] | M57: Banten | N57: Banten
A58: Jambi Tebo Unit 1 | B58: G104953 | C58: Captive | D58: Coal mining - Power generation | E58: 200 | F58: 0 | G58: cancelled | H58: cancelled | I58: cancelled | J58: -1.39 | K58: 102.42 | L58: Korea Electric Power Corp [100.0%] | M58: Jambi | N58: Jambi
A59: Jambi Tebo Unit 2 | B59: G104954 | C59: Captive | D59: Coal mining - Power generation | E59: 200 | F59: 0 | G59: cancelled | H59: cancelled | I59: cancelled | J59: -1.39 | K59: 102.42 | L59: Korea Electric Power Corp [100.0%] | M59: Jambi | N59: Jambi
A60: Mesuji Unit 1 | B60: G106887 | C60: Captive | D60: Coal mining - Power generation | E60: 350 | F60: 0 | G60: cancelled | H60: cancelled | I60: cancelled | J60: -4.012776 | K60: 105.46296 | L60: China Shenhua Energy [100.0%] | M60: Lampung | N60: Lampung
A61: Mesuji Unit 2 | B61: G106888 | C61: Captive | D61: Coal mining - Power generation | E61: 350 | F61: 0 | G61: cancelled | H61: cancelled | I61: cancelled | J61: -4.012776 | K61: 105.46296 | L61: China Shenhua Energy [100.0%] | M61: Lampung | N61: Lampung
A62: Pindo-Deli-Ii Unit 1 | B62: G107980 | C62: Captive | D62: Coal mining - Power generation | E62: 50 | F62: 2007 | G62: operating | H62: operating | I62: operating | J62: -6.385474 | K62: 107.34362 | L62: PT Dian Swastatika Sentosa [100.0%] | M62: West Java | N62: Jawa Barat
A63: Sinar Mas Jambi Unit 1 | B63: G109402 | C63: Captive | D63: Coal mining - Power generation | E63: 200 | F63: 0 | G63: cancelled | H63: cancelled | I63: cancelled | J63: -1.61 | K63: 101.91 | L63: PT Dian Swastatika Sentosa [100.0%] | M63: Jambi | N63: Jambi
A64: Sinar Mas Jambi Unit 2 | B64: G109403 | C64: Captive | D64: Coal mining - Power generation | E64: 200 | F64: 0 | G64: cancelled | H64: cancelled | I64: cancelled | J64: -1.61 | K64: 101.91 | L64: PT Dian Swastatika Sentosa [100.0%] | M64: Jambi | N64: Jambi
A65: Tabalong Wisesa Unit 1 | B65: G109792 | C65: Captive | D65: Coal mining - Power generation | E65: 30 | F65: 2013 | G65: operating | H65: operating | I65: operating | J65: -2.158586 | K65: 115.44593 | L65: PT Adaro Power | M65: South Kalimantan | N65: Kalimantan Tengah
... A214: Timah South Sumatra Unit 2 | B214: G110176 | C214: Captive | D214: Tin | E214: 150 | F214: 0 | G214: cancelled | H214: cancelled | I214: cancelled | J214: -3.539482 | K214: 103.75484 | L214: PT Timah [100.0%] | M214: South Sumatra | N214: Sumatra Selatan
A215: Bakrie Sangatta Unit 1 | B215: G100455 | C215: IPP | E215: 100 | F215: 0 | G215: cancelled | H215: cancelled | I215: cancelled | J215: 0.605 | K215: 117.481 | L215: Bakrie Group | M215: East Kalimantan | N215: Kalimantan Timur
A216: Bakrie Sangatta Unit 2 | B216: G100456 | C216: IPP | E216: 100 | F216: 0 | G216: cancelled | H216: cancelled | I216: cancelled | J216: 0.605 | K216: 117.481 | L216: Bakrie Group | M216: East Kalimantan | N216: Kalimantan Timur
A217: Bali | B217: G113818 | C217: IPP | E217: 135 | F217: 0 | G217: cancelled | H217: cancelled | I217: cancelled | J217: -8.447602 | K217: 115.12221 | L217: to be determined [100.0%] | M217: Bali | N217: Bali
A218: Bangko Tengah Unit 3 | B218: G100512 | C218: IPP | E218: 660 | F218: 0 | G218: cancelled | H218: cancelled | I218: cancelled | J218: -3.734 | K218: 103.759 | L218: China Huadian Group Corp [55.0%]; PT Bukit Asam Tbk [45.0%] | M218: South Sumatra | N218: Sumatra Selatan
A219: Bangko Tengah Unit 4 | B219: G100513 | C219: IPP | E219: 660 | F219: 0 | G219: cancelled | H219: cancelled | I219: cancelled | J219: -3.734 | K219: 103.759 | L219: China Huadian Group Corp [55.0%]; PT Bukit Asam Tbk [45.0%] | M219: South Sumatra | N219: Sumatra Selatan
A220: Banjarsari Unit 1 | B220: G100519 | C220: IPP | E220: 110 | F220: 2015 | G220: operating | H220: operating | I220: operating | J220: -3.72507 | K220: 103.69039 | L220: PT Bukit Asam Tbk [59.8%]; PT PLN (Persero) [37.2%]; other unknown/mixed entity types [3.0%] | M220: South Sumatra | N220: Sumatra Selatan
A221: Banjarsari Unit 2 | B221: G100520 | C221: IPP | E221: 110 | F221: 2015 | G221: operating | H221: operating | I221: operating | J221: -3.72507 | K221: 103.69039 | L221: PT Bukit Asam Tbk [59.8%]; PT PLN (Persero) [37.2%]; other unknown/mixed entity types [3.0%] | M221: South Sumatra | N221: Sumatra Selatan
A222: Banten BSE Unit 1 | B222: G114349 | C222: IPP | E222: 300 | F222: 2023 | G222: cancelled | H222: cancelled | I222: cancelled | J222: -6.485765 | K222: 106.03813 | L222: BTN Power; PT Biidznillah Tambang Nusantara | M222: Banten | N222: Banten
A223: Banten BSE Unit 2 | B223: G114350 | C223: IPP | E223: 300 | F223: 2023 | G223: cancelled | H223: cancelled | I223: cancelled | J223: -6.485765 | K223: 106.03813 | L223: BTN Power; PT Biidznillah Tambang Nusantara | M223: Banten | N223: Banten
A224: Banten Serang Unit 2 | B224: G113817 | C224: IPP | E224: 660 | F224: 2025 | G224: cancelled | H224: cancelled | I224: cancelled | J224: -5.882972 | K224: 106.04593 | L224: Genting Group | M224: Banten | N224: Banten
A225: Banten Unit 1 / Banten Serang | B225: G100536 | C225: IPP | E225: 660 | F225: 2017 | G225: operating | H225: operating | I225: operating | J225: -5.882972 | K225: 106.04593 | L225: Genting Group | M225: Banten | N225: Banten
A226: Banyuasin Unit 1 | B226: G100548 | C226: IPP | E226: 120 | F226: 2021 | G226: cancelled | H226: cancelled | I226: cancelled | J226: -3.347874 | K226: 103.90047 | L226: Oceanwide Holdings Co Ltd [85.0%]; PT Satya Abadi Semesta [10.0%]; China Power International Development Co Ltd [5.0%] | M226: South Sumatra | N226: Sumatra Selatan
... A265: Jawa-10 | B265: G113472 | C265: IPP | E265: 1000 | F265: 2026 | G265: construction | H265: construction | I265: construction | J265: -5.8892179 | K265: 106.0336 | L265: PT PLN (Persero) [51.0%]; PT Barito Pacific [49.0%] | M265: Banten | N265: Banten
A266: Jawa-11 | B266: G104976 | C266: IPP | E266: 600 | F266: 2026 | G266: cancelled | H266: cancelled | I266: cancelled | J266: -7.26 | K266: 110.66 | L266: to be determined [100.0%] | M266: 0 | N266: 0
A267: Jawa-12 Unit 1 | B267: G104977 | C267: IPP | E267: 1000 | F267: 2026 | G267: cancelled | H267: cancelled | I267: cancelled | J267: -7.26 | K267: 110.66 | L267: to be determined [100.0%] | M267: 0 | N267: 0
A268: Jawa-12 Unit 2 | B268: G104978 | C268: IPP | E268: 1000 | F268: 2026 | G268: cancelled | H268: cancelled | I268: cancelled | J268: -7.26 | K268: 110.66 | L268: to be determined [100.0%] | M268: 0 | N268: 0
A269: Jawa-13 | B269: G104979 | C269: IPP | E269: 2000 | F269: 2026 | G269: cancelled | H269: cancelled | I269: cancelled | J269: -7.26 | K269: 110.66 | L269: to be determined [100.0%] | M269: 0 | N269: 0
A270: Jawa-3 Unit 1 | B270: G109954 | C270: IPP | E270: 660 | F270: 2025 | G270: cancelled | H270: cancelled | I270: shelved | J270: -6.768519 | K270: 108.64519 | L270: Bakrie Power; PT Tanjung Jati Power | M270: West Java | N270: Jawa Barat
A271: Jawa-3 Unit 2 | B271: G109955 | C271: IPP | E271: 660 | F271: 2026 | G271: cancelled | H271: cancelled | I271: shelved | J271: -6.768519 | K271: 108.64519 | L271: Bakrie Power; PT Tanjung Jati Power | M271: West Java | N271: Jawa Barat
A272: Jawa-4/Tanjung Jati B Unit 5 | B272: G109958 | C272: IPP | E272: 1000 | F272: 2022 | G272: operating | H272: operating | I272: construction | J272: -6.446488 | K272: 110.74236 | L272: Kansai Electric Power Co; PT United Tractors Tbk; Sumitomo Corp | M272: Central Java | N272: Jawa Tengah
A273: Jawa-4/Tanjung Jati B Unit 6 | B273: G109959 | C273: IPP | E273: 1000 | F273: 2022 | G273: operating | H273: operating | I273: construction | J273: -6.446488 | K273: 110.74236 | L273: Kansai Electric Power Co; PT United Tractors Tbk; Sumitomo Corp | M273: Central Java | N273: Jawa Tengah
A274: Jawa-7 Unit 1 | B274: G104986 | C274: IPP | E274: 991 | F274: 2019 | G274: operating | H274: operating | I274: operating | J274: -5.991694 | K274: 106.1008 | L274: China Shenhua Energy Co Ltd [70.0%]; PT PLN (Persero) [30.0%] | M274: Banten | N274: Banten
A275: Jawa-7 Unit 2 | B275: G104987 | C275: IPP | E275: 991 | F275: 2020 | G275: operating | H275: operating | I275: operating | J275: -5.991694 | K275: 106.1008 | L275: China Shenhua Energy Co Ltd [70.0%]; PT PLN (Persero) [30.0%] | M275: Banten | N275: Banten
A276: Jawa-8 | B276: G101589 | C276: IPP | E276: 1000 | F276: 2019 | G276: operating | H276: operating | I276: operating | J276: -7.6832417 | K276: 109.09638 | L276: PT Sumberenergy Sakti Prima [51.0%]; PT Pembangkitan Jawa Bali [49.0%] | M276: Central Java | N276: Jawa Tengah
A277: Jawa-9 | B277: G100538 | C277: IPP | E277: 1000 | F277: 2025 | G277: construction | H277: construction | I277: construction | J277: -5.8892179 | K277: 106.0336 | L277: PT PLN (Persero) [51.0%]; PT Barito Pacific [49.0%] | M277: Banten | N277: Banten
A278: Jeneponto-1 Unit 1 | B278: G108234 | C278: IPP | E278: 125 | F278: 2012 | G278: operating | H278: operating | I278: operating | J278: -5.617881 | K278: 119.55119 | L278: Bosawa Corp | M278: South Sulawesi | N278: Sulawesi Selatan
A279: Jeneponto-1 Unit 2 | B279: G108235 | C279: IPP | E279: 125 | F279: 2012 | G279: operating | H279: operating | I279: operating | J279: -5.617881 | K279: 119.55119 | L279: Bosawa Corp | M279: South Sulawesi | N279: Sulawesi Selatan
A280: Jeneponto-2 Unit 1 | B280: G108236 | C280: IPP | E280: 135 | F280: 2018 | G280: operating | H280: operating | I280: operating | J280: -5.617881 | K280: 119.55119 | L280: Bosawa Corp | M280: South Sulawesi | N280: Sulawesi Selatan
A281: Jeneponto-2 Unit 2 | B281: G108237 | C281: IPP | E281: 135 | F281: 2018 | G281: operating | H281: operating | I281: operating | J281: -5.617881 | K281: 119.55119 | L281: Bosawa Corp | M281: South Sulawesi | N281: Sulawesi Selatan
... A288: Kalbar-2 Unit 2 | B288: G113442 | C288: IPP | E288: 100 | F288: 2025 | G288: cancelled | H288: cancelled | I288: cancelled | J288: -0.276265 | K288: 109.27959 | L288: to be determined [100.0%] | M288: West Kalimantan | N288: Kalimantan Barat
A289: Kalbar-4 | B289: G105470 | C289: IPP | E289: 200 | F289: 2028 | G289: cancelled | H289: cancelled | I289: cancelled | J289: 1.227 | K289: 114.577 | L289: to be determined [100.0%] | M289: 0 | N289: 0
A290: Kalsel Unit 1 | B290: G109790 | C290: IPP | E290: 100 | F290: 2019 | G290: operating | H290: operating | I290: operating | J290: -2.163427 | K290: 115.44081 | L290: PT Adaro Power [65.0%]; Korea Electric Power Corp [35.0%] | M290: South Kalimantan | N290: Kalimantan Tengah
A291: Kalsel Unit 2 | B291: G109791 | C291: IPP | E291: 100 | F291: 2019 | G291: operating | H291: operating | I291: operating | J291: -2.163427 | K291: 115.44081 | L291: PT Adaro Power [65.0%]; Korea Electric Power Corp [35.0%] | M291: South Kalimantan | N291: Kalimantan Tengah
A292: Kalselteng-1 Unit 1 | B292: G105484 | C292: IPP | E292: 100 | F292: 2020 | G292: operating | H292: operating | I292: operating | J292: -1.370796 | K292: 113.5672 | L292: Datang Overseas Energy Investment Co Ltd [75.0%]; Sinar Mas Group [25.0%] | M292: Central Kalimantan | N292: Kalimantan Tengah
A293: Kalselteng-1 Unit 2 | B293: G105485 | C293: IPP | E293: 100 | F293: 2020 | G293: operating | H293: operating | I293: operating | J293: -1.370796 | K293: 113.5672 | L293: Datang Overseas Energy Investment Co Ltd [75.0%]; Sinar Mas Group [25.0%] | M293: Central Kalimantan | N293: Kalimantan Tengah
A294: Kalselteng-3 Unit 1 | B294: G105486 | C294: IPP | E294: 100 | F294: 2024 | G294: cancelled | H294: cancelled | I294: cancelled | J294: -2.8086279 | K294: 111.64307 | L294: PT PLN (Persero) [100.0%] | M294: Central Kalimantan | N294: Kalimantan Tengah
A295: Kalselteng-3 Unit 2 | B295: G105487 | C295: IPP | E295: 100 | F295: 2025 | G295: cancelled | H295: cancelled | I295: cancelled | J295: -2.8086279 | K295: 111.64307 | L295: PT PLN (Persero) [100.0%] | M295: Central Kalimantan | N295: Kalimantan Tengah
A296: Kalselteng-4 Unit 1 | B296: G114186 | C296: IPP | E296: 100 | F296: 2026 | G296: cancelled | H296: cancelled | I296: cancelled | J296: 1.034129 | K296: 108.9726 | L296: PT Barito Pacific [100.0%] | M296: Central Kalimantan | N296: Kalimantan Tengah
A297: Kalselteng-4 Unit 2 | B297: G114187 | C297: IPP | E297: 100 | F297: 2027 | G297: cancelled | H297: cancelled | I297: cancelled | J297: 1.034129 | K297: 108.9726 | L297: PT Barito Pacific [100.0%] | M297: Central Kalimantan | N297: Kalimantan Tengah
A298: Kaltim (MT) Unit 1 | B298: NA | C298: IPP | E298: 27.5 | F298: 2018 | G298: operating | H298: operating | I298: operating | J298: -0.77860264 | K298: 117.18886 | M298: East Kalimantan | N298: Kalimantan Timur
A299: Kaltim (MT) Unit 2 | B299: NA | C299: IPP | E299: 27.5 | F299: 2018 | G299: operating | H299: operating | I299: operating | J299: -0.77860264 | K299: 117.18886 | M299: East Kalimantan | N299: Kalimantan Timur
A300: Kaltim Teluk Balikpapan Unit 3 | B300: G113833 | C300: IPP | E300: 300 | F300: 0 | G300: cancelled | H300: cancelled | I300: cancelled | J300: -1.17036 | K300: 116.78872 | L300: Genting Group | M300: East Kalimantan | N300: Kalimantan Timur
A301: Kaltim Unit 1 | B301: G105490 | C301: IPP | E301: 100 | F301: 2019 | G301: operating | H301: operating | I301: operating | J301: 0.0551785 | K301: 117.49459 | L301: PT PLN (Persero) [100.0%] | M301: East Kalimantan | N301: Kalimantan Timur
A302: Kaltim Unit 2 | B302: G105491 | C302: IPP | E302: 100 | F302: 2020 | G302: operating | H302: operating | I302: operating | J302: 0.0551785 | K302: 117.49459 | L302: PT PLN (Persero) [100.0%] | M302: East Kalimantan | N302: Kalimantan Timur
A303: Kaltim-3 Unit 1 | B303: G105494 | C303: IPP | E303: 100 | F303: 2025 | G303: cancelled | H303: cancelled | I303: cancelled | J303: 0.135698 | K303: 116.22072 | L303: to be determined [100.0%] | M303: Central Kalimantan | N303: Kalimantan Tengah
A304: Kaltim-3 Unit 2 | B304: G105495 | C304: IPP | E304: 100 | F304: 2026 | G304: cancelled | H304: cancelled | I304: cancelled | J304: 0.135698 | K304: 116.22072 | L304: to be determined [100.0%] | M304: Central Kalimantan | N304: Kalimantan Tengah
A305: Kaltim-4 Unit 1 | B305: G105496 | C305: IPP | E305: 100 | F305: 2020 | G305: operating | H305: operating | I305: operating | J305: -0.36501 | K305: 117.06505 | L305: PT Indonesia Energi Dinamika [100.0%] | M305: Central Kalimantan | N305: Kalimantan Tengah
A306: Kaltim-4 Unit 2 | B306: G105497 | C306: IPP | E306: 100 | F306: 2020 | G306: operating | H306: operating | I306: operating | J306: -0.36501 | K306: 117.06505 | L306: PT Indonesia Energi Dinamika [100.0%] | M306: Central Kalimantan | N306: Kalimantan Tengah
A307: Kaltim-6 | B307: G105500 | C307: IPP | E307: 200 | F307: 2028 | G307: cancelled | H307: cancelled | I307: cancelled | J307: 1.227 | K307: 114.577 | L307: to be determined [100.0%] | M307: 0 | N307: 0
A308: Karang Asem Unit 1 | B308: G105583 | C308: IPP | E308: 100 | F308: 0 | G308: cancelled | H308: cancelled | I308: cancelled | J308: -8.366667 | K308: 115.51667 | L308: Oceanwide Holdings Co Ltd [85.0%]; PT Satya Abadi Semesta [10.0%]; China Power International Development Co Ltd [5.0%] | M308: Bali | N308: Bali
A309: Karang Asem Unit 2 | B309: G105584 | C309: IPP | E309: 100 | F309: 0 | G309: cancelled | H309: cancelled | I309: cancelled | J309: -8.366667 | K309: 115.51667 | L309: Oceanwide Holdings Co Ltd [85.0%]; PT Satya Abadi Semesta [10.0%]; China Power International Development Co Ltd [5.0%] | M309: Bali | N309: Bali
A310: Keban Agung Unit 1 | B310: G105632 | C310: IPP | E310: 135 | F310: 2015 | G310: operating | H310: operating | I310: operating | J310: -3.75149 | K310: 103.64809 | L310: Priamanaya Djan International | M310: South Sumatra | N310: Sumatra Selatan
A311: Keban Agung Unit 2 | B311: G105633 | C311: IPP | E311: 135 | F311: 2015 | G311: operating | H311: operating | I311: operating | J311: -3.75149 | K311: 103.64809 | L311: Priamanaya Djan International | M311: South Sumatra | N311: Sumatra Selatan
A312: Kendari-3 Unit 1 | B312: G105669 | C312: IPP | E312: 50 | F312: 2019 | G312: operating | H312: operating | I312: operating | J312: -4.0512916 | K312: 122.65345 | L312: Datang Overseas Energy Investment Co Ltd [75.0%]; Sinar Mas Group [25.0%] | M312: Southeast Sulawesi | N312: Sulawesi Tenggara
A313: Kendari-3 Unit 2 | B313: G105670 | C313: IPP | E313: 50 | F313: 2019 | G313: operating | H313: operating | I313: operating | J313: -4.0512916 | K313: 122.65345 | L313: Datang Overseas Energy Investment Co Ltd [75.0%]; Sinar Mas Group [25.0%] | M313: Southeast Sulawesi | N313: Sulawesi Tenggara
A314: Komering Agung Phase III | B314: G113838 | C314: IPP | E314: 30 | F314: 0 | G314: cancelled | H314: cancelled | I314: cancelled | J314: -4.976468 | K314: 105.18568 | L314: PT Pembangunan Perumahan | M314: South Sumatra | N314: Sumatra Selatan
A315: Komering Agung Phase IV | B315: G113839 | C315: IPP | E315: 30 | F315: 0 | G315: cancelled | H315: cancelled | I315: cancelled | J315: -4.976468 | K315: 105.18568 | L315: PT Pembangunan Perumahan | M315: South Sumatra | N315: Sumatra Selatan
A316: Kuala Tanjung-1 Unit 1 | B316: G105996 | C316: IPP | E316: 135 | F316: 0 | G316: cancelled | H316: cancelled | I316: cancelled | J316: 3.386793 | K316: 99.426699 | L316: Oceanwide Holdings Co Ltd [85.0%]; PT Satya Abadi Semesta [10.0%]; China Power International Development Co Ltd [5.0%] | M316: North Sumatra | N316: Sumatra Utara
A317: Kuala Tanjung-1 Unit 2 | B317: G105997 | C317: IPP | E317: 135 | F317: 0 | G317: cancelled | H317: cancelled | I317: cancelled | J317: 3.386793 | K317: 99.426699 | L317: Oceanwide Holdings Co Ltd [85.0%]; PT Satya Abadi Semesta [10.0%]; China Power International Development Co Ltd [5.0%] | M317: North Sumatra | N317: Sumatra Utara
A318: Kuala Tanjung-2 | B318: G105998 | C318: IPP | E318: 450 | F318: 0 | G318: cancelled | H318: cancelled | I318: cancelled | J318: 3.375398 | K318: 99.441805 | L318: to be determined [100.0%] | M318: North Sumatra | N318: Sumatra Utara
A319: Lamhotma Unit 1 | B319: G106134 | C319: IPP | E319: 100 | F319: 0 | G319: cancelled | H319: cancelled | I319: cancelled | J319: 3.375398 | K319: 99.441805 | L319: Medco Energi Internasional Tbk [48.0%] | M319: North Sumatra | N319: Sumatra Utara
A320: Lamhotma Unit 2 | B320: G106135 | C320: IPP | E320: 100 | F320: 0 | G320: cancelled | H320: cancelled | I320: cancelled | J320: 3.375398 | K320: 99.441805 | L320: Medco Energi Internasional Tbk [48.0%] | M320: North Sumatra | N320: Sumatra Utara
A321: Lati Unit 1 | B321: NA | C321: IPP | E321: 7 | F321: 2004 | G321: operating | H321: operating | I321: operating | J321: 2.2149949 | K321: 117.61913 | M321: East Kalimantan | N321: Kalimantan Timur
A322: Lati Unit 2 | B322: NA | C322: IPP | E322: 7 | F322: 2004 | G322: operating | H322: operating | I322: operating | J322: 2.2149949 | K322: 117.61913 | M322: East Kalimantan | N322: Kalimantan Timur
A323: Lombok 3 Unit 1 | B323: G106386 | C323: IPP | E323: 50 | F323: 2026 | G323: cancelled | H323: cancelled | I323: cancelled | J323: -8.285204 | K323: 116.60316 | L323: to be determined [100.0%] | M323: West Nusa Tenggara | N323: Nusa Tenggara Barat
A324: Lombok 3 Unit 2 | B324: G106387 | C324: IPP | E324: 50 | F324: 2027 | G324: cancelled | H324: cancelled | I324: cancelled | J324: -8.285204 | K324: 116.60316 | L324: to be determined [100.0%] | M324: West Nusa Tenggara | N324: Nusa Tenggara Barat
A325: Lombok 4 Unit 1 | B325: G114194 | C325: IPP | E325: 50 | F325: 2028 | G325: cancelled | H325: cancelled | I325: cancelled | J325: -8.573277 | K325: 116.35112 | L325: to be determined [100.0%] | M325: West Nusa Tenggara | N325: Nusa Tenggara Barat
A326: Lombok 4 Unit 2 | B326: G114195 | C326: IPP | E326: 50 | F326: 2029 | G326: cancelled | H326: cancelled | I326: cancelled | J326: -8.573277 | K326: 116.35112 | L326: to be determined [100.0%] | M326: West Nusa Tenggara | N326: Nusa Tenggara Barat
A327: Lombok Timur Unit 1 | B327: NA | C327: IPP | E327: 25 | F327: 2017 | G327: operating | H327: operating | I327: operating | J327: -8.4349475 | K327: 116.70507 | M327: West Nusa Tenggara | N327: Nusa Tenggara Barat
A328: Lombok Timur Unit 2 | B328: NA | C328: IPP | E328: 25 | F328: 2017 | G328: operating | H328: operating | I328: operating | J328: -8.4349475 | K328: 116.70507 | M328: West Nusa Tenggara | N328: Nusa Tenggara Barat
A329: Madura PTBA Unit 1 | B329: G106545 | C329: IPP | E329: 225 | F329: 0 | G329: cancelled | H329: cancelled | I329: cancelled | J329: -7.077733 | K329: 113.28709 | L329: PT Bukit Asam [100.0%] | M329: East Java | N329: Jawa Timur
A330: Madura PTBA Unit 2 | B330: G106546 | C330: IPP | E330: 225 | F330: 0 | G330: cancelled | H330: cancelled | I330: cancelled | J330: -7.077733 | K330: 113.28709 | L330: PT Bukit Asam [100.0%] | M330: East Java | N330: Jawa Timur
...

Sheet PLN & IPP
A1: Data Source | B1: CFPP name | C1: Capacity (MW) | D1: GEM unit/phase ID | E1: GEM ID | F1: GCPT name - plant & unit | G1: Island | H1: In RUPTL 2021-2030 | I1: In RUPTL 2025-2034 | J1: Biomass Co-firing Status | K1: Biomass type | L1: Biomass share | M1: Gov. Prog. | N1: Status June 2023, JETP | O1: Status July 2024 | P1: Status July 2026 | Q1: COD | R1: COD_RUPTL 2025-2034 (Base) | S1: Retirement target | T1: Years in operation | U1: Capacity Group | V1: YO Group | W1: Owner | X1: Steam Tech. | Y1: Boiler Tech. | Z1: thermal_efficiency | AA1: Emission Control Tech. | AB1: Notes | AC1: Latitude | AD1: Longitude | AE1: Annual NOx, ton/year | AF1: Annual SOx, ton/year | AG1: Annual PMs, ton/year | AH1: Conc. NOx | AI1: Conc. SOx | AJ1: Conc. PM | AK1: Unit for gases | AL1: Hg in coal, ppb | AM1: Stack height (m) | AN1: Stack diameter (m) | AO1: Flue exit temp (℃) | AP1: Flue velocity (m/s) | AQ1: Link
A2: Priority | B2: Alor Unit 1 | C2: 3 | D2: NA | E2: NA | F2: <30 MW | G2: Nusa Tenggara | H2: Yes | J2: =iferror(vlookup(vlookup(B2,'Co-firing inputs'!B:C,2,false),'Co-firing inputs'!B:G,6,false),"None") -> None | N2: planned | O2: planned | Q2: 2025 | T2: =YEAR(today())-Q2 -> 1 | U2: =IF(AND(C2>0,C2<=100),"1",IF(AND(C2>100,C2<=300),"2",IF(AND(C2>300,C2<=600),"3",IF(AND(C2>600,C2<=1000),"4",IF(C2>1000,"5"))))) -> 1 | V2: =IF(T2<=0,"Planned",IF(AND(T2>0,T2<=5),"1",IF(AND(T2>5,T2<=10),"2",IF(AND(T2>10,T2<=15),"3",IF(AND(T2>15,T2<=20),"4",IF(AND(T2>20,T2<=25),"5",IF(AND(T2>25,T2<=30),"6",IF(AND(T2>30,T2<=35),"7",IF(AND(T2>35,T2<=40),"8",IF(T2>40,"9")))))))))) -> 1 | W2: PLN | X2: SubC | Y2: Stoker | AC2: -8.2417453 | AD2: 124.53197
B3: Alor Unit 2 | C3: 3 | D3: NA | E3: NA | F3: <30 MW | G3: Nusa Tenggara | H3: Yes | J3: =iferror(vlookup(vlookup(B3,'Co-firing inputs'!B:C,2,false),'Co-firing inputs'!B:G,6,false),"None") -> None | N3: planned | O3: planned | Q3: 2025 | T3: =YEAR(today())-Q3 -> 1 | U3: =IF(AND(C3>0,C3<=100),"1",IF(AND(C3>100,C3<=300),"2",IF(AND(C3>300,C3<=600),"3",IF(AND(C3>600,C3<=1000),"4",IF(C3>1000,"5"))))) -> 1 | V3: =IF(T3<=0,"Planned",IF(AND(T3>0,T3<=5),"1",IF(AND(T3>5,T3<=10),"2",IF(AND(T3>10,T3<=15),"3",IF(AND(T3>15,T3<=20),"4",IF(AND(T3>20,T3<=25),"5",IF(AND(T3>25,T3<=30),"6",IF(AND(T3>30,T3<=35),"7",IF(AND(T3>35,T3<=40),"8",IF(T3>40,"9")))))))))) -> 1 | W3: PLN | X3: SubC | Y3: Stoker | AC3: -8.2417453 | AD3: 124.53197
B4: Ampana Unit 1 | C4: 3 | D4: NA | E4: NA | F4: <30 MW | G4: Sulawesi | J4: Commercial/implemented | K4: Woodchip | L4: 0.05 | N4: operating | O4: operating | P4: operating | Q4: 2017 | T4: =YEAR(today())-Q4 -> 9 | U4: =IF(AND(C4>0,C4<=100),"1",IF(AND(C4>100,C4<=300),"2",IF(AND(C4>300,C4<=600),"3",IF(AND(C4>600,C4<=1000),"4",IF(C4>1000,"5"))))) -> 1 | V4: =IF(T4<=0,"Planned",IF(AND(T4>0,T4<=5),"1",IF(AND(T4>5,T4<=10),"2",IF(AND(T4>10,T4<=15),"3",IF(AND(T4>15,T4<=20),"4",IF(AND(T4>20,T4<=25),"5",IF(AND(T4>25,T4<=30),"6",IF(AND(T4>30,T4<=35),"7",IF(AND(T4>35,T4<=40),"8",IF(T4>40,"9")))))))))) -> 2 | W4: PLN | AC4: -0.96418417 | AD4: 121.82305
B5: Ampana Unit 2 | C5: 3 | D5: NA | E5: NA | F5: <30 MW | G5: Sulawesi | J5: Commercial/implemented | K5: Woodchip | L5: 0.05 | N5: operating | O5: operating | P5: operating | Q5: 2017 | T5: =YEAR(today())-Q5 -> 9 | U5: =IF(AND(C5>0,C5<=100),"1",IF(AND(C5>100,C5<=300),"2",IF(AND(C5>300,C5<=600),"3",IF(AND(C5>600,C5<=1000),"4",IF(C5>1000,"5"))))) -> 1 | V5: =IF(T5<=0,"Planned",IF(AND(T5>0,T5<=5),"1",IF(AND(T5>5,T5<=10),"2",IF(AND(T5>10,T5<=15),"3",IF(AND(T5>15,T5<=20),"4",IF(AND(T5>20,T5<=25),"5",IF(AND(T5>25,T5<=30),"6",IF(AND(T5>30,T5<=35),"7",IF(AND(T5>35,T5<=40),"8",IF(T5>40,"9")))))))))) -> 2 | W5: PLN | AC5: -0.96418417 | AD5: 121.82305
B6: Atambua Unit 1 | C6: 6 | D6: NA | E6: NA | F6: <30 MW | G6: Nusa Tenggara | H6: Yes | I6: Yes | J6: =iferror(vlookup(vlookup(B6,'Co-firing inputs'!B:C,2,false),'Co-firing inputs'!B:G,6,false),"None") -> None | N6: planned | O6: planned | Q6: 2027 | R6: 2030 | T6: =YEAR(today())-Q6 -> -1 | U6: =IF(AND(C6>0,C6<=100),"1",IF(AND(C6>100,C6<=300),"2",IF(AND(C6>300,C6<=600),"3",IF(AND(C6>600,C6<=1000),"4",IF(C6>1000,"5"))))) -> 1 | V6: =IF(T6<=0,"Planned",IF(AND(T6>0,T6<=5),"1",IF(AND(T6>5,T6<=10),"2",IF(AND(T6>10,T6<=15),"3",IF(AND(T6>15,T6<=20),"4",IF(AND(T6>20,T6<=25),"5",IF(AND(T6>25,T6<=30),"6",IF(AND(T6>30,T6<=35),"7",IF(AND(T6>35,T6<=40),"8",IF(T6>40,"9")))))))))) -> Planned | W6: PLN | X6: SubC | Y6: Stoker | AC6: -0.3730972 | AD6: 117.06246
B7: Atambua Unit 2 | C7: 6 | D7: NA | E7: NA | F7: <30 MW | G7: Nusa Tenggara | H7: Yes | I7: Yes | J7: =iferror(vlookup(vlookup(B7,'Co-firing inputs'!B:C,2,false),'Co-firing inputs'!B:G,6,false),"None") -> None | N7: planned | O7: planned | Q7: 2027 | R7: 2030 | T7: =YEAR(today())-Q7 -> -1 | U7: =IF(AND(C7>0,C7<=100),"1",IF(AND(C7>100,C7<=300),"2",IF(AND(C7>300,C7<=600),"3",IF(AND(C7>600,C7<=1000),"4",IF(C7>1000,"5"))))) -> 1 | V7: =IF(T7<=0,"Planned",IF(AND(T7>0,T7<=5),"1",IF(AND(T7>5,T7<=10),"2",IF(AND(T7>10,T7<=15),"3",IF(AND(T7>15,T7<=20),"4",IF(AND(T7>20,T7<=25),"5",IF(AND(T7>25,T7<=30),"6",IF(AND(T7>30,T7<=35),"7",IF(AND(T7>35,T7<=40),"8",IF(T7>40,"9")))))))))) -> Planned | W7: PLN | X7: SubC | Y7: Stoker | AC7: -0.3730972 | AD7: 117.06246
B8: Atambua Unit 3 | C8: 6 | D8: NA | E8: NA | F8: <30 MW | G8: Nusa Tenggara | H8: Yes | I8: Yes | J8: =iferror(vlookup(vlookup(B8,'Co-firing inputs'!B:C,2,false),'Co-firing inputs'!B:G,6,false),"None") -> None | N8: planned | O8: planned | Q8: 2027 | R8: 2030 | T8: =YEAR(today())-Q8 -> -1 | U8: =IF(AND(C8>0,C8<=100),"1",IF(AND(C8>100,C8<=300),"2",IF(AND(C8>300,C8<=600),"3",IF(AND(C8>600,C8<=1000),"4",IF(C8>1000,"5"))))) -> 1 | V8: =IF(T8<=0,"Planned",IF(AND(T8>0,T8<=5),"1",IF(AND(T8>5,T8<=10),"2",IF(AND(T8>10,T8<=15),"3",IF(AND(T8>15,T8<=20),"4",IF(AND(T8>20,T8<=25),"5",IF(AND(T8>25,T8<=30),"6",IF(AND(T8>30,T8<=35),"7",IF(AND(T8>35,T8<=40),"8",IF(T8>40,"9")))))))))) -> Planned | W8: PLN | X8: SubC | Y8: Stoker | AC8: -0.3730972 | AD8: 117.06246
B9: Atambua Unit 4 | C9: 6 | D9: NA | E9: NA | F9: <30 MW | G9: Nusa Tenggara | H9: Yes | I9: Yes | J9: =iferror(vlookup(vlookup(B9,'Co-firing inputs'!B:C,2,false),'Co-firing inputs'!B:G,6,false),"None") -> None | N9: planned | O9: planned | Q9: 2027 | R9: 2030 | T9: =YEAR(today())-Q9 -> -1 | U9: =IF(AND(C9>0,C9<=100),"1",IF(AND(C9>100,C9<=300),"2",IF(AND(C9>300,C9<=600),"3",IF(AND(C9>600,C9<=1000),"4",IF(C9>1000,"5"))))) -> 1 | V9: =IF(T9<=0,"Planned",IF(AND(T9>0,T9<=5),"1",IF(AND(T9>5,T9<=10),"2",IF(AND(T9>10,T9<=15),"3",IF(AND(T9>15,T9<=20),"4",IF(AND(T9>20,T9<=25),"5",IF(AND(T9>25,T9<=30),"6",IF(AND(T9>30,T9<=35),"7",IF(AND(T9>35,T9<=40),"8",IF(T9>40,"9")))))))))) -> Planned | W9: PLN | X9: SubC | Y9: Stoker | AC9: -0.3730972 | AD9: 117.06246
B10: Berau Unit 1 | C10: 7 | D10: NA | E10: NA | F10: <30 MW | G10: Kalimantan | J10: =iferror(vlookup(vlookup(B10,'Co-firing inputs'!B:C,2,false),'Co-firing inputs'!B:G,6,false),"None") -> Commercial/implemented | K10: Palm Kernel Shell | L10: 0.05 | N10: operating | O10: operating | P10: operating | Q10: 2020 | T10: =YEAR(today())-Q10 -> 6 | U10: =IF(AND(C10>0,C10<=100),"1",IF(AND(C10>100,C10<=300),"2",IF(AND(C10>300,C10<=600),"3",IF(AND(C10>600,C10<=1000),"4",IF(C10>1000,"5"))))) -> 1 | V10: =IF(T10<=0,"Planned",IF(AND(T10>0,T10<=5),"1",IF(AND(T10>5,T10<=10),"2",IF(AND(T10>10,T10<=15),"3",IF(AND(T10>15,T10<=20),"4",IF(AND(T10>20,T10<=25),"5",IF(AND(T10>25,T10<=30),"6",IF(AND(T10>30,T10<=35),"7",IF(AND(T10>35,T10<=40),"8",IF(T10>40,"9")))))))))) -> 2 | W10: PLN | X10: SubC | Y10: Stoker | AA10: ESP | AC10: 2.1567161 | AD10: 117.39229
B11: Berau Unit 2 | C11: 7 | D11: NA | E11: NA | F11: <30 MW | G11: Kalimantan | J11: =iferror(vlookup(vlookup(B11,'Co-firing inputs'!B:C,2,false),'Co-firing inputs'!B:G,6,false),"None") -> Commercial/implemented | K11: Palm Kernel Shell | L11: 0.05 | N11: operating | O11: operating | P11: operating | Q11: 2019 | T11: =YEAR(today())-Q11 -> 7 | U11: =IF(AND(C11>0,C11<=100),"1",IF(AND(C11>100,C11<=300),"2",IF(AND(C11>300,C11<=600),"3",IF(AND(C11>600,C11<=1000),"4",IF(C11>1000,"5"))))) -> 1 | V11: =IF(T11<=0,"Planned",IF(AND(T11>0,T11<=5),"1",IF(AND(T11>5,T11<=10),"2",IF(AND(T11>10,T11<=15),"3",IF(AND(T11>15,T11<=20),"4",IF(AND(T11>20,T11<=25),"5",IF(AND(T11>25,T11<=30),"6",IF(AND(T11>30,T11<=35),"7",IF(AND(T11>35,T11<=40),"8",IF(T11>40,"9")))))))))) -> 2 | W11: PLN | X11: SubC | Y11: Stoker | AA11: ESP | AC11: 2.1567161 | AD11: 117.39229
B12: Bima Unit 1 | C12: 10 | D12: NA | E12: NA | F12: <30 MW | G12: Nusa Tenggara | H12: Yes | J12: =iferror(vlookup(vlookup(B12,'Co-firing inputs'!B:C,2,false),'Co-firing inputs'!B:G,6,false),"None") -> None | M12: FTP-1 | N12: planned | O12: planned | Q12: 2029 | T12: =YEAR(today())-Q12 -> -3 | U12: =IF(AND(C12>0,C12<=100),"1",IF(AND(C12>100,C12<=300),"2",IF(AND(C12>300,C12<=600),"3",IF(AND(C12>600,C12<=1000),"4",IF(C12>1000,"5"))))) -> 1 | V12: =IF(T12<=0,"Planned",IF(AND(T12>0,T12<=5),"1",IF(AND(T12>5,T12<=10),"2",IF(AND(T12>10,T12<=15),"3",IF(AND(T12>15,T12<=20),"4",IF(AND(T12>20,T12<=25),"5",IF(AND(T12>25,T12<=30),"6",IF(AND(T12>30,T12<=35),"7",IF(AND(T12>35,T12<=40),"8",IF(T12>40,"9")))))))))) -> Planned | W12: PLN | X12: SubC | Y12: CFB | AC12: -8.4072501 | AD12: 118.69985
B13: Bima Unit 2 | C13: 10 | D13: NA | E13: NA | F13: <30 MW | G13: Nusa Tenggara | H13: Yes | J13: =iferror(vlookup(vlookup(B13,'Co-firing inputs'!B:C,2,false),'Co-firing inputs'!B:G,6,false),"None") -> None | M13: FTP-1 | N13: planned | O13: planned | Q13: 2029 | T13: =YEAR(today())-Q13 -> -3 | U13: =IF(AND(C13>0,C13<=100),"1",IF(AND(C13>100,C13<=300),"2",IF(AND(C13>300,C13<=600),"3",IF(AND(C13>600,C13<=1000),"4",IF(C13>1000,"5"))))) -> 1 | V13: =IF(T13<=0,"Planned",IF(AND(T13>0,T13<=5),"1",IF(AND(T13>5,T13<=10),"2",IF(AND(T13>10,T13<=15),"3",IF(AND(T13>15,T13<=20),"4",IF(AND(T13>20,T13<=25),"5",IF(AND(T13>25,T13<=30),"6",IF(AND(T13>30,T13<=35),"7",IF(AND(T13>35,T13<=40),"8",IF(T13>40,"9")))))))))) -> Planned | W13: PLN | X13: SubC | Y13: CFB | AC13: -8.4072501 | AD13: 118.69985
B14: Embalut Unit 1 | C14: 25 | D14: NA | E14: NA | F14: <30 MW | G14: Kalimantan | J14: =iferror(vlookup(vlookup(B14,'Co-firing inputs'!B:C,2,false),'Co-firing inputs'!B:G,6,false),"None") -> None | N14: operating | O14: operating | P14: operating | Q14: 2008 | T14: =YEAR(today())-Q14 -> 18 | U14: =IF(AND(C14>0,C14<=100),"1",IF(AND(C14>100,C14<=300),"2",IF(AND(C14>300,C14<=600),"3",IF(AND(C14>600,C14<=1000),"4",IF(C14>1000,"5"))))) -> 1 | V14: =IF(T14<=0,"Planned",IF(AND(T14>0,T14<=5),"1",IF(AND(T14>5,T14<=10),"2",IF(AND(T14>10,T14<=15),"3",IF(AND(T14>15,T14<=20),"4",IF(AND(T14>20,T14<=25),"5",IF(AND(T14>25,T14<=30),"6",IF(AND(T14>30,T14<=35),"7",IF(AND(T14>35,T14<=40),"8",IF(T14>40,"9")))))))))) -> 4 | W14: IPP | X14: SubC | Y14: PC | AC14: -0.3730972 | AD14: 117.06246
B15: Embalut Unit 2 | C15: 25 | D15: NA | E15: NA | F15: <30 MW | G15: Kalimantan | J15: =iferror(vlookup(vlookup(B15,'Co-firing inputs'!B:C,2,false),'Co-firing inputs'!B:G,6,false),"None") -> None | N15: operating | O15: operating | P15: operating | Q15: 2008 | T15: =YEAR(today())-Q15 -> 18 | U15: =IF(AND(C15>0,C15<=100),"1",IF(AND(C15>100,C15<=300),"2",IF(AND(C15>300,C15<=600),"3",IF(AND(C15>600,C15<=1000),"4",IF(C15>1000,"5"))))) -> 1 | V15: =IF(T15<=0,"Planned",IF(AND(T15>0,T15<=5),"1",IF(AND(T15>5,T15<=10),"2",IF(AND(T15>10,T15<=15),"3",IF(AND(T15>15,T15<=20),"4",IF(AND(T15>20,T15<=25),"5",IF(AND(T15>25,T15<=30),"6",IF(AND(T15>30,T15<=35),"7",IF(AND(T15>35,T15<=40),"8",IF(T15>40,"9")))))))))) -> 4 | W15: IPP | X15: SubC | Y15: PC | AC15: -0.3730972 | AD15: 117.06246
B16: Gorontalo Unit 1 | C16: 25 | D16: NA | E16: NA | F16: <30 MW | G16: Sulawesi | J16: =iferror(vlookup(vlookup(B16,'Co-firing inputs'!B:C,2,false),'Co-firing inputs'!B:G,6,false),"None") -> Commercial/implemented | K16: Woodchip & Sawdust | L16: 0.05 | N16: operating | O16: operating | P16: operating | Q16: 2020 | T16: =YEAR(today())-Q16 -> 6 | U16: =IF(AND(C16>0,C16<=100),"1",IF(AND(C16>100,C16<=300),"2",IF(AND(C16>300,C16<=600),"3",IF(AND(C16>600,C16<=1000),"4",IF(C16>1000,"5"))))) -> 1 | V16: =IF(T16<=0,"Planned",IF(AND(T16>0,T16<=5),"1",IF(AND(T16>5,T16<=10),"2",IF(AND(T16>10,T16<=15),"3",IF(AND(T16>15,T16<=20),"4",IF(AND(T16>20,T16<=25),"5",IF(AND(T16>25,T16<=30),"6",IF(AND(T16>30,T16<=35),"7",IF(AND(T16>35,T16<=40),"8",IF(T16>40,"9")))))))))) -> 2 | W16: PLN | X16: SubC | Y16: CFB | AA16: ESP, Cyclone, Limestone | AC16: 0.85051045 | AD16: 122.79643
B17: Gorontalo Unit 2 | C17: 25 | D17: NA | E17: NA | F17: <30 MW | G17: Sulawesi | J17: =iferror(vlookup(vlookup(B17,'Co-firing inputs'!B:C,2,false),'Co-firing inputs'!B:G,6,false),"None") -> Commercial/implemented | K17: Woodchip & Sawdust | L17: 0.05 | N17: operating | O17: operating | P17: operating | Q17: 2020 | T17: =YEAR(today())-Q17 -> 6 | U17: =IF(AND(C17>0,C17<=100),"1",IF(AND(C17>100,C17<=300),"2",IF(AND(C17>300,C17<=600),"3",IF(AND(C17>600,C17<=1000),"4",IF(C17>1000,"5"))))) -> 1 | V17: =IF(T17<=0,"Planned",IF(AND(T17>0,T17<=5),"1",IF(AND(T17>5,T17<=10),"2",IF(AND(T17>10,T17<=15),"3",IF(AND(T17>15,T17<=20),"4",IF(AND(T17>20,T17<=25),"5",IF(AND(T17>25,T17<=30),"6",IF(AND(T17>30,T17<=35),"7",IF(AND(T17>35,T17<=40),"8",IF(T17>40,"9")))))))))) -> 2 | W17: PLN | X17: SubC | Y17: CFB | AA17: ESP, Cyclone, Limestone | AC17: 0.85051045 | AD17: 122.79643
B18: Holtekamp Unit 1 | C18: 10 | D18: NA | E18: NA | F18: <30 MW | G18: Papua | J18: Commercial/implemented | K18: Woodchip | L18: NA | N18: operating | O18: operating | P18: operating | Q18: 2011 | T18: =YEAR(today())-Q18 -> 15 | U18: =IF(AND(C18>0,C18<=100),"1",IF(AND(C18>100,C18<=300),"2",IF(AND(C18>300,C18<=600),"3",IF(AND(C18>600,C18<=1000),"4",IF(C18>1000,"5"))))) -> 1 | V18: =IF(T18<=0,"Planned",IF(AND(T18>0,T18<=5),"1",IF(AND(T18>5,T18<=10),"2",IF(AND(T18>10,T18<=15),"3",IF(AND(T18>15,T18<=20),"4",IF(AND(T18>20,T18<=25),"5",IF(AND(T18>25,T18<=30),"6",IF(AND(T18>30,T18<=35),"7",IF(AND(T18>35,T18<=40),"8",IF(T18>40,"9")))))))))) -> 3 | W18: PLN | X18: SubC | Y18: Stoker | AA18: Dust Collector, Desulphuriser | AC18: -2.6143323 | AD18: 140.79049
B19: Holtekamp Unit 2 | C19: 10 | D19: NA | E19: NA | F19: <30 MW | G19: Papua | J19: Commercial/implemented | K19: Woodchip | L19: NA | N19: operating | O19: operating | P19: operating | Q19: 2011 | T19: =YEAR(today())-Q19 -> 15 | U19: =IF(AND(C19>0,C19<=100),"1",IF(AND(C19>100,C19<=300),"2",IF(AND(C19>300,C19<=600),"3",IF(AND(C19>600,C19<=1000),"4",IF(C19>1000,"5"))))) -> 1 | V19: =IF(T19<=0,"Planned",IF(AND(T19>0,T19<=5),"1",IF(AND(T19>5,T19<=10),"2",IF(AND(T19>10,T19<=15),"3",IF(AND(T19>15,T19<=20),"4",IF(AND(T19>20,T19<=25),"5",IF(AND(T19>25,T19<=30),"6",IF(AND(T19>30,T19<=35),"7",IF(AND(T19>35,T19<=40),"8",IF(T19>40,"9")))))))))) -> 3 | W19: PLN | X19: SubC | Y19: Stoker | AA19: Dust Collector, Desulphuriser | AC19: -2.6143323 | AD19: 140.79049
B20: Jeranjang Unit 1 | C20: 25 | D20: NA | E20: NA | F20: <30 MW | G20: Nusa Tenggara | J20: =iferror(vlookup(vlookup(B20,'Co-firing inputs'!B:C,2,false),'Co-firing inputs'!B:G,6,false),"None") -> Commercial/implemented | K20: Sawdust, Waste Pellet | L20: 0.03 | N20: operating | O20: operating | P20: operating | Q20: 2014 | T20: =YEAR(today())-Q20 -> 12 | U20: =IF(AND(C20>0,C20<=100),"1",IF(AND(C20>100,C20<=300),"2",IF(AND(C20>300,C20<=600),"3",IF(AND(C20>600,C20<=1000),"4",IF(C20>1000,"5"))))) -> 1 | V20: =IF(T20<=0,"Planned",IF(AND(T20>0,T20<=5),"1",IF(AND(T20>5,T20<=10),"2",IF(AND(T20>10,T20<=15),"3",IF(AND(T20>15,T20<=20),"4",IF(AND(T20>20,T20<=25),"5",IF(AND(T20>25,T20<=30),"6",IF(AND(T20>30,T20<=35),"7",IF(AND(T20>35,T20<=40),"8",IF(T20>40,"9")))))))))) -> 3 | W20: PLN | X20: SubC | Y20: CFB | AA20: ESP, Low NOx Burner | AC20: -8.6587616 | AD20: 116.07313 | AL20: 77.6
B21: Jeranjang Unit 2 | C21: 25 | D21: NA | E21: NA | F21: <30 MW | G21: Nusa Tenggara | J21: =iferror(vlookup(vlookup(B21,'Co-firing inputs'!B:C,2,false),'Co-firing inputs'!B:G,6,false),"None") -> Commercial/implemented | K21: Sawdust, Waste Pellet | L21: 0.03 | N21: operating | O21: operating | P21: operating | Q21: 2014 | T21: =YEAR(today())-Q21 -> 12 | U21: =IF(AND(C21>0,C21<=100),"1",IF(AND(C21>100,C21<=300),"2",IF(AND(C21>300,C21<=600),"3",IF(AND(C21>600,C21<=1000),"4",IF(C21>1000,"5"))))) -> 1 | V21: =IF(T21<=0,"Planned",IF(AND(T21>0,T21<=5),"1",IF(AND(T21>5,T21<=10),"2",IF(AND(T21>10,T21<=15),"3",IF(AND(T21>15,T21<=20),"4",IF(AND(T21>20,T21<=25),"5",IF(AND(T21>25,T21<=30),"6",IF(AND(T21>30,T21<=35),"7",IF(AND(T21>35,T21<=40),"8",IF(T21>40,"9")))))))))) -> 3 | W21: PLN | X21: SubC | Y21: CFB | AA21: ESP, Low NOx Burner | AC21: -8.6587616 | AD21: 116.07313 | AL21: 77.6
B22: Jeranjang Unit 3 | C22: 25 | D22: NA | E22: NA | F22: <30 MW | G22: Nusa Tenggara | J22: =iferror(vlookup(vlookup(B22,'Co-firing inputs'!B:C,2,false),'Co-firing inputs'!B:G,6,false),"None") -> Commercial/implemented | K22: Sawdust, Waste Pellet | L22: 0.03 | N22: operating | O22: operating | P22: operating | Q22: 2014 | T22: =YEAR(today())-Q22 -> 12 | U22: =IF(AND(C22>0,C22<=100),"1",IF(AND(C22>100,C22<=300),"2",IF(AND(C22>300,C22<=600),"3",IF(AND(C22>600,C22<=1000),"4",IF(C22>1000,"5"))))) -> 1 | V22: =IF(T22<=0,"Planned",IF(AND(T22>0,T22<=5),"1",IF(AND(T22>5,T22<=10),"2",IF(AND(T22>10,T22<=15),"3",IF(AND(T22>15,T22<=20),"4",IF(AND(T22>20,T22<=25),"5",IF(AND(T22>25,T22<=30),"6",IF(AND(T22>30,T22<=35),"7",IF(AND(T22>35,T22<=40),"8",IF(T22>40,"9")))))))))) -> 3 | W22: PLN | X22: SubC | Y22: CFB | AA22: ESP, Low NOx Burner | AB22: 16/8/24 - new entry, Jeranjang, 3x25MW, https://www.rri.co.id/bisnis/529070/dukung-nze-2050-pt-pba-komitmen-penuhi-biomassa-pltu-jeranjang | AC22: -8.6587616 | AD22: 116.07313 | AL22: 77.6
A23: Priority | B23: Kaltim (MT) Unit 1 | C23: 27.5 | D23: NA | E23: NA | F23: <30 MW | G23: Kalimantan | J23: =iferror(vlookup(vlookup(B23,'Co-firing inputs'!B:C,2,false),'Co-firing inputs'!B:G,6,false),"None") -> None | N23: operating | O23: operating | P23: operating | Q23: 2018 | T23: =YEAR(today())-Q23 -> 8 | U23: =IF(AND(C23>0,C23<=100),"1",IF(AND(C23>100,C23<=300),"2",IF(AND(C23>300,C23<=600),"3",IF(AND(C23>600,C23<=1000),"4",IF(C23>1000,"5"))))) -> 1 | V23: =IF(T23<=0,"Planned",IF(AND(T23>0,T23<=5),"1",IF(AND(T23>5,T23<=10),"2",IF(AND(T23>10,T23<=15),"3",IF(AND(T23>15,T23<=20),"4",IF(AND(T23>20,T23<=25),"5",IF(AND(T23>25,T23<=30),"6",IF(AND(T23>30,T23<=35),"7",IF(AND(T23>35,T23<=40),"8",IF(T23>40,"9")))))))))) -> 2 | W23: IPP | X23: SubC-MM | Y23: CFB | AB23: PLTU Muara Jawa - Kutai Kartanegara, Kalimantan Timur | AC23: -0.77860264 | AD23: 117.18886
B24: Kaltim (MT) Unit 2 | C24: 27.5 | D24: NA | E24: NA | F24: <30 MW | G24: Kalimantan | J24: =iferror(vlookup(vlookup(B24,'Co-firing inputs'!B:C,2,false),'Co-firing inputs'!B:G,6,false),"None") -> None | N24: operating | O24: operating | P24: operating | Q24: 2018 | T24: =YEAR(today())-Q24 -> 8 | U24: =IF(AND(C24>0,C24<=100),"1",IF(AND(C24>100,C24<=300),"2",IF(AND(C24>300,C24<=600),"3",IF(AND(C24>600,C24<=1000),"4",IF(C24>1000,"5"))))) -> 1 | V24: =IF(T24<=0,"Planned",IF(AND(T24>0,T24<=5),"1",IF(AND(T24>5,T24<=10),"2",IF(AND(T24>10,T24<=15),"3",IF(AND(T24>15,T24<=20),"4",IF(AND(T24>20,T24<=25),"5",IF(AND(T24>25,T24<=30),"6",IF(AND(T24>30,T24<=35),"7",IF(AND(T24>35,T24<=40),"8",IF(T24>40,"9")))))))))) -> 2 | W24: IPP | X24: SubC-MM | Y24: CFB | AB24: PLTU Muara Jawa - Kutai Kartanegara, Kalimantan Timur | AC24: -0.77860264 | AD24: 117.18886
B25: Ketapang Unit 1 | C25: 10 | D25: NA | E25: NA | F25: <30 MW | G25: Kalimantan | J25: =iferror(vlookup(vlookup(B25,'Co-firing inputs'!B:C,2,false),'Co-firing inputs'!B:G,6,false),"None") -> Commercial/implemented | K25: Palm Kernel Shell | L25: 0.05 | N25: operating | O25: operating | P25: operating | Q25: 2016 | T25: =YEAR(today())-Q25 -> 10 | U25: =IF(AND(C25>0,C25<=100),"1",IF(AND(C25>100,C25<=300),"2",IF(AND(C25>300,C25<=600),"3",IF(AND(C25>600,C25<=1000),"4",IF(C25>1000,"5"))))) -> 1 | V25: =IF(T25<=0,"Planned",IF(AND(T25>0,T25<=5),"1",IF(AND(T25>5,T25<=10),"2",IF(AND(T25>10,T25<=15),"3",IF(AND(T25>15,T25<=20),"4",IF(AND(T25>20,T25<=25),"5",IF(AND(T25>25,T25<=30),"6",IF(AND(T25>30,T25<=35),"7",IF(AND(T25>35,T25<=40),"8",IF(T25>40,"9")))))))))) -> 2 | W25: PLN | X25: SubC | Y25: CFB | AA25: ESP, Low NOx Burner, Limestone | AC25: -1.7800852 | AD25: 109.94267 | AL25: 63.4
A26: AMDAL on hand | B26: Ketapang Unit 2 | C26: 10 | D26: NA | E26: NA | F26: <30 MW | G26: Kalimantan | J26: =iferror(vlookup(vlookup(B26,'Co-firing inputs'!B:C,2,false),'Co-firing inputs'!B:G,6,false),"None") -> Commercial/implemented | K26: Palm Kernel Shell | L26: 0.05 | N26: operating | O26: operating | P26: operating | Q26: 2016 | T26: =YEAR(today())-Q26 -> 10 | U26: =IF(AND(C26>0,C26<=100),"1",IF(AND(C26>100,C26<=300),"2",IF(AND(C26>300,C26<=600),"3",IF(AND(C26>600,C26<=1000),"4",IF(C26>1000,"5"))))) -> 1 | V26: =IF(T26<=0,"Planned",IF(AND(T26>0,T26<=5),"1",IF(AND(T26>5,T26<=10),"2",IF(AND(T26>10,T26<=15),"3",IF(AND(T26>15,T26<=20),"4",IF(AND(T26>20,T26<=25),"5",IF(AND(T26>25,T26<=30),"6",IF(AND(T26>30,T26<=35),"7",IF(AND(T26>35,T26<=40),"8",IF(T26>40,"9")))))))))) -> 2 | W26: PLN | X26: SubC | Y26: CFB | AA26: ESP, Limestone | AC26: -1.7800852 | AD26: 109.94267 | AL26: 63.4
A27: AMDAL on hand | B27: Kotabaru Unit 1 | C27: 7 | D27: NA | E27: NA | F27: <30 MW | G27: Kalimantan | H27: Yes | I27: Yes | J27: =iferror(vlookup(vlookup(B27,'Co-firing inputs'!B:C,2,false),'Co-firing inputs'!B:G,6,false),"None") -> None | N27: planned | O27: planned | Q27: 2025 | R27: 2030 | T27: =YEAR(today())-Q27 -> 1 | U27: =IF(AND(C27>0,C27<=100),"1",IF(AND(C27>100,C27<=300),"2",IF(AND(C27>300,C27<=600),"3",IF(AND(C27>600,C27<=1000),"4",IF(C27>1000,"5"))))) -> 1 | V27: =IF(T27<=0,"Planned",IF(AND(T27>0,T27<=5),"1",IF(AND(T27>5,T27<=10),"2",IF(AND(T27>10,T27<=15),"3",IF(AND(T27>15,T27<=20),"4",IF(AND(T27>20,T27<=25),"5",IF(AND(T27>25,T27<=30),"6",IF(AND(T27>30,T27<=35),"7",IF(AND(T27>35,T27<=40),"8",IF(T27>40,"9")))))))))) -> 1 | W27: PLN | X27: SubC | Y27: Stoker | AC27: -3.21269 | AD27: 116.25666
B28: Kotabaru Unit 2 | C28: 7 | D28: NA | E28: NA | F28: <30 MW | G28: Kalimantan | H28: Yes | I28: Yes | J28: =iferror(vlookup(vlookup(B28,'Co-firing inputs'!B:C,2,false),'Co-firing inputs'!B:G,6,false),"None") -> None | N28: planned | O28: planned | Q28: 2025 | R28: 2030 | T28: =YEAR(today())-Q28 -> 1 | U28: =IF(AND(C28>0,C28<=100),"1",IF(AND(C28>100,C28<=300),"2",IF(AND(C28>300,C28<=600),"3",IF(AND(C28>600,C28<=1000),"4",IF(C28>1000,"5"))))) -> 1 | V28: =IF(T28<=0,"Planned",IF(AND(T28>0,T28<=5),"1",IF(AND(T28>5,T28<=10),"2",IF(AND(T28>10,T28<=15),"3",IF(AND(T28>15,T28<=20),"4",IF(AND(T28>20,T28<=25),"5",IF(AND(T28>25,T28<=30),"6",IF(AND(T28>30,T28<=35),"7",IF(AND(T28>35,T28<=40),"8",IF(T28>40,"9")))))))))) -> 1 | W28: PLN | X28: SubC | Y28: Stoker | AC28: -3.21269 | AD28: 116.25666
B29: Kupang Baru Unit 1 | C29: 15 | D29: NA | E29: NA | F29: <30 MW | G29: Nusa Tenggara | I29: Yes | J29: Commercial/implemented | K29: Woodchip | L29: 0.05 | Q29: 2025 | R29: 2025 | T29: =YEAR(today())-Q29 -> 1 | U29: =IF(AND(C29>0,C29<=100),"1",IF(AND(C29>100,C29<=300),"2",IF(AND(C29>300,C29<=600),"3",IF(AND(C29>600,C29<=1000),"4",IF(C29>1000,"5"))))) -> 1 | V29: =IF(T29<=0,"Planned",IF(AND(T29>0,T29<=5),"1",IF(AND(T29>5,T29<=10),"2",IF(AND(T29>10,T29<=15),"3",IF(AND(T29>15,T29<=20),"4",IF(AND(T29>20,T29<=25),"5",IF(AND(T29>25,T29<=30),"6",IF(AND(T29>30,T29<=35),"7",IF(AND(T29>35,T29<=40),"8",IF(T29>40,"9")))))))))) -> 1 | W29: PLN | AC29: -10.239014 | AD29: 123.49016
B30: Kupang Baru Unit 2 | C30: 15 | D30: NA | E30: NA | F30: <30 MW | G30: Nusa Tenggara | I30: Yes | J30: Commercial/implemented | K30: Woodchip | L30: 0.05 | Q30: 2025 | R30: 2025 | T30: =YEAR(today())-Q30 -> 1 | U30: =IF(AND(C30>0,C30<=100),"1",IF(AND(C30>100,C30<=300),"2",IF(AND(C30>300,C30<=600),"3",IF(AND(C30>600,C30<=1000),"4",IF(C30>1000,"5"))))) -> 1 | V30: =IF(T30<=0,"Planned",IF(AND(T30>0,T30<=5),"1",IF(AND(T30>5,T30<=10),"2",IF(AND(T30>10,T30<=15),"3",IF(AND(T30>15,T30<=20),"4",IF(AND(T30>20,T30<=25),"5",IF(AND(T30>25,T30<=30),"6",IF(AND(T30>30,T30<=35),"7",IF(AND(T30>35,T30<=40),"8",IF(T30>40,"9")))))))))) -> 1 | W30: PLN | AC30: -10.239014 | AD30: 123.49016
B31: Kupang Unit 1 | C31: 16.5 | D31: NA | E31: NA | F31: <30 MW | G31: Nusa Tenggara | J31: =iferror(vlookup(vlookup(B31,'Co-firing inputs'!B:C,2,false),'Co-firing inputs'!B:G,6,false),"None") -> Commercial/implemented | K31: Woodchip | L31: 0.05 | M31: FTP-1 | N31: operating | O31: operating | P31: operating | Q31: 2013 | T31: =YEAR(today())-Q31 -> 13 | U31: =IF(AND(C31>0,C31<=100),"1",IF(AND(C31>100,C31<=300),"2",IF(AND(C31>300,C31<=600),"3",IF(AND(C31>600,C31<=1000),"4",IF(C31>1000,"5"))))) -> 1 | V31: =IF(T31<=0,"Planned",IF(AND(T31>0,T31<=5),"1",IF(AND(T31>5,T31<=10),"2",IF(AND(T31>10,T31<=15),"3",IF(AND(T31>15,T31<=20),"4",IF(AND(T31>20,T31<=25),"5",IF(AND(T31>25,T31<=30),"6",IF(AND(T31>30,T31<=35),"7",IF(AND(T31>35,T31<=40),"8",IF(T31>40,"9")))))))))) -> 3 | W31: PLN | X31: SubC | Y31: CFB | AA31: ESP | AC31: -10.238914 | AD31: 123.49026 | AL31: 50.75
B32: Kupang Unit 2 | C32: 16.5 | D32: NA | E32: NA | F32: <30 MW | G32: Nusa Tenggara | J32: =iferror(vlookup(vlookup(B32,'Co-firing inputs'!B:C,2,false),'Co-firing inputs'!B:G,6,false),"None") -> Commercial/implemented | K32: Woodchip | L32: 0.05 | M32: FTP-1 | N32: operating | O32: operating | P32: operating | Q32: 2013 | T32: =YEAR(today())-Q32 -> 13 | U32: =IF(AND(C32>0,C32<=100),"1",IF(AND(C32>100,C32<=300),"2",IF(AND(C32>300,C32<=600),"3",IF(AND(C32>600,C32<=1000),"4",IF(C32>1000,"5"))))) -> 1 | V32: =IF(T32<=0,"Planned",IF(AND(T32>0,T32<=5),"1",IF(AND(T32>5,T32<=10),"2",IF(AND(T32>10,T32<=15),"3",IF(AND(T32>15,T32<=20),"4",IF(AND(T32>20,T32<=25),"5",IF(AND(T32>25,T32<=30),"6",IF(AND(T32>30,T32<=35),"7",IF(AND(T32>35,T32<=40),"8",IF(T32>40,"9")))))))))) -> 3 | W32: PLN | X32: SubC | Y32: CFB | AA32: ESP | AC32: -10.238914 | AD32: 123.49026 | AL32: 50.75
B33: Lati Unit 1 | C33: 7 | D33: NA | E33: NA | F33: <30 MW | G33: Kalimantan | J33: =iferror(vlookup(vlookup(B33,'Co-firing inputs'!B:C,2,false),'Co-firing inputs'!B:G,6,false),"None") -> None | N33: operating | O33: operating | P33: operating | Q33: 2004 | T33: =YEAR(today())-Q33 -> 22 | U33: =IF(AND(C33>0,C33<=100),"1",IF(AND(C33>100,C33<=300),"2",IF(AND(C33>300,C33<=600),"3",IF(AND(C33>600,C33<=1000),"4",IF(C33>1000,"5"))))) -> 1 | V33: =IF(T33<=0,"Planned",IF(AND(T33>0,T33<=5),"1",IF(AND(T33>5,T33<=10),"2",IF(AND(T33>10,T33<=15),"3",IF(AND(T33>15,T33<=20),"4",IF(AND(T33>20,T33<=25),"5",IF(AND(T33>25,T33<=30),"6",IF(AND(T33>30,T33<=35),"7",IF(AND(T33>35,T33<=40),"8",IF(T33>40,"9")))))))))) -> 5 | W33: IPP | X33: SubC | Y33: Stoker | AC33: 2.2149949 | AD33: 117.61913
B34: Lati Unit 2 | C34: 7 | D34: NA | E34: NA | F34: <30 MW | G34: Kalimantan | J34: =iferror(vlookup(vlookup(B34,'Co-firing inputs'!B:C,2,false),'Co-firing inputs'!B:G,6,false),"None") -> None | N34: operating | O34: operating | P34: operating | Q34: 2004 | T34: =YEAR(today())-Q34 -> 22 | U34: =IF(AND(C34>0,C34<=100),"1",IF(AND(C34>100,C34<=300),"2",IF(AND(C34>300,C34<=600),"3",IF(AND(C34>600,C34<=1000),"4",IF(C34>1000,"5"))))) -> 1 | V34: =IF(T34<=0,"Planned",IF(AND(T34>0,T34<=5),"1",IF(AND(T34>5,T34<=10),"2",IF(AND(T34>10,T34<=15),"3",IF(AND(T34>15,T34<=20),"4",IF(AND(T34>20,T34<=25),"5",IF(AND(T34>25,T34<=30),"6",IF(AND(T34>30,T34<=35),"7",IF(AND(T34>35,T34<=40),"8",IF(T34>40,"9")))))))))) -> 5 | W34: IPP | X34: SubC | Y34: Stoker | AC34: 2.2149949 | AD34: 117.61913
B35: Lati Unit 3 | C35: 7 | D35: NA | E35: NA | F35: <30 MW | G35: Kalimantan | J35: =iferror(vlookup(vlookup(B35,'Co-firing inputs'!B:C,2,false),'Co-firing inputs'!B:G,6,false),"None") -> None | N35: operating | O35: operating | P35: operating | Q35: 2004 | T35: =YEAR(today())-Q35 -> 22 | U35: =IF(AND(C35>0,C35<=100),"1",IF(AND(C35>100,C35<=300),"2",IF(AND(C35>300,C35<=600),"3",IF(AND(C35>600,C35<=1000),"4",IF(C35>1000,"5"))))) -> 1 | V35: =IF(T35<=0,"Planned",IF(AND(T35>0,T35<=5),"1",IF(AND(T35>5,T35<=10),"2",IF(AND(T35>10,T35<=15),"3",IF(AND(T35>15,T35<=20),"4",IF(AND(T35>20,T35<=25),"5",IF(AND(T35>25,T35<=30),"6",IF(AND(T35>30,T35<=35),"7",IF(AND(T35>35,T35<=40),"8",IF(T35>40,"9")))))))))) -> 5 | W35: IPP | X35: SubC | Y35: Stoker | AC35: 2.2149949 | AD35: 117.61913
A36: AMDAL on hand | B36: Lombok Timur Unit 1 | C36: 25 | D36: NA | E36: NA | F36: <30 MW | G36: Nusa Tenggara | J36: =iferror(vlookup(vlookup(B36,'Co-firing inputs'!B:C,2,false),'Co-firing inputs'!B:G,6,false),"None") -> None | N36: operating | O36: operating | P36: operating | Q36: 2017 | T36: =YEAR(today())-Q36 -> 9 | U36: =IF(AND(C36>0,C36<=100),"1",IF(AND(C36>100,C36<=300),"2",IF(AND(C36>300,C36<=600),"3",IF(AND(C36>600,C36<=1000),"4",IF(C36>1000,"5"))))) -> 1 | V36: =IF(T36<=0,"Planned",IF(AND(T36>0,T36<=5),"1",IF(AND(T36>5,T36<=10),"2",IF(AND(T36>10,T36<=15),"3",IF(AND(T36>15,T36<=20),"4",IF(AND(T36>20,T36<=25),"5",IF(AND(T36>25,T36<=30),"6",IF(AND(T36>30,T36<=35),"7",IF(AND(T36>35,T36<=40),"8",IF(T36>40,"9")))))))))) -> 2 | W36: IPP | X36: SubC | Y36: CFB | AB36: Location: Desa Padak Guar, Kelurahan Labuan Pandan, Kecamatan Sambelia, Kabupaten Lombok Timur, Provinsi Nusa Tenggara Barat | AC36: -8.4349475 | AD36: 116.70507 | AQ36: https://web.pln.co.id/cms/media/siaran-pers/2013/07/pln-tandatangani-perjanjian-jual-beli-listrik-pltu-lombok-timur-dengan-pt-lombok-energy-dynamics/
A37: AMDAL on hand | B37: Lombok Timur Unit 2 | C37: 25 | D37: NA | E37: NA | F37: <30 MW | G37: Nusa Tenggara | J37: =iferror(vlookup(vlookup(B37,'Co-firing inputs'!B:C,2,false),'Co-firing inputs'!B:G,6,false),"None") -> None | N37: operating | O37: operating | P37: operating | Q37: 2017 | T37: =YEAR(today())-Q37 -> 9 | U37: =IF(AND(C37>0,C37<=100),"1",IF(AND(C37>100,C37<=300),"2",IF(AND(C37>300,C37<=600),"3",IF(AND(C37>600,C37<=1000),"4",IF(C37>1000,"5"))))) -> 1 | V37: =IF(T37<=0,"Planned",IF(AND(T37>0,T37<=5),"1",IF(AND(T37>5,T37<=10),"2",IF(AND(T37>10,T37<=15),"3",IF(AND(T37>15,T37<=20),"4",IF(AND(T37>20,T37<=25),"5",IF(AND(T37>25,T37<=30),"6",IF(AND(T37>30,T37<=35),"7",IF(AND(T37>35,T37<=40),"8",IF(T37>40,"9")))))))))) -> 2 | W37: IPP | X37: SubC | Y37: CFB | AB37: Location: Desa Padak Guar, Kelurahan Labuan Pandan, Kecamatan Sambelia, Kabupaten Lombok Timur, Provinsi Nusa Tenggara Barat | AC37: -8.4349475 | AD37: 116.70507
A38: AMDAL on hand | B38: Malinau Unit 1 | C38: 3 | D38: NA | E38: NA | F38: <30 MW | G38: Kalimantan | H38: Yes | J38: Commercial/implemented | K38: Palm Kernel Shell | L38: NA | N38: construction | O38: operating | P38: operating | Q38: 2021 | T38: =YEAR(today())-Q38 -> 5 | U38: =IF(AND(C38>0,C38<=100),"1",IF(AND(C38>100,C38<=300),"2",IF(AND(C38>300,C38<=600),"3",IF(AND(C38>600,C38<=1000),"4",IF(C38>1000,"5"))))) -> 1 | V38: =IF(T38<=0,"Planned",IF(AND(T38>0,T38<=5),"1",IF(AND(T38>5,T38<=10),"2",IF(AND(T38>10,T38<=15),"3",IF(AND(T38>15,T38<=20),"4",IF(AND(T38>20,T38<=25),"5",IF(AND(T38>25,T38<=30),"6",IF(AND(T38>30,T38<=35),"7",IF(AND(T38>35,T38<=40),"8",IF(T38>40,"9")))))))))) -> 1 | W38: PLN | X38: SubC | Y38: Stoker | AC38: 3.6363153 | AD38: 116.67169
B39: Malinau Unit 2 | C39: 3 | D39: NA | E39: NA | F39: <30 MW | G39: Kalimantan | H39: Yes | J39: Commercial/implemented | K39: Palm Kernel Shell | L39: NA | N39: construction | O39: operating | P39: operating | Q39: 2021 | T39: =YEAR(today())-Q39 -> 5 | U39: =IF(AND(C39>0,C39<=100),"1",IF(AND(C39>100,C39<=300),"2",IF(AND(C39>300,C39<=600),"3",IF(AND(C39>600,C39<=1000),"4",IF(C39>1000,"5"))))) -> 1 | V39: =IF(T39<=0,"Planned",IF(AND(T39>0,T39<=5),"1",IF(AND(T39>5,T39<=10),"2",IF(AND(T39>10,T39<=15),"3",IF(AND(T39>15,T39<=20),"4",IF(AND(T39>20,T39<=25),"5",IF(AND(T39>25,T39<=30),"6",IF(AND(T39>30,T39<=35),"7",IF(AND(T39>35,T39<=40),"8",IF(T39>40,"9")))))))))) -> 1 | W39: PLN | X39: SubC | Y39: Stoker | AC39: 3.6363153 | AD39: 116.67169
B40: Mamuju Unit 1 | C40: 25 | D40: NA | E40: NA | F40: <30 MW | G40: Sulawesi | J40: =iferror(vlookup(vlookup(B40,'Co-firing inputs'!B:C,2,false),'Co-firing inputs'!B:G,6,false),"None") -> None | N40: operating | O40: operating | P40: operating | Q40: 2018 | T40: =YEAR(today())-Q40 -> 8 | U40: =IF(AND(C40>0,C40<=100),"1",IF(AND(C40>100,C40<=300),"2",IF(AND(C40>300,C40<=600),"3",IF(AND(C40>600,C40<=1000),"4",IF(C40>1000,"5"))))) -> 1 | V40: =IF(T40<=0,"Planned",IF(AND(T40>0,T40<=5),"1",IF(AND(T40>5,T40<=10),"2",IF(AND(T40>10,T40<=15),"3",IF(AND(T40>15,T40<=20),"4",IF(AND(T40>20,T40<=25),"5",IF(AND(T40>25,T40<=30),"6",IF(AND(T40>30,T40<=35),"7",IF(AND(T40>35,T40<=40),"8",IF(T40>40,"9")))))))))) -> 2 | W40: IPP | X40: SubC | Y40: CFB | AC40: -2.4724046 | AD40: 119.14687
A41: AMDAL on hand | B41: Mamuju Unit 2 | C41: 25 | D41: NA | E41: NA | F41: <30 MW | G41: Sulawesi | J41: =iferror(vlookup(vlookup(B41,'Co-firing inputs'!B:C,2,false),'Co-firing inputs'!B:G,6,false),"None") -> None | N41: operating | O41: operating | P41: operating | Q41: 2018 | T41: =YEAR(today())-Q41 -> 8 | U41: =IF(AND(C41>0,C41<=100),"1",IF(AND(C41>100,C41<=300),"2",IF(AND(C41>300,C41<=600),"3",IF(AND(C41>600,C41<=1000),"4",IF(C41>1000,"5"))))) -> 1 | V41: =IF(T41<=0,"Planned",IF(AND(T41>0,T41<=5),"1",IF(AND(T41>5,T41<=10),"2",IF(AND(T41>10,T41<=15),"3",IF(AND(T41>15,T41<=20),"4",IF(AND(T41>20,T41<=25),"5",IF(AND(T41>25,T41<=30),"6",IF(AND(T41>30,T41<=35),"7",IF(AND(T41>35,T41<=40),"8",IF(T41>40,"9")))))))))) -> 2 | W41: IPP | X41: SubC | Y41: CFB | AC41: -2.4724046 | AD41: 119.14687
A42: AMDAL on hand | B42: Molotabu Unit 1 | C42: 10 | D42: NA | E42: NA | F42: <30 MW | G42: Sulawesi | J42: =iferror(vlookup(vlookup(B42,'Co-firing inputs'!B:C,2,false),'Co-firing inputs'!B:G,6,false),"None") -> None | N42: operating | O42: operating | P42: operating | Q42: 2013 | T42: =YEAR(today())-Q42 -> 13 | U42: =IF(AND(C42>0,C42<=100),"1",IF(AND(C42>100,C42<=300),"2",IF(AND(C42>300,C42<=600),"3",IF(AND(C42>600,C42<=1000),"4",IF(C42>1000,"5"))))) -> 1 | V42: =IF(T42<=0,"Planned",IF(AND(T42>0,T42<=5),"1",IF(AND(T42>5,T42<=10),"2",IF(AND(T42>10,T42<=15),"3",IF(AND(T42>15,T42<=20),"4",IF(AND(T42>20,T42<=25),"5",IF(AND(T42>25,T42<=30),"6",IF(AND(T42>30,T42<=35),"7",IF(AND(T42>35,T42<=40),"8",IF(T42>40,"9")))))))))) -> 3 | W42: PLN | X42: SubC | Y42: CFB | AA42: ESP, Low NOx Burner | AC42: 0.43402912 | AD42: 123.13407
A43: AMDAL on hand | B43: Molotabu Unit 2 | C43: 10 | D43: NA | E43: NA | F43: <30 MW | G43: Sulawesi | J43: =iferror(vlookup(vlookup(B43,'Co-firing inputs'!B:C,2,false),'Co-firing inputs'!B:G,6,false),"None") -> None | N43: operating | O43: operating | P43: operating | Q43: 2013 | T43: =YEAR(today())-Q43 -> 13 | U43: =IF(AND(C43>0,C43<=100),"1",IF(AND(C43>100,C43<=300),"2",IF(AND(C43>300,C43<=600),"3",IF(AND(C43>600,C43<=1000),"4",IF(C43>1000,"5"))))) -> 1 | V43: =IF(T43<=0,"Planned",IF(AND(T43>0,T43<=5),"1",IF(AND(T43>5,T43<=10),"2",IF(AND(T43>10,T43<=15),"3",IF(AND(T43>15,T43<=20),"4",IF(AND(T43>20,T43<=25),"5",IF(AND(T43>25,T43<=30),"6",IF(AND(T43>30,T43<=35),"7",IF(AND(T43>35,T43<=40),"8",IF(T43>40,"9")))))))))) -> 3 | W43: PLN | X43: SubC | Y43: CFB | AC43: 0.43402912 | AD43: 123.13407
A44: AMDAL on hand | B44: Nabire-Kalibobo Unit 1 | C44: 7 | D44: NA | E44: NA | F44: <30 MW | G44: Papua | H44: Yes | J44: =iferror(vlookup(vlookup(B44,'Co-firing inputs'!B:C,2,false),'Co-firing inputs'!B:G,6,false),"None") -> None | N44: construction | O44: operating | P44: operating | Q44: 2022 | T44: =YEAR(today())-Q44 -> 4 | U44: =IF(AND(C44>0,C44<=100),"1",IF(AND(C44>100,C44<=300),"2",IF(AND(C44>300,C44<=600),"3",IF(AND(C44>600,C44<=1000),"4",IF(C44>1000,"5"))))) -> 1 | V44: =IF(T44<=0,"Planned",IF(AND(T44>0,T44<=5),"1",IF(AND(T44>5,T44<=10),"2",IF(AND(T44>10,T44<=15),"3",IF(AND(T44>15,T44<=20),"4",IF(AND(T44>20,T44<=25),"5",IF(AND(T44>25,T44<=30),"6",IF(AND(T44>30,T44<=35),"7",IF(AND(T44>35,T44<=40),"8",IF(T44>40,"9")))))))))) -> 1 | W44: IPP | X44: SubC | Y44: Stoker | AC44: -3.3796544 | AD44: 135.45687
B45: Nabire-Kalibobo Unit 2 | C45: 7 | D45: NA | E45: NA | F45: <30 MW | G45: Papua | H45: Yes | J45: =iferror(vlookup(vlookup(B45,'Co-firing inputs'!B:C,2,false),'Co-firing inputs'!B:G,6,false),"None") -> None | N45: construction | O45: operating | P45: operating | Q45: 2022 | T45: =YEAR(today())-Q45 -> 4 | U45: =IF(AND(C45>0,C45<=100),"1",IF(AND(C45>100,C45<=300),"2",IF(AND(C45>300,C45<=600),"3",IF(AND(C45>600,C45<=1000),"4",IF(C45>1000,"5"))))) -> 1 | V45: =IF(T45<=0,"Planned",IF(AND(T45>0,T45<=5),"1",IF(AND(T45>5,T45<=10),"2",IF(AND(T45>10,T45<=15),"3",IF(AND(T45>15,T45<=20),"4",IF(AND(T45>20,T45<=25),"5",IF(AND(T45>25,T45<=30),"6",IF(AND(T45>30,T45<=35),"7",IF(AND(T45>35,T45<=40),"8",IF(T45>40,"9")))))))))) -> 1 | W45: IPP | X45: SubC | Y45: Stoker | AC45: -3.3796544 | AD45: 135.45687
B46: Nii Tanasa Unit 1 | C46: 10 | D46: NA | E46: NA | F46: <30 MW | G46: Sulawesi | J46: =iferror(vlookup(vlookup(B46,'Co-firing inputs'!B:C,2,false),'Co-firing inputs'!B:G,6,false),"None") -> Commercial/implemented | K46: Palm Kernel Shell | L46: NA | N46: operating | O46: operating | P46: operating | Q46: 2014 | T46: =YEAR(today())-Q46 -> 12 | U46: =IF(AND(C46>0,C46<=100),"1",IF(AND(C46>100,C46<=300),"2",IF(AND(C46>300,C46<=600),"3",IF(AND(C46>600,C46<=1000),"4",IF(C46>1000,"5"))))) -> 1 | V46: =IF(T46<=0,"Planned",IF(AND(T46>0,T46<=5),"1",IF(AND(T46>5,T46<=10),"2",IF(AND(T46>10,T46<=15),"3",IF(AND(T46>15,T46<=20),"4",IF(AND(T46>20,T46<=25),"5",IF(AND(T46>25,T46<=30),"6",IF(AND(T46>30,T46<=35),"7",IF(AND(T46>35,T46<=40),"8",IF(T46>40,"9")))))))))) -> 3 | W46: PLN | X46: SubC | Y46: Stoker | AA46: ESP | AC46: -3.8962396 | AD46: 122.53781
B47: Nii Tanasa Unit 2 | C47: 10 | D47: NA | E47: NA | F47: <30 MW | G47: Sulawesi | J47: =iferror(vlookup(vlookup(B47,'Co-firing inputs'!B:C,2,false),'Co-firing inputs'!B:G,6,false),"None") -> Commercial/implemented | K47: Palm Kernel Shell | L47: NA | N47: operating | O47: operating | P47: operating | Q47: 2012 | T47: =YEAR(today())-Q47 -> 14 | U47: =IF(AND(C47>0,C47<=100),"1",IF(AND(C47>100,C47<=300),"2",IF(AND(C47>300,C47<=600),"3",IF(AND(C47>600,C47<=1000),"4",IF(C47>1000,"5"))))) -> 1 | V47: =IF(T47<=0,"Planned",IF(AND(T47>0,T47<=5),"1",IF(AND(T47>5,T47<=10),"2",IF(AND(T47>10,T47<=15),"3",IF(AND(T47>15,T47<=20),"4",IF(AND(T47>20,T47<=25),"5",IF(AND(T47>25,T47<=30),"6",IF(AND(T47>30,T47<=35),"7",IF(AND(T47>35,T47<=40),"8",IF(T47>40,"9")))))))))) -> 3 | W47: PLN | X47: SubC | Y47: Stoker | AA47: ESP | AC47: -3.8962396 | AD47: 122.53781
B48: Nii Tanasa Unit 3 | C48: 10 | D48: NA | E48: NA | F48: <30 MW | G48: Sulawesi | J48: =iferror(vlookup(vlookup(B48,'Co-firing inputs'!B:C,2,false),'Co-firing inputs'!B:G,6,false),"None") -> Commercial/implemented | K48: Palm Kernel Shell | L48: NA | N48: operating | O48: operating | P48: operating | Q48: 2012 | T48: =YEAR(today())-Q48 -> 14 | U48: =IF(AND(C48>0,C48<=100),"1",IF(AND(C48>100,C48<=300),"2",IF(AND(C48>300,C48<=600),"3",IF(AND(C48>600,C48<=1000),"4",IF(C48>1000,"5"))))) -> 1 | V48: =IF(T48<=0,"Planned",IF(AND(T48>0,T48<=5),"1",IF(AND(T48>5,T48<=10),"2",IF(AND(T48>10,T48<=15),"3",IF(AND(T48>15,T48<=20),"4",IF(AND(T48>20,T48<=25),"5",IF(AND(T48>25,T48<=30),"6",IF(AND(T48>30,T48<=35),"7",IF(AND(T48>35,T48<=40),"8",IF(T48>40,"9")))))))))) -> 3 | W48: PLN | X48: SubC | Y48: Stoker | AA48: ESP | AC48: -3.8962396 | AD48: 122.53781
B49: Palu Unit 1 | C49: 15 | D49: NA | E49: NA | F49: <30 MW | G49: Sulawesi | J49: =iferror(vlookup(vlookup(B49,'Co-firing inputs'!B:C,2,false),'Co-firing inputs'!B:G,6,false),"None") -> None | N49: operating | O49: operating | P49: operating | Q49: 2006 | T49: =YEAR(today())-Q49 -> 20 | U49: =IF(AND(C49>0,C49<=100),"1",IF(AND(C49>100,C49<=300),"2",IF(AND(C49>300,C49<=600),"3",IF(AND(C49>600,C49<=1000),"4",IF(C49>1000,"5"))))) -> 1 | V49: =IF(T49<=0,"Planned",IF(AND(T49>0,T49<=5),"1",IF(AND(T49>5,T49<=10),"2",IF(AND(T49>10,T49<=15),"3",IF(AND(T49>15,T49<=20),"4",IF(AND(T49>20,T49<=25),"5",IF(AND(T49>25,T49<=30),"6",IF(AND(T49>30,T49<=35),"7",IF(AND(T49>35,T49<=40),"8",IF(T49>40,"9")))))))))) -> 4 | W49: PLN | X49: SubC | Y49: CFB | AA49: ESP | AC49: -0.7332027 | AD49: 119.85592
B50: Palu Unit 2 | C50: 15 | D50: NA | E50: NA | F50: <30 MW | G50: Sulawesi | J50: =iferror(vlookup(vlookup(B50,'Co-firing inputs'!B:C,2,false),'Co-firing inputs'!B:G,6,false),"None") -> None | N50: operating | O50: operating | P50: operating | Q50: 2006 | T50: =YEAR(today())-Q50 -> 20 | U50: =IF(AND(C50>0,C50<=100),"1",IF(AND(C50>100,C50<=300),"2",IF(AND(C50>300,C50<=600),"3",IF(AND(C50>600,C50<=1000),"4",IF(C50>1000,"5"))))) -> 1 | V50: =IF(T50<=0,"Planned",IF(AND(T50>0,T50<=5),"1",IF(AND(T50>5,T50<=10),"2",IF(AND(T50>10,T50<=15),"3",IF(AND(T50>15,T50<=20),"4",IF(AND(T50>20,T50<=25),"5",IF(AND(T50>25,T50<=30),"6",IF(AND(T50>30,T50<=35),"7",IF(AND(T50>35,T50<=40),"8",IF(T50>40,"9")))))))))) -> 4 | W50: PLN | X50: SubC | Y50: CFB | AA50: ESP | AC50: -0.7332027 | AD50: 119.85592
B51: Palu Unit 3 | C51: 18 | D51: NA | E51: NA | F51: <30 MW | G51: Sulawesi | J51: =iferror(vlookup(vlookup(B51,'Co-firing inputs'!B:C,2,false),'Co-firing inputs'!B:G,6,false),"None") -> None | N51: operating | O51: operating | P51: operating | Q51: 2016 | T51: =YEAR(today())-Q51 -> 10 | U51: =IF(AND(C51>0,C51<=100),"1",IF(AND(C51>100,C51<=300),"2",IF(AND(C51>300,C51<=600),"3",IF(AND(C51>600,C51<=1000),"4",IF(C51>1000,"5"))))) -> 1 | V51: =IF(T51<=0,"Planned",IF(AND(T51>0,T51<=5),"1",IF(AND(T51>5,T51<=10),"2",IF(AND(T51>10,T51<=15),"3",IF(AND(T51>15,T51<=20),"4",IF(AND(T51>20,T51<=25),"5",IF(AND(T51>25,T51<=30),"6",IF(AND(T51>30,T51<=35),"7",IF(AND(T51>35,T51<=40),"8",IF(T51>40,"9")))))))))) -> 2 | W51: PLN | X51: SubC | Y51: CFB | AA51: ESP | AC51: -0.7332027 | AD51: 119.85592
A52: AMDAL on hand | B52: Palu Unit 4 | C52: 18 | D52: NA | E52: NA | F52: <30 MW | G52: Sulawesi | J52: =iferror(vlookup(vlookup(B52,'Co-firing inputs'!B:C,2,false),'Co-firing inputs'!B:G,6,false),"None") -> None | N52: operating | O52: operating | P52: operating | Q52: 2016 | T52: =YEAR(today())-Q52 -> 10 | U52: =IF(AND(C52>0,C52<=100),"1",IF(AND(C52>100,C52<=300),"2",IF(AND(C52>300,C52<=600),"3",IF(AND(C52>600,C52<=1000),"4",IF(C52>1000,"5"))))) -> 1 | V52: =IF(T52<=0,"Planned",IF(AND(T52>0,T52<=5),"1",IF(AND(T52>5,T52<=10),"2",IF(AND(T52>10,T52<=15),"3",IF(AND(T52>15,T52<=20),"4",IF(AND(T52>20,T52<=25),"5",IF(AND(T52>25,T52<=30),"6",IF(AND(T52>30,T52<=35),"7",IF(AND(T52>35,T52<=40),"8",IF(T52>40,"9")))))))))) -> 2 | W52: PLN | X52: SubC | Y52: CFB | AA52: ESP | AC52: -0.7332027 | AD52: 119.85592
A53: AMDAL on hand | B53: Pantai Kura-Kura Unit 1 | C53: 27.5 | D53: NA | E53: NA | F53: <30 MW | G53: Kalimantan | H53: Yes | I53: Yes | J53: =iferror(vlookup(vlookup(B53,'Co-firing inputs'!B:C,2,false),'Co-firing inputs'!B:G,6,false),"None") -> None | M53: FTP-1 | N53: planned | O53: planned | Q53: 2025 | R53: 2030 | T53: =YEAR(today())-Q53 -> 1 | U53: =IF(AND(C53>0,C53<=100),"1",IF(AND(C53>100,C53<=300),"2",IF(AND(C53>300,C53<=600),"3",IF(AND(C53>600,C53<=1000),"4",IF(C53>1000,"5"))))) -> 1 | V53: =IF(T53<=0,"Planned",IF(AND(T53>0,T53<=5),"1",IF(AND(T53>5,T53<=10),"2",IF(AND(T53>10,T53<=15),"3",IF(AND(T53>15,T53<=20),"4",IF(AND(T53>20,T53<=25),"5",IF(AND(T53>25,T53<=30),"6",IF(AND(T53>30,T53<=35),"7",IF(AND(T53>35,T53<=40),"8",IF(T53>40,"9")))))))))) -> 1 | W53: PLN | X53: SubC | Y53: CFB | AC53: 0.8296542 | AD53: 108.86409
A54: AMDAL on hand | B54: Pantai Kura-Kura Unit 2 | C54: 27.5 | D54: NA | E54: NA | F54: <30 MW | G54: Kalimantan | H54: Yes | I54: Yes | J54: =iferror(vlookup(vlookup(B54,'Co-firing inputs'!B:C,2,false),'Co-firing inputs'!B:G,6,false),"None") -> None | M54: FTP-1 | N54: planned | O54: planned | Q54: 2025 | R54: 2030 | T54: =YEAR(today())-Q54 -> 1 | U54: =IF(AND(C54>0,C54<=100),"1",IF(AND(C54>100,C54<=300),"2",IF(AND(C54>300,C54<=600),"3",IF(AND(C54>600,C54<=1000),"4",IF(C54>1000,"5"))))) -> 1 | V54: =IF(T54<=0,"Planned",IF(AND(T54>0,T54<=5),"1",IF(AND(T54>5,T54<=10),"2",IF(AND(T54>10,T54<=15),"3",IF(AND(T54>15,T54<=20),"4",IF(AND(T54>20,T54<=25),"5",IF(AND(T54>25,T54<=30),"6",IF(AND(T54>30,T54<=35),"7",IF(AND(T54>35,T54<=40),"8",IF(T54>40,"9")))))))))) -> 1 | W54: PLN | X54: SubC | Y54: CFB | AC54: 0.8296542 | AD54: 108.86409
B55: Ropa Unit 1 | C55: 7 | D55: NA | E55: NA | F55: <30 MW | G55: Nusa Tenggara | J55: =iferror(vlookup(vlookup(B55,'Co-firing inputs'!B:C,2,false),'Co-firing inputs'!B:G,6,false),"None") -> Commercial/implemented | K55: RDF Pellet | L55: 0.1 | N55: operating | O55: operating | P55: operating | Q55: 2014 | T55: =YEAR(today())-Q55 -> 12 | U55: =IF(AND(C55>0,C55<=100),"1",IF(AND(C55>100,C55<=300),"2",IF(AND(C55>300,C55<=600),"3",IF(AND(C55>600,C55<=1000),"4",IF(C55>1000,"5"))))) -> 1 | V55: =IF(T55<=0,"Planned",IF(AND(T55>0,T55<=5),"1",IF(AND(T55>5,T55<=10),"2",IF(AND(T55>10,T55<=15),"3",IF(AND(T55>15,T55<=20),"4",IF(AND(T55>20,T55<=25),"5",IF(AND(T55>25,T55<=30),"6",IF(AND(T55>30,T55<=35),"7",IF(AND(T55>35,T55<=40),"8",IF(T55>40,"9")))))))))) -> 3 | W55: PLN | X55: SubC | Y55: Stoker | AA55: ESP | AC55: -8.5086 | AD55: 121.70134 | AL55: 53.94
A56: CREA estimates available | B56: Ropa Unit 2 | C56: 7 | D56: NA | E56: NA | F56: <30 MW | G56: Nusa Tenggara | J56: =iferror(vlookup(vlookup(B56,'Co-firing inputs'!B:C,2,false),'Co-firing inputs'!B:G,6,false),"None") -> Commercial/implemented | K56: RDF Pellet | L56: 0.1 | N56: operating | O56: operating | P56: operating | Q56: 2014 | T56: =YEAR(today())-Q56 -> 12 | U56: =IF(AND(C56>0,C56<=100),"1",IF(AND(C56>100,C56<=300),"2",IF(AND(C56>300,C56<=600),"3",IF(AND(C56>600,C56<=1000),"4",IF(C56>1000,"5"))))) -> 1 | V56: =IF(T56<=0,"Planned",IF(AND(T56>0,T56<=5),"1",IF(AND(T56>5,T56<=10),"2",IF(AND(T56>10,T56<=15),"3",IF(AND(T56>15,T56<=20),"4",IF(AND(T56>20,T56<=25),"5",IF(AND(T56>25,T56<=30),"6",IF(AND(T56>30,T56<=35),"7",IF(AND(T56>35,T56<=40),"8",IF(T56>40,"9")))))))))) -> 3 | W56: PLN | X56: SubC | Y56: Stoker | AA56: ESP | AC56: -8.5086 | AD56: 121.70134 | AL56: 53.94
A57: CREA estimates available | B57: Rote Ndao Unit 1 | C57: 3 | D57: NA | E57: NA | F57: <30 MW | G57: Nusa Tenggara | H57: Yes | J57: =iferror(vlookup(vlookup(B57,'Co-firing inputs'!B:C,2,false),'Co-firing inputs'!B:G,6,false),"None") -> None | N57: planned | O57: planned | Q57: 2025 | T57: =YEAR(today())-Q57 -> 1 | U57: =IF(AND(C57>0,C57<=100),"1",IF(AND(C57>100,C57<=300),"2",IF(AND(C57>300,C57<=600),"3",IF(AND(C57>600,C57<=1000),"4",IF(C57>1000,"5"))))) -> 1 | V57: =IF(T57<=0,"Planned",IF(AND(T57>0,T57<=5),"1",IF(AND(T57>5,T57<=10),"2",IF(AND(T57>10,T57<=15),"3",IF(AND(T57>15,T57<=20),"4",IF(AND(T57>20,T57<=25),"5",IF(AND(T57>25,T57<=30),"6",IF(AND(T57>30,T57<=35),"7",IF(AND(T57>35,T57<=40),"8",IF(T57>40,"9")))))))))) -> 1 | W57: PLN | X57: SubC | Y57: Stoker | AC57: -10.671419 | AD57: 123.10879
A58: CREA estimates available | B58: Rote Ndao Unit 2 | C58: 3 | D58: NA | E58: NA | F58: <30 MW | G58: Nusa Tenggara | H58: Yes | J58: =iferror(vlookup(vlookup(B58,'Co-firing inputs'!B:C,2,false),'Co-firing inputs'!B:G,6,false),"None") -> None | N58: planned | O58: planned | Q58: 2025 | T58: =YEAR(today())-Q58 -> 1 | U58: =IF(AND(C58>0,C58<=100),"1",IF(AND(C58>100,C58<=300),"2",IF(AND(C58>300,C58<=600),"3",IF(AND(C58>600,C58<=1000),"4",IF(C58>1000,"5"))))) -> 1 | V58: =IF(T58<=0,"Planned",IF(AND(T58>0,T58<=5),"1",IF(AND(T58>5,T58<=10),"2",IF(AND(T58>10,T58<=15),"3",IF(AND(T58>15,T58<=20),"4",IF(AND(T58>20,T58<=25),"5",IF(AND(T58>25,T58<=30),"6",IF(AND(T58>30,T58<=35),"7",IF(AND(T58>35,T58<=40),"8",IF(T58>40,"9")))))))))) -> 1 | W58: PLN | X58: SubC | Y58: Stoker | AC58: -10.671419 | AD58: 123.10879
A59: CREA estimates available | B59: Sampit Unit 1 | C59: 25 | D59: NA | E59: NA | F59: <30 MW | G59: Kalimantan | H59: Yes | I59: Yes | J59: =iferror(vlookup(vlookup(B59,'Co-firing inputs'!B:C,2,false),'Co-firing inputs'!B:G,6,false),"None") -> None | N59: planned | O59: planned | Q59: 2025 | R59: 2030 | T59: =YEAR(today())-Q59 -> 1 | U59: =IF(AND(C59>0,C59<=100),"1",IF(AND(C59>100,C59<=300),"2",IF(AND(C59>300,C59<=600),"3",IF(AND(C59>600,C59<=1000),"4",IF(C59>1000,"5"))))) -> 1 | V59: =IF(T59<=0,"Planned",IF(AND(T59>0,T59<=5),"1",IF(AND(T59>5,T59<=10),"2",IF(AND(T59>10,T59<=15),"3",IF(AND(T59>15,T59<=20),"4",IF(AND(T59>20,T59<=25),"5",IF(AND(T59>25,T59<=30),"6",IF(AND(T59>30,T59<=35),"7",IF(AND(T59>35,T59<=40),"8",IF(T59>40,"9")))))))))) -> 1 | W59: PLN | X59: SubC | Y59: CFB | AC59: -2.7622791 | AD59: 112.90636
A60: Emissions Data available https://drive.google.com/drive/folders/18ffuFwBob8eZuk9B8MAWvkthY3IicOq8 | B60: Sampit Unit 2 | C60: 25 | D60: NA | E60: NA | F60: <30 MW | G60: Kalimantan | H60: Yes | I60: Yes | J60: =iferror(vlookup(vlookup(B60,'Co-firing inputs'!B:C,2,false),'Co-firing inputs'!B:G,6,false),"None") -> None | N60: planned | O60: planned | Q60: 2025 | R60: 2030 | T60: =YEAR(today())-Q60 -> 1 | U60: =IF(AND(C60>0,C60<=100),"1",IF(AND(C60>100,C60<=300),"2",IF(AND(C60>300,C60<=600),"3",IF(AND(C60>600,C60<=1000),"4",IF(C60>1000,"5"))))) -> 1 | V60: =IF(T60<=0,"Planned",IF(AND(T60>0,T60<=5),"1",IF(AND(T60>5,T60<=10),"2",IF(AND(T60>10,T60<=15),"3",IF(AND(T60>15,T60<=20),"4",IF(AND(T60>20,T60<=25),"5",IF(AND(T60>25,T60<=30),"6",IF(AND(T60>30,T60<=35),"7",IF(AND(T60>35,T60<=40),"8",IF(T60>40,"9")))))))))) -> 1 | W60: PLN | X60: SubC | Y60: CFB | AC60: -2.7622791 | AD60: 112.90636
A61: Emissions Data available https://drive.google.com/drive/folders/18ffuFwBob8eZuk9B8MAWvkthY3IicOq8 | B61: Sanggau Unit 1 | C61: 7 | D61: NA | E61: NA | F61: <30 MW | G61: Kalimantan | J61: =iferror(vlookup(vlookup(B61,'Co-firing inputs'!B:C,2,false),'Co-firing inputs'!B:G,6,false),"None") -> Commercial/implemented | K61: Palm Kernel Shell | L61: 0.05 | N61: operating | O61: operating | P61: operating | Q61: 2014 | T61: =YEAR(today())-Q61 -> 12 | U61: =IF(AND(C61>0,C61<=100),"1",IF(AND(C61>100,C61<=300),"2",IF(AND(C61>300,C61<=600),"3",IF(AND(C61>600,C61<=1000),"4",IF(C61>1000,"5"))))) -> 1 | V61: =IF(T61<=0,"Planned",IF(AND(T61>0,T61<=5),"1",IF(AND(T61>5,T61<=10),"2",IF(AND(T61>10,T61<=15),"3",IF(AND(T61>15,T61<=20),"4",IF(AND(T61>20,T61<=25),"5",IF(AND(T61>25,T61<=30),"6",IF(AND(T61>30,T61<=35),"7",IF(AND(T61>35,T61<=40),"8",IF(T61>40,"9")))))))))) -> 3 | W61: PLN | X61: SubC | Y61: Stoker | AA61: ESP, Limestone, Bag Filter | AC61: 0.030709665 | AD61: 110.55554
A62: AMDAL on hand | B62: Sanggau Unit 2 | C62: 7 | D62: NA | E62: NA | F62: <30 MW | G62: Kalimantan | J62: =iferror(vlookup(vlookup(B62,'Co-firing inputs'!B:C,2,false),'Co-firing inputs'!B:G,6,false),"None") -> Commercial/implemented | K62: Palm Kernel Shell | L62: 0.05 | N62: operating | O62: operating | P62: operating | Q62: 2014 | T62: =YEAR(today())-Q62 -> 12 | U62: =IF(AND(C62>0,C62<=100),"1",IF(AND(C62>100,C62<=300),"2",IF(AND(C62>300,C62<=600),"3",IF(AND(C62>600,C62<=1000),"4",IF(C62>1000,"5"))))) -> 1 | V62: =IF(T62<=0,"Planned",IF(AND(T62>0,T62<=5),"1",IF(AND(T62>5,T62<=10),"2",IF(AND(T62>10,T62<=15),"3",IF(AND(T62>15,T62<=20),"4",IF(AND(T62>20,T62<=25),"5",IF(AND(T62>25,T62<=30),"6",IF(AND(T62>30,T62<=35),"7",IF(AND(T62>35,T62<=40),"8",IF(T62>40,"9")))))))))) -> 3 | W62: PLN | X62: SubC | Y62: Stoker | AA62: ESP, Limestone | AC62: 0.030709665 | AD62: 110.55554
A63: CREA estimates available | B63: Sintang Unit 1 | C63: 7 | D63: NA | E63: NA | F63: <30 MW | G63: Kalimantan | J63: =iferror(vlookup(vlookup(B63,'Co-firing inputs'!B:C,2,false),'Co-firing inputs'!B:G,6,false),"None") -> Commercial/implemented | K63: Palm Kernel Shell | L63: 0.05 | N63: operating | O63: operating | P63: operating | Q63: 2018 | T63: =YEAR(today())-Q63 -> 8 | U63: =IF(AND(C63>0,C63<=100),"1",IF(AND(C63>100,C63<=300),"2",IF(AND(C63>300,C63<=600),"3",IF(AND(C63>600,C63<=1000),"4",IF(C63>1000,"5"))))) -> 1 | V63: =IF(T63<=0,"Planned",IF(AND(T63>0,T63<=5),"1",IF(AND(T63>5,T63<=10),"2",IF(AND(T63>10,T63<=15),"3",IF(AND(T63>15,T63<=20),"4",IF(AND(T63>20,T63<=25),"5",IF(AND(T63>25,T63<=30),"6",IF(AND(T63>30,T63<=35),"7",IF(AND(T63>35,T63<=40),"8",IF(T63>40,"9")))))))))) -> 2 | W63: PLN | X63: SubC | Y63: Stoker | AA63: ESP, Limestone | AC63: 0.074256594 | AD63: 111.43399
A64: Priority | B64: Sintang Unit 2 | C64: 7 | D64: NA | E64: NA | F64: <30 MW | G64: Kalimantan | J64: =iferror(vlookup(vlookup(B64,'Co-firing inputs'!B:C,2,false),'Co-firing inputs'!B:G,6,false),"None") -> Commercial/implemented | K64: Palm Kernel Shell | L64: 0.05 | N64: operating | O64: operating | P64: operating | Q64: 2018 | T64: =YEAR(today())-Q64 -> 8 | U64: =IF(AND(C64>0,C64<=100),"1",IF(AND(C64>100,C64<=300),"2",IF(AND(C64>300,C64<=600),"3",IF(AND(C64>600,C64<=1000),"4",IF(C64>1000,"5"))))) -> 1 | V64: =IF(T64<=0,"Planned",IF(AND(T64>0,T64<=5),"1",IF(AND(T64>5,T64<=10),"2",IF(AND(T64>10,T64<=15),"3",IF(AND(T64>15,T64<=20),"4",IF(AND(T64>20,T64<=25),"5",IF(AND(T64>25,T64<=30),"6",IF(AND(T64>30,T64<=35),"7",IF(AND(T64>35,T64<=40),"8",IF(T64>40,"9")))))))))) -> 2 | W64: PLN | X64: SubC | Y64: Stoker | AA64: ESP, Limestone | AC64: 0.074256594 | AD64: 111.43399
A65: Priority | B65: Sintang Unit 3 | C65: 7 | D65: NA | E65: NA | F65: <30 MW | G65: Kalimantan | J65: =iferror(vlookup(vlookup(B65,'Co-firing inputs'!B:C,2,false),'Co-firing inputs'!B:G,6,false),"None") -> Commercial/implemented | K65: Palm Kernel Shell | L65: 0.05 | N65: operating | O65: operating | P65: operating | Q65: 2018 | T65: =YEAR(today())-Q65 -> 8 | U65: =IF(AND(C65>0,C65<=100),"1",IF(AND(C65>100,C65<=300),"2",IF(AND(C65>300,C65<=600),"3",IF(AND(C65>600,C65<=1000),"4",IF(C65>1000,"5"))))) -> 1 | V65: =IF(T65<=0,"Planned",IF(AND(T65>0,T65<=5),"1",IF(AND(T65>5,T65<=10),"2",IF(AND(T65>10,T65<=15),"3",IF(AND(T65>15,T65<=20),"4",IF(AND(T65>20,T65<=25),"5",IF(AND(T65>25,T65<=30),"6",IF(AND(T65>30,T65<=35),"7",IF(AND(T65>35,T65<=40),"8",IF(T65>40,"9")))))))))) -> 2 | W65: PLN | X65: SubC | Y65: Stoker | AA65: ESP, Limestone | AC65: 0.074256594 | AD65: 111.43399
A66: AMDAL on hand | B66: Sofifi Unit 1 | C66: 3 | D66: NA | E66: NA | F66: <30 MW | G66: North Maluku | H66: Yes | I66: Yes | J66: =iferror(vlookup(vlookup(B66,'Co-firing inputs'!B:C,2,false),'Co-firing inputs'!B:G,6,false),"None") -> Planned | N66: operating | O66: operating | P66: operating | Q66: 2023 | R66: 2025 | T66: =YEAR(today())-Q66 -> 3 | U66: =IF(AND(C66>0,C66<=100),"1",IF(AND(C66>100,C66<=300),"2",IF(AND(C66>300,C66<=600),"3",IF(AND(C66>600,C66<=1000),"4",IF(C66>1000,"5"))))) -> 1 | V66: =IF(T66<=0,"Planned",IF(AND(T66>0,T66<=5),"1",IF(AND(T66>5,T66<=10),"2",IF(AND(T66>10,T66<=15),"3",IF(AND(T66>15,T66<=20),"4",IF(AND(T66>20,T66<=25),"5",IF(AND(T66>25,T66<=30),"6",IF(AND(T66>30,T66<=35),"7",IF(AND(T66>35,T66<=40),"8",IF(T66>40,"9")))))))))) -> 1 | W66: PLN | X66: SubC | Y66: Stoker | AC66: 0.64966938 | AD66: 127.54129
A67: AMDAL on hand | B67: Sofifi Unit 2 | C67: 3 | D67: NA | E67: NA | F67: <30 MW | G67: North Maluku | H67: Yes | I67: Yes | J67: =iferror(vlookup(vlookup(B67,'Co-firing inputs'!B:C,2,false),'Co-firing inputs'!B:G,6,false),"None") -> Planned | N67: operating | O67: operating | P67: operating | Q67: 2023 | R67: 2025 | T67: =YEAR(today())-Q67 -> 3 | U67: =IF(AND(C67>0,C67<=100),"1",IF(AND(C67>100,C67<=300),"2",IF(AND(C67>300,C67<=600),"3",IF(AND(C67>600,C67<=1000),"4",IF(C67>1000,"5"))))) -> 1 | V67: =IF(T67<=0,"Planned",IF(AND(T67>0,T67<=5),"1",IF(AND(T67>5,T67<=10),"2",IF(AND(T67>10,T67<=15),"3",IF(AND(T67>15,T67<=20),"4",IF(AND(T67>20,T67<=25),"5",IF(AND(T67>25,T67<=30),"6",IF(AND(T67>30,T67<=35),"7",IF(AND(T67>35,T67<=40),"8",IF(T67>40,"9")))))))))) -> 1 | W67: PLN | X67: SubC | Y67: Stoker | AC67: 0.64966938 | AD67: 127.54129
A68: Priority | B68: Sorong Unit 1 | C68: 7 | D68: NA | E68: NA | F68: <30 MW | G68: Papua | H68: Yes | I68: Yes | J68: =iferror(vlookup(vlookup(B68,'Co-firing inputs'!B:C,2,false),'Co-firing inputs'!B:G,6,false),"None") -> None | N68: planned | O68: operating | P68: operating | Q68: 2023 | R68: 2025 | T68: =YEAR(today())-Q68 -> 3 | U68: =IF(AND(C68>0,C68<=100),"1",IF(AND(C68>100,C68<=300),"2",IF(AND(C68>300,C68<=600),"3",IF(AND(C68>600,C68<=1000),"4",IF(C68>1000,"5"))))) -> 1 | V68: =IF(T68<=0,"Planned",IF(AND(T68>0,T68<=5),"1",IF(AND(T68>5,T68<=10),"2",IF(AND(T68>10,T68<=15),"3",IF(AND(T68>15,T68<=20),"4",IF(AND(T68>20,T68<=25),"5",IF(AND(T68>25,T68<=30),"6",IF(AND(T68>30,T68<=35),"7",IF(AND(T68>35,T68<=40),"8",IF(T68>40,"9")))))))))) -> 1 | W68: PLN | X68: SubC | Y68: Stoker | AC68: -1.0194764 | AD68: 131.24935
A69: Priority | B69: Sorong Unit 2 | C69: 7 | D69: NA | E69: NA | F69: <30 MW | G69: Papua | H69: Yes | I69: Yes | J69: =iferror(vlookup(vlookup(B69,'Co-firing inputs'!B:C,2,false),'Co-firing inputs'!B:G,6,false),"None") -> None | N69: planned | O69: operating | P69: operating | Q69: 2023 | R69: 2025 | T69: =YEAR(today())-Q69 -> 3 | U69: =IF(AND(C69>0,C69<=100),"1",IF(AND(C69>100,C69<=300),"2",IF(AND(C69>300,C69<=600),"3",IF(AND(C69>600,C69<=1000),"4",IF(C69>1000,"5"))))) -> 1 | V69: =IF(T69<=0,"Planned",IF(AND(T69>0,T69<=5),"1",IF(AND(T69>5,T69<=10),"2",IF(AND(T69>10,T69<=15),"3",IF(AND(T69>15,T69<=20),"4",IF(AND(T69>20,T69<=25),"5",IF(AND(T69>25,T69<=30),"6",IF(AND(T69>30,T69<=35),"7",IF(AND(T69>35,T69<=40),"8",IF(T69>40,"9")))))))))) -> 1 | W69: PLN | X69: SubC | Y69: Stoker | AC69: -1.0194764 | AD69: 131.24935
A70: Priority | B70: Sorong Unit 3 | C70: 7 | D70: NA | E70: NA | F70: <30 MW | G70: Papua | H70: Yes | I70: Yes | J70: =iferror(vlookup(vlookup(B70,'Co-firing inputs'!B:C,2,false),'Co-firing inputs'!B:G,6,false),"None") -> None | N70: planned | O70: operating | P70: operating | Q70: 2023 | R70: 2026 | T70: =YEAR(today())-Q70 -> 3 | U70: =IF(AND(C70>0,C70<=100),"1",IF(AND(C70>100,C70<=300),"2",IF(AND(C70>300,C70<=600),"3",IF(AND(C70>600,C70<=1000),"4",IF(C70>1000,"5"))))) -> 1 | V70: =IF(T70<=0,"Planned",IF(AND(T70>0,T70<=5),"1",IF(AND(T70>5,T70<=10),"2",IF(AND(T70>10,T70<=15),"3",IF(AND(T70>15,T70<=20),"4",IF(AND(T70>20,T70<=25),"5",IF(AND(T70>25,T70<=30),"6",IF(AND(T70>30,T70<=35),"7",IF(AND(T70>35,T70<=40),"8",IF(T70>40,"9")))))))))) -> 1 | W70: PLN | X70: SubC | Y70: Stoker | AC70: -1.0194764 | AD70: 131.24935
A71: CREA estimates available | B71: Sorong Unit 4 | C71: 7 | D71: NA | E71: NA | F71: <30 MW | G71: Papua | H71: Yes | I71: Yes | J71: =iferror(vlookup(vlookup(B71,'Co-firing inputs'!B:C,2,false),'Co-firing inputs'!B:G,6,false),"None") -> None | N71: planned | O71: operating | P71: operating | Q71: 2023 | R71: 2026 | T71: =YEAR(today())-Q71 -> 3 | U71: =IF(AND(C71>0,C71<=100),"1",IF(AND(C71>100,C71<=300),"2",IF(AND(C71>300,C71<=600),"3",IF(AND(C71>600,C71<=1000),"4",IF(C71>1000,"5"))))) -> 1 | V71: =IF(T71<=0,"Planned",IF(AND(T71>0,T71<=5),"1",IF(AND(T71>5,T71<=10),"2",IF(AND(T71>10,T71<=15),"3",IF(AND(T71>15,T71<=20),"4",IF(AND(T71>20,T71<=25),"5",IF(AND(T71>25,T71<=30),"6",IF(AND(T71>30,T71<=35),"7",IF(AND(T71>35,T71<=40),"8",IF(T71>40,"9")))))))))) -> 1 | W71: PLN | X71: SubC | Y71: Stoker | AC71: -1.0194764 | AD71: 131.24935
B72: Suge Unit 1 | C72: 16.5 | D72: NA | E72: NA | F72: <30 MW | G72: Sumatra | J72: =iferror(vlookup(vlookup(B72,'Co-firing inputs'!B:C,2,false),'Co-firing inputs'!B:G,6,false),"None") -> Commercial/implemented | K72: Palm Kernel Shell | L72: 0.05 | N72: operating | O72: operating | P72: operating | Q72: 2015 | T72: =YEAR(today())-Q72 -> 11 | U72: =IF(AND(C72>0,C72<=100),"1",IF(AND(C72>100,C72<=300),"2",IF(AND(C72>300,C72<=600),"3",IF(AND(C72>600,C72<=1000),"4",IF(C72>1000,"5"))))) -> 1 | V72: =IF(T72<=0,"Planned",IF(AND(T72>0,T72<=5),"1",IF(AND(T72>5,T72<=10),"2",IF(AND(T72>10,T72<=15),"3",IF(AND(T72>15,T72<=20),"4",IF(AND(T72>20,T72<=25),"5",IF(AND(T72>25,T72<=30),"6",IF(AND(T72>30,T72<=35),"7",IF(AND(T72>35,T72<=40),"8",IF(T72>40,"9")))))))))) -> 3 | W72: PLN | X72: SubC | Y72: CFB | AA72: ESP, Low NOx Burner | AC72: -2.8921441 | AD72: 107.56467
B73: Suge Unit 2 | C73: 16.5 | D73: NA | E73: NA | F73: <30 MW | G73: Sumatra | J73: =iferror(vlookup(vlookup(B73,'Co-firing inputs'!B:C,2,false),'Co-firing inputs'!B:G,6,false),"None") -> Commercial/implemented | K73: Palm Kernel Shell | L73: 0.05 | N73: operating | O73: operating | P73: operating | Q73: 2015 | T73: =YEAR(today())-Q73 -> 11 | U73: =IF(AND(C73>0,C73<=100),"1",IF(AND(C73>100,C73<=300),"2",IF(AND(C73>300,C73<=600),"3",IF(AND(C73>600,C73<=1000),"4",IF(C73>1000,"5"))))) -> 1 | V73: =IF(T73<=0,"Planned",IF(AND(T73>0,T73<=5),"1",IF(AND(T73>5,T73<=10),"2",IF(AND(T73>10,T73<=15),"3",IF(AND(T73>15,T73<=20),"4",IF(AND(T73>20,T73<=25),"5",IF(AND(T73>25,T73<=30),"6",IF(AND(T73>30,T73<=35),"7",IF(AND(T73>35,T73<=40),"8",IF(T73>40,"9")))))))))) -> 3 | W73: PLN | X73: SubC | Y73: CFB | AA73: ESP | AC73: -2.8921441 | AD73: 107.56467
B74: Sumbawa Barat Unit 1 | C74: 7 | D74: NA | E74: NA | F74: <30 MW | G74: Nusa Tenggara | J74: =iferror(vlookup(vlookup(B74,'Co-firing inputs'!B:C,2,false),'Co-firing inputs'!B:G,6,false),"None") -> Commercial/implemented | K74: Corncob | L74: 0.03 | N74: operating | O74: operating | P74: operating | Q74: 2019 | T74: =YEAR(today())-Q74 -> 7 | U74: =IF(AND(C74>0,C74<=100),"1",IF(AND(C74>100,C74<=300),"2",IF(AND(C74>300,C74<=600),"3",IF(AND(C74>600,C74<=1000),"4",IF(C74>1000,"5"))))) -> 1 | V74: =IF(T74<=0,"Planned",IF(AND(T74>0,T74<=5),"1",IF(AND(T74>5,T74<=10),"2",IF(AND(T74>10,T74<=15),"3",IF(AND(T74>15,T74<=20),"4",IF(AND(T74>20,T74<=25),"5",IF(AND(T74>25,T74<=30),"6",IF(AND(T74>30,T74<=35),"7",IF(AND(T74>35,T74<=40),"8",IF(T74>40,"9")))))))))) -> 2 | W74: PLN | X74: SubC | Y74: Stoker | AA74: ESP | AC74: -8.7420955 | AD74: 116.77689
B75: Sumbawa Barat Unit 2 | C75: 7 | D75: NA | E75: NA | F75: <30 MW | G75: Nusa Tenggara | J75: =iferror(vlookup(vlookup(B75,'Co-firing inputs'!B:C,2,false),'Co-firing inputs'!B:G,6,false),"None") -> Commercial/implemented | K75: Corncob | L75: 0.03 | N75: operating | O75: operating | P75: operating | Q75: 2019 | T75: =YEAR(today())-Q75 -> 7 | U75: =IF(AND(C75>0,C75<=100),"1",IF(AND(C75>100,C75<=300),"2",IF(AND(C75>300,C75<=600),"3",IF(AND(C75>600,C75<=1000),"4",IF(C75>1000,"5"))))) -> 1 | V75: =IF(T75<=0,"Planned",IF(AND(T75>0,T75<=5),"1",IF(AND(T75>5,T75<=10),"2",IF(AND(T75>10,T75<=15),"3",IF(AND(T75>15,T75<=20),"4",IF(AND(T75>20,T75<=25),"5",IF(AND(T75>25,T75<=30),"6",IF(AND(T75>30,T75<=35),"7",IF(AND(T75>35,T75<=40),"8",IF(T75>40,"9")))))))))) -> 2 | W75: PLN | X75: SubC | Y75: Stoker | AA75: ESP | AC75: -8.7420955 | AD75: 116.77689
B76: Talaud Unit 1 | C76: 3 | D76: NA | E76: NA | F76: <30 MW | G76: Sulawesi | H76: Yes | J76: =iferror(vlookup(vlookup(B76,'Co-firing inputs'!B:C,2,false),'Co-firing inputs'!B:G,6,false),"None") -> None | N76: operating | O76: operating | P76: operating | Q76: 2022 | T76: =YEAR(today())-Q76 -> 4 | U76: =IF(AND(C76>0,C76<=100),"1",IF(AND(C76>100,C76<=300),"2",IF(AND(C76>300,C76<=600),"3",IF(AND(C76>600,C76<=1000),"4",IF(C76>1000,"5"))))) -> 1 | V76: =IF(T76<=0,"Planned",IF(AND(T76>0,T76<=5),"1",IF(AND(T76>5,T76<=10),"2",IF(AND(T76>10,T76<=15),"3",IF(AND(T76>15,T76<=20),"4",IF(AND(T76>20,T76<=25),"5",IF(AND(T76>25,T76<=30),"6",IF(AND(T76>30,T76<=35),"7",IF(AND(T76>35,T76<=40),"8",IF(T76>40,"9")))))))))) -> 1 | W76: PLN | X76: SubC | Y76: Stoker | AC76: 4.0754239 | AD76: 126.69763
B77: Talaud Unit 2 | C77: 3 | D77: NA | E77: NA | F77: <30 MW | G77: Sulawesi | H77: Yes | J77: =iferror(vlookup(vlookup(B77,'Co-firing inputs'!B:C,2,false),'Co-firing inputs'!B:G,6,false),"None") -> None | N77: operating | O77: operating | P77: operating | Q77: 2022 | T77: =YEAR(today())-Q77 -> 4 | U77: =IF(AND(C77>0,C77<=100),"1",IF(AND(C77>100,C77<=300),"2",IF(AND(C77>300,C77<=600),"3",IF(AND(C77>600,C77<=1000),"4",IF(C77>1000,"5"))))) -> 1 | V77: =IF(T77<=0,"Planned",IF(AND(T77>0,T77<=5),"1",IF(AND(T77>5,T77<=10),"2",IF(AND(T77>10,T77<=15),"3",IF(AND(T77>15,T77<=20),"4",IF(AND(T77>20,T77<=25),"5",IF(AND(T77>25,T77<=30),"6",IF(AND(T77>30,T77<=35),"7",IF(AND(T77>35,T77<=40),"8",IF(T77>40,"9")))))))))) -> 1 | W77: PLN | X77: SubC | Y77: Stoker | AC77: 4.0754239 | AD77: 126.69763
B78: Tanah Grogot Unit 1 | C78: 7 | D78: NA | E78: NA | F78: <30 MW | G78: Kalimantan | H78: Yes | I78: Yes | J78: =iferror(vlookup(vlookup(B78,'Co-firing inputs'!B:C,2,false),'Co-firing inputs'!B:G,6,false),"None") -> None | N78: operating | O78: operating | P78: operating | Q78: 2023 | R78: 2030 | T78: =YEAR(today())-Q78 -> 3 | U78: =IF(AND(C78>0,C78<=100),"1",IF(AND(C78>100,C78<=300),"2",IF(AND(C78>300,C78<=600),"3",IF(AND(C78>600,C78<=1000),"4",IF(C78>1000,"5"))))) -> 1 | V78: =IF(T78<=0,"Planned",IF(AND(T78>0,T78<=5),"1",IF(AND(T78>5,T78<=10),"2",IF(AND(T78>10,T78<=15),"3",IF(AND(T78>15,T78<=20),"4",IF(AND(T78>20,T78<=25),"5",IF(AND(T78>25,T78<=30),"6",IF(AND(T78>30,T78<=35),"7",IF(AND(T78>35,T78<=40),"8",IF(T78>40,"9")))))))))) -> 1 | W78: PLN | X78: SubC | Y78: Stoker | AC78: -1.8163468 | AD78: 116.19327
B79: Tanah Grogot Unit 2 | C79: 7 | D79: NA | E79: NA | F79: <30 MW | G79: Kalimantan | H79: Yes | I79: Yes | J79: =iferror(vlookup(vlookup(B79,'Co-firing inputs'!B:C,2,false),'Co-firing inputs'!B:G,6,false),"None") -> None | N79: operating | O79: operating | P79: operating | Q79: 2023 | R79: 2030 | T79: =YEAR(today())-Q79 -> 3 | U79: =IF(AND(C79>0,C79<=100),"1",IF(AND(C79>100,C79<=300),"2",IF(AND(C79>300,C79<=600),"3",IF(AND(C79>600,C79<=1000),"4",IF(C79>1000,"5"))))) -> 1 | V79: =IF(T79<=0,"Planned",IF(AND(T79>0,T79<=5),"1",IF(AND(T79>5,T79<=10),"2",IF(AND(T79>10,T79<=15),"3",IF(AND(T79>15,T79<=20),"4",IF(AND(T79>20,T79<=25),"5",IF(AND(T79>25,T79<=30),"6",IF(AND(T79>30,T79<=35),"7",IF(AND(T79>35,T79<=40),"8",IF(T79>40,"9")))))))))) -> 1 | W79: PLN | X79: SubC | Y79: Stoker | AC79: -1.8163468 | AD79: 116.19327
B80: Tanjung Balai Karimun Unit 1 | C80: 7 | D80: NA | E80: NA | F80: <30 MW | G80: Sumatra | J80: Commercial/implemented | K80: Woodchip | L80: NA | N80: operating | O80: operating | P80: operating | Q80: 2014 | T80: =YEAR(today())-Q80 -> 12 | U80: =IF(AND(C80>0,C80<=100),"1",IF(AND(C80>100,C80<=300),"2",IF(AND(C80>300,C80<=600),"3",IF(AND(C80>600,C80<=1000),"4",IF(C80>1000,"5"))))) -> 1 | V80: =IF(T80<=0,"Planned",IF(AND(T80>0,T80<=5),"1",IF(AND(T80>5,T80<=10),"2",IF(AND(T80>10,T80<=15),"3",IF(AND(T80>15,T80<=20),"4",IF(AND(T80>20,T80<=25),"5",IF(AND(T80>25,T80<=30),"6",IF(AND(T80>30,T80<=35),"7",IF(AND(T80>35,T80<=40),"8",IF(T80>40,"9")))))))))) -> 3 | W80: PLN | X80: SubC | Y80: Stoker | AA80: Low NOx Burner, Multicyclone | AC80: 1.0453389 | AD80: 103.41054 | AL80: 59.1
B81: Tanjung Balai Karimun Unit 2 | C81: 7 | D81: NA | E81: NA | F81: <30 MW | G81: Sumatra | J81: Commercial/implemented | K81: Woodchip | L81: NA | N81: operating | O81: operating | P81: operating | Q81: 2013 | T81: =YEAR(today())-Q81 -> 13 | U81: =IF(AND(C81>0,C81<=100),"1",IF(AND(C81>100,C81<=300),"2",IF(AND(C81>300,C81<=600),"3",IF(AND(C81>600,C81<=1000),"4",IF(C81>1000,"5"))))) -> 1 | V81: =IF(T81<=0,"Planned",IF(AND(T81>0,T81<=5),"1",IF(AND(T81>5,T81<=10),"2",IF(AND(T81>10,T81<=15),"3",IF(AND(T81>15,T81<=20),"4",IF(AND(T81>20,T81<=25),"5",IF(AND(T81>25,T81<=30),"6",IF(AND(T81>30,T81<=35),"7",IF(AND(T81>35,T81<=40),"8",IF(T81>40,"9")))))))))) -> 3 | W81: PLN | X81: SubC | Y81: Stoker | AA81: Low NOx Burner, Multicyclone | AC81: 1.0453389 | AD81: 103.41054 | AL81: 59.1
B82: Tanjung Selor Unit 1 | C82: 7 | D82: NA | E82: NA | F82: <30 MW | G82: Kalimantan | H82: Yes | I82: Yes | J82: =iferror(vlookup(vlookup(B82,'Co-firing inputs'!B:C,2,false),'Co-firing inputs'!B:G,6,false),"None") -> None | O82: operating | P82: operating | Q82: 2023 | R82: 2030 | T82: =YEAR(today())-Q82 -> 3 | U82: =IF(AND(C82>0,C82<=100),"1",IF(AND(C82>100,C82<=300),"2",IF(AND(C82>300,C82<=600),"3",IF(AND(C82>600,C82<=1000),"4",IF(C82>1000,"5"))))) -> 1 | V82: =IF(T82<=0,"Planned",IF(AND(T82>0,T82<=5),"1",IF(AND(T82>5,T82<=10),"2",IF(AND(T82>10,T82<=15),"3",IF(AND(T82>15,T82<=20),"4",IF(AND(T82>20,T82<=25),"5",IF(AND(T82>25,T82<=30),"6",IF(AND(T82>30,T82<=35),"7",IF(AND(T82>35,T82<=40),"8",IF(T82>40,"9")))))))))) -> 1 | W82: PLN | X82: SubC | Y82: Stoker | AC82: 2.8137626 | AD82: 117.36754
B83: Tanjung Selor Unit 2 | C83: 7 | D83: NA | E83: NA | F83: <30 MW | G83: Kalimantan | H83: Yes | I83: Yes | J83: =iferror(vlookup(vlookup(B83,'Co-firing inputs'!B:C,2,false),'Co-firing inputs'!B:G,6,false),"None") -> None | O83: operating | P83: operating | Q83: 2023 | R83: 2030 | T83: =YEAR(today())-Q83 -> 3 | U83: =IF(AND(C83>0,C83<=100),"1",IF(AND(C83>100,C83<=300),"2",IF(AND(C83>300,C83<=600),"3",IF(AND(C83>600,C83<=1000),"4",IF(C83>1000,"5"))))) -> 1 | V83: =IF(T83<=0,"Planned",IF(AND(T83>0,T83<=5),"1",IF(AND(T83>5,T83<=10),"2",IF(AND(T83>10,T83<=15),"3",IF(AND(T83>15,T83<=20),"4",IF(AND(T83>20,T83<=25),"5",IF(AND(T83>25,T83<=30),"6",IF(AND(T83>30,T83<=35),"7",IF(AND(T83>35,T83<=40),"8",IF(T83>40,"9")))))))))) -> 1 | W83: PLN | X83: SubC | Y83: Stoker | AC83: 2.8137626 | AD83: 117.36754
B84: Tembilahan Unit 1 | C84: 7 | D84: NA | E84: NA | F84: <30 MW | G84: Sumatra | J84: Commercial/implemented | K84: Woodchip | L84: 0.25 | N84: operating | O84: operating | P84: operating | Q84: 2015 | T84: =YEAR(today())-Q84 -> 11 | U84: =IF(AND(C84>0,C84<=100),"1",IF(AND(C84>100,C84<=300),"2",IF(AND(C84>300,C84<=600),"3",IF(AND(C84>600,C84<=1000),"4",IF(C84>1000,"5"))))) -> 1 | V84: =IF(T84<=0,"Planned",IF(AND(T84>0,T84<=5),"1",IF(AND(T84>5,T84<=10),"2",IF(AND(T84>10,T84<=15),"3",IF(AND(T84>15,T84<=20),"4",IF(AND(T84>20,T84<=25),"5",IF(AND(T84>25,T84<=30),"6",IF(AND(T84>30,T84<=35),"7",IF(AND(T84>35,T84<=40),"8",IF(T84>40,"9")))))))))) -> 3 | W84: PLN | X84: SubC | Y84: Stoker | AA84: ESP | AC84: -0.29816518 | AD84: 103.2037
B85: Tembilahan Unit 2 | C85: 7 | D85: NA | E85: NA | F85: <30 MW | G85: Sumatra | J85: Commercial/implemented | K85: Woodchip | L85: 0.25 | N85: operating | O85: operating | P85: operating | Q85: 2015 | T85: =YEAR(today())-Q85 -> 11 | U85: =IF(AND(C85>0,C85<=100),"1",IF(AND(C85>100,C85<=300),"2",IF(AND(C85>300,C85<=600),"3",IF(AND(C85>600,C85<=1000),"4",IF(C85>1000,"5"))))) -> 1 | V85: =IF(T85<=0,"Planned",IF(AND(T85>0,T85<=5),"1",IF(AND(T85>5,T85<=10),"2",IF(AND(T85>10,T85<=15),"3",IF(AND(T85>15,T85<=20),"4",IF(AND(T85>20,T85<=25),"5",IF(AND(T85>25,T85<=30),"6",IF(AND(T85>30,T85<=35),"7",IF(AND(T85>35,T85<=40),"8",IF(T85>40,"9")))))))))) -> 3 | W85: PLN | X85: SubC | Y85: Stoker | AA85: ESP | AC85: -0.29816518 | AD85: 103.2037
B86: Tidore Unit 1 | C86: 7 | D86: NA | E86: NA | F86: <30 MW | G86: North Maluku | J86: Commercial/implemented | K86: Woodchip | L86: 0.05 | N86: operating | O86: operating | P86: operating | Q86: 2016 | T86: =YEAR(today())-Q86 -> 10 | U86: =IF(AND(C86>0,C86<=100),"1",IF(AND(C86>100,C86<=300),"2",IF(AND(C86>300,C86<=600),"3",IF(AND(C86>600,C86<=1000),"4",IF(C86>1000,"5"))))) -> 1 | V86: =IF(T86<=0,"Planned",IF(AND(T86>0,T86<=5),"1",IF(AND(T86>5,T86<=10),"2",IF(AND(T86>10,T86<=15),"3",IF(AND(T86>15,T86<=20),"4",IF(AND(T86>20,T86<=25),"5",IF(AND(T86>25,T86<=30),"6",IF(AND(T86>30,T86<=35),"7",IF(AND(T86>35,T86<=40),"8",IF(T86>40,"9")))))))))) -> 2 | W86: PLN | X86: SubC | Y86: Stoker | AA86: ESP | AC86: 0.73908001 | AD86: 127.38866 | AL86: 57.5 | AM86: 40 | AN86: 3 | AO86: 26.85 | AP86: 54.12 | AQ86: Stack: https://jurnal.ummu.ac.id/index.php/dintek/article/view/560
B87: Tidore Unit 2 | C87: 7 | D87: NA | E87: NA | F87: <30 MW | G87: North Maluku | J87: Commercial/implemented | K87: Woodchip | L87: 0.05 | N87: operating | O87: operating | P87: operating | Q87: 2016 | T87: =YEAR(today())-Q87 -> 10 | U87: =IF(AND(C87>0,C87<=100),"1",IF(AND(C87>100,C87<=300),"2",IF(AND(C87>300,C87<=600),"3",IF(AND(C87>600,C87<=1000),"4",IF(C87>1000,"5"))))) -> 1 | V87: =IF(T87<=0,"Planned",IF(AND(T87>0,T87<=5),"1",IF(AND(T87>5,T87<=10),"2",IF(AND(T87>10,T87<=15),"3",IF(AND(T87>15,T87<=20),"4",IF(AND(T87>20,T87<=25),"5",IF(AND(T87>25,T87<=30),"6",IF(AND(T87>30,T87<=35),"7",IF(AND(T87>35,T87<=40),"8",IF(T87>40,"9")))))))))) -> 2 | W87: PLN | X87: SubC | Y87: Stoker | AA87: ESP | AC87: 0.73908001 | AD87: 127.38866 | AL87: 57.5 | AM87: 40 | AN87: 3 | AO87: 26.85 | AP87: 54.12 | AQ87: Stack: https://jurnal.ummu.ac.id/index.php/dintek/article/view/560
B88: Adipala Unit 1 | C88: 660 | D88: G100000100040 | E88: G100040 | F88: =vlookup(D88,'GCPT Jul 2026'!A:G,7,false) -> Adipala Unit 1 | G88: Java | J88: =iferror(vlookup(vlookup(B88,'Co-firing inputs'!B:C,2,false),'Co-firing inputs'!B:G,6,false),"None") -> Commercial/implemented | K88: Sawdust | L88: 0.05 | N88: operating | O88: operating | P88: operating | Q88: 2015 | T88: =YEAR(today())-Q88 -> 11 | U88: =IF(AND(C88>0,C88<=100),"1",IF(AND(C88>100,C88<=300),"2",IF(AND(C88>300,C88<=600),"3",IF(AND(C88>600,C88<=1000),"4",IF(C88>1000,"5"))))) -> 4 | V88: =IF(T88<=0,"Planned",IF(AND(T88>0,T88<=5),"1",IF(AND(T88>5,T88<=10),"2",IF(AND(T88>10,T88<=15),"3",IF(AND(T88>15,T88<=20),"4",IF(AND(T88>20,T88<=25),"5",IF(AND(T88>25,T88<=30),"6",IF(AND(T88>30,T88<=35),"7",IF(AND(T88>35,T88<=40),"8",IF(T88>40,"9")))))))))) -> 3 | W88: PLN | X88: SC | Y88: PC | AA88: ESP, Low NOx Burner | AC88: =vlookup(D88,'GCPT Jul 2026'!A:AF,31,false) -> -7.685942 | AD88: =vlookup(D88,'GCPT Jul 2026'!A:AF,32,false) -> 109.13756 | AM88: 210 | AQ88: http://karya.brin.go.id/id/eprint/4612/1/PROSIDING_SUTANTO%20WW_DKK_PSTA_2012.pdf
B89: Amurang Unit 1 | C89: 30 | D89: G100000100180 | E89: G100180 | F89: =vlookup(D89,'GCPT Jul 2026'!A:G,7,false) -> Amurang Unit 1 | G89: Sulawesi | J89: =iferror(vlookup(vlookup(B89,'Co-firing inputs'!B:C,2,false),'Co-firing inputs'!B:G,6,false),"None") -> Commercial/implemented | K89: Sawdust | L89: 0.05 | N89: operating | O89: operating | P89: operating | Q89: 2012 | T89: =YEAR(today())-Q89 -> 14 | U89: =IF(AND(C89>0,C89<=100),"1",IF(AND(C89>100,C89<=300),"2",IF(AND(C89>300,C89<=600),"3",IF(AND(C89>600,C89<=1000),"4",IF(C89>1000,"5"))))) -> 1 | V89: =IF(T89<=0,"Planned",IF(AND(T89>0,T89<=5),"1",IF(AND(T89>5,T89<=10),"2",IF(AND(T89>10,T89<=15),"3",IF(AND(T89>15,T89<=20),"4",IF(AND(T89>20,T89<=25),"5",IF(AND(T89>25,T89<=30),"6",IF(AND(T89>30,T89<=35),"7",IF(AND(T89>35,T89<=40),"8",IF(T89>40,"9")))))))))) -> 3 | W89: PLN | X89: SubC | Y89: CFB | AA89: ESP, Low NOx Burner, Limestone | AC89: 1.182502 | AD89: =vlookup(D89,'GCPT Jul 2026'!A:AF,32,false) -> 124.48056 | AM89: 60.5 | AN89: 3.36 | AQ89: Stack: https://www.tingtai.com.tw/h/albumDetail?key=yf8d3&cont=324544
B90: Amurang Unit 2 | C90: 30 | D90: G100000100181 | E90: G100181 | F90: =vlookup(D90,'GCPT Jul 2026'!A:G,7,false) -> Amurang Unit 2 | G90: Sulawesi | J90: =iferror(vlookup(vlookup(B90,'Co-firing inputs'!B:C,2,false),'Co-firing inputs'!B:G,6,false),"None") -> Commercial/implemented | K90: Sawdust | L90: 0.05 | N90: operating | O90: operating | P90: operating | Q90: 2012 | T90: =YEAR(today())-Q90 -> 14 | U90: =IF(AND(C90>0,C90<=100),"1",IF(AND(C90>100,C90<=300),"2",IF(AND(C90>300,C90<=600),"3",IF(AND(C90>600,C90<=1000),"4",IF(C90>1000,"5"))))) -> 1 | V90: =IF(T90<=0,"Planned",IF(AND(T90>0,T90<=5),"1",IF(AND(T90>5,T90<=10),"2",IF(AND(T90>10,T90<=15),"3",IF(AND(T90>15,T90<=20),"4",IF(AND(T90>20,T90<=25),"5",IF(AND(T90>25,T90<=30),"6",IF(AND(T90>30,T90<=35),"7",IF(AND(T90>35,T90<=40),"8",IF(T90>40,"9")))))))))) -> 3 | W90: PLN | X90: SubC | Y90: CFB | AA90: ESP, Low NOx Burner, Limestone | AC90: 1.182502 | AD90: =vlookup(D90,'GCPT Jul 2026'!A:AF,32,false) -> 124.48056 | AM90: 60.5 | AN90: 3.36 | AQ90: Stack: https://www.tingtai.com.tw/h/albumDetail?key=yf8d3&cont=324544
B91: Amurang (Lease) Unit 1 | C91: 30 | D91: G100000113971 | E91: G113971 | F91: =vlookup(D91,'GCPT Jul 2026'!A:G,7,false) -> Amurang-2 Unit 1 | G91: Sulawesi | J91: =iferror(vlookup(vlookup(B91,'Co-firing inputs'!B:C,2,false),'Co-firing inputs'!B:G,6,false),"None") -> None | N91: operating | O91: operating | P91: operating | Q91: 2018 | T91: =YEAR(today())-Q91 -> 8 | U91: =IF(AND(C91>0,C91<=100),"1",IF(AND(C91>100,C91<=300),"2",IF(AND(C91>300,C91<=600),"3",IF(AND(C91>600,C91<=1000),"4",IF(C91>1000,"5"))))) -> 1 | V91: =IF(T91<=0,"Planned",IF(AND(T91>0,T91<=5),"1",IF(AND(T91>5,T91<=10),"2",IF(AND(T91>10,T91<=15),"3",IF(AND(T91>15,T91<=20),"4",IF(AND(T91>20,T91<=25),"5",IF(AND(T91>25,T91<=30),"6",IF(AND(T91>30,T91<=35),"7",IF(AND(T91>35,T91<=40),"8",IF(T91>40,"9")))))))))) -> 2 | W91: PLN | X91: SubC | Y91: CFB | AA91: ESP, Limestone | AC91: 1.182502 | AD91: =vlookup(D91,'GCPT Jul 2026'!A:AF,32,false) -> 124.48056
B92: Amurang (Lease) Unit 2 | C92: 30 | D92: G100000113972 | E92: G113972 | F92: =vlookup(D92,'GCPT Jul 2026'!A:G,7,false) -> Amurang-2 Unit 2 | G92: Sulawesi | J92: =iferror(vlookup(vlookup(B92,'Co-firing inputs'!B:C,2,false),'Co-firing inputs'!B:G,6,false),"None") -> None | N92: operating | O92: operating | P92: operating | Q92: 2018 | T92: =YEAR(today())-Q92 -> 8 | U92: =IF(AND(C92>0,C92<=100),"1",IF(AND(C92>100,C92<=300),"2",IF(AND(C92>300,C92<=600),"3",IF(AND(C92>600,C92<=1000),"4",IF(C92>1000,"5"))))) -> 1 | V92: =IF(T92<=0,"Planned",IF(AND(T92>0,T92<=5),"1",IF(AND(T92>5,T92<=10),"2",IF(AND(T92>10,T92<=15),"3",IF(AND(T92>15,T92<=20),"4",IF(AND(T92>20,T92<=25),"5",IF(AND(T92>25,T92<=30),"6",IF(AND(T92>30,T92<=35),"7",IF(AND(T92>35,T92<=40),"8",IF(T92>40,"9")))))))))) -> 2 | W92: PLN | X92: SubC | Y92: CFB | AA92: ESP, Limestone | AC92: 1.182502 | AD92: =vlookup(D92,'GCPT Jul 2026'!A:AF,32,false) -> 124.48056
B93: Asam-asam Unit 1 | C93: 65 | D93: G100000105482 | E93: G105482 | F93: =vlookup(D93,'GCPT Jul 2026'!A:G,7,false) -> Asam-Asam Unit 1 | G93: Kalimantan | J93: =iferror(vlookup(vlookup(B93,'Co-firing inputs'!B:C,2,false),'Co-firing inputs'!B:G,6,false),"None") -> Commercial/implemented | K93: Sawdust | L93: 0.05 | N93: operating | O93: operating | P93: operating | Q93: 2013 | T93: =YEAR(today())-Q93 -> 13 | U93: =IF(AND(C93>0,C93<=100),"1",IF(AND(C93>100,C93<=300),"2",IF(AND(C93>300,C93<=600),"3",IF(AND(C93>600,C93<=1000),"4",IF(C93>1000,"5"))))) -> 1 | V93: =IF(T93<=0,"Planned",IF(AND(T93>0,T93<=5),"1",IF(AND(T93>5,T93<=10),"2",IF(AND(T93>10,T93<=15),"3",IF(AND(T93>15,T93<=20),"4",IF(AND(T93>20,T93<=25),"5",IF(AND(T93>25,T93<=30),"6",IF(AND(T93>30,T93<=35),"7",IF(AND(T93>35,T93<=40),"8",IF(T93>40,"9")))))))))) -> 3 | W93: PLN | X93: SubC | Y93: PC | AA93: ESP, Low NOx Burner | AC93: =vlookup(D93,'GCPT Jul 2026'!A:AF,31,false) -> -3.9265336 | AD93: =vlookup(D93,'GCPT Jul 2026'!A:AF,32,false) -> 115.10581 | AH93: 123 | AI93: 323 | AJ93: =average(1, 339) -> 170 | AK93: ppm | AL93: 62.4 | AQ93: https://www.jica.go.jp/english/our_work/evaluation/oda_loan/post/2004/pdf/theme_04-1_full.pdf https://drive.google.com/file/d/1pg5KB5pndXqSZ7J-ZeE1A8J0LMZ-gDb6/view?usp=share_link
B94: Asam-asam Unit 2 | C94: 65 | D94: G100000105483 | E94: G105483 | F94: =vlookup(D94,'GCPT Jul 2026'!A:G,7,false) -> Asam-Asam Unit 2 | G94: Kalimantan | J94: =iferror(vlookup(vlookup(B94,'Co-firing inputs'!B:C,2,false),'Co-firing inputs'!B:G,6,false),"None") -> Commercial/implemented | K94: Sawdust | L94: 0.05 | N94: operating | O94: operating | P94: operating | Q94: 2013 | T94: =YEAR(today())-Q94 -> 13 | U94: =IF(AND(C94>0,C94<=100),"1",IF(AND(C94>100,C94<=300),"2",IF(AND(C94>300,C94<=600),"3",IF(AND(C94>600,C94<=1000),"4",IF(C94>1000,"5"))))) -> 1 | V94: =IF(T94<=0,"Planned",IF(AND(T94>0,T94<=5),"1",IF(AND(T94>5,T94<=10),"2",IF(AND(T94>10,T94<=15),"3",IF(AND(T94>15,T94<=20),"4",IF(AND(T94>20,T94<=25),"5",IF(AND(T94>25,T94<=30),"6",IF(AND(T94>30,T94<=35),"7",IF(AND(T94>35,T94<=40),"8",IF(T94>40,"9")))))))))) -> 3 | W94: PLN | X94: SubC | Y94: PC | AA94: ESP, Low NOx Burner | AC94: =vlookup(D94,'GCPT Jul 2026'!A:AF,31,false) -> -3.9265336 | AD94: =vlookup(D94,'GCPT Jul 2026'!A:AF,32,false) -> 115.10581 | AH94: 123 | AI94: 323 | AJ94: =average(1, 339) -> 170 | AK94: ppm | AL94: 62.4 | AQ94: https://www.jica.go.jp/english/our_work/evaluation/oda_loan/post/2004/pdf/theme_04-1_full.pdf https://drive.google.com/file/d/1pg5KB5pndXqSZ7J-ZeE1A8J0LMZ-gDb6/view?usp=share_link
B95: Kalselteng-2 Unit 1 | C95: 100 | D95: G100000100515 | E95: G100515 | F95: =vlookup(D95,'GCPT Jul 2026'!A:G,7,false) -> Asam-Asam Unit 5 | G95: Kalimantan | H95: Yes | J95: Commercial/implemented | K95: NA | L95: NA | N95: construction | O95: construction | P95: operating | Q95: 2024 | T95: =YEAR(today())-Q95 -> 2 | U95: =IF(AND(C95>0,C95<=100),"1",IF(AND(C95>100,C95<=300),"2",IF(AND(C95>300,C95<=600),"3",IF(AND(C95>600,C95<=1000),"4",IF(C95>1000,"5"))))) -> 1 | V95: =IF(T95<=0,"Planned",IF(AND(T95>0,T95<=5),"1",IF(AND(T95>5,T95<=10),"2",IF(AND(T95>10,T95<=15),"3",IF(AND(T95>15,T95<=20),"4",IF(AND(T95>20,T95<=25),"5",IF(AND(T95>25,T95<=30),"6",IF(AND(T95>30,T95<=35),"7",IF(AND(T95>35,T95<=40),"8",IF(T95>40,"9")))))))))) -> 1 | W95: PLN | X95: SubC | Y95: PC | AC95: =vlookup(D95,'GCPT Jul 2026'!A:AF,31,false) -> -3.9265336 | AD95: =vlookup(D95,'GCPT Jul 2026'!A:AF,32,false) -> 115.10581
B96: Kalselteng-2 Unit 2 | C96: 100 | D96: G100000100516 | E96: G100516 | F96: =vlookup(D96,'GCPT Jul 2026'!A:G,7,false) -> Asam-Asam Unit 6 | G96: Kalimantan | H96: Yes | J96: Commercial/implemented | K96: NA | L96: NA | N96: construction | O96: construction | P96: operating | Q96: 2025 | T96: =YEAR(today())-Q96 -> 1 | U96: =IF(AND(C96>0,C96<=100),"1",IF(AND(C96>100,C96<=300),"2",IF(AND(C96>300,C96<=600),"3",IF(AND(C96>600,C96<=1000),"4",IF(C96>1000,"5"))))) -> 1 | V96: =IF(T96<=0,"Planned",IF(AND(T96>0,T96<=5),"1",IF(AND(T96>5,T96<=10),"2",IF(AND(T96>10,T96<=15),"3",IF(AND(T96>15,T96<=20),"4",IF(AND(T96>20,T96<=25),"5",IF(AND(T96>25,T96<=30),"6",IF(AND(T96>30,T96<=35),"7",IF(AND(T96>35,T96<=40),"8",IF(T96>40,"9")))))))))) -> 1 | W96: PLN | X96: SubC | Y96: PC | AC96: =vlookup(D96,'GCPT Jul 2026'!A:AF,31,false) -> -3.9265336 | AD96: =vlookup(D96,'GCPT Jul 2026'!A:AF,32,false) -> 115.10581
B97: Asam-Asam Unit 3 | C97: 65 | D97: G100000100517 | E97: G100517 | F97: =vlookup(D97,'GCPT Jul 2026'!A:G,7,false) -> Asam-Asam Unit B-3 | G97: Kalimantan | J97: =iferror(vlookup(vlookup(B97,'Co-firing inputs'!B:C,2,false),'Co-firing inputs'!B:G,6,false),"None") -> Commercial/implemented | K97: Sawdust | L97: 0.05 | M97: FTP-1 | N97: operating | O97: operating | P97: operating | Q97: 2000 | T97: =YEAR(today())-Q97 -> 26 | U97: =IF(AND(C97>0,C97<=100),"1",IF(AND(C97>100,C97<=300),"2",IF(AND(C97>300,C97<=600),"3",IF(AND(C97>600,C97<=1000),"4",IF(C97>1000,"5"))))) -> 1 | V97: =IF(T97<=0,"Planned",IF(AND(T97>0,T97<=5),"1",IF(AND(T97>5,T97<=10),"2",IF(AND(T97>10,T97<=15),"3",IF(AND(T97>15,T97<=20),"4",IF(AND(T97>20,T97<=25),"5",IF(AND(T97>25,T97<=30),"6",IF(AND(T97>30,T97<=35),"7",IF(AND(T97>35,T97<=40),"8",IF(T97>40,"9")))))))))) -> 6 | W97: PLN | X97: SubC | Y97: PC | AA97: ESP, Low NOx Burner | AC97: =vlookup(D97,'GCPT Jul 2026'!A:AF,31,false) -> -3.9265336 | AD97: =vlookup(D97,'GCPT Jul 2026'!A:AF,32,false) -> 115.10581 | AH97: 123 | AI97: 323 | AJ97: =average(1, 339) -> 170 | AK97: ppm | AL97: 62.4 | AQ97: https://www.jica.go.jp/english/our_work/evaluation/oda_loan/post/2004/pdf/theme_04-1_full.pdf https://drive.google.com/file/d/1pg5KB5pndXqSZ7J-ZeE1A8J0LMZ-gDb6/view?usp=share_link
B98: Asam-Asam Unit 4 | C98: 65 | D98: G100000100518 | E98: G100518 | F98: =vlookup(D98,'GCPT Jul 2026'!A:G,7,false) -> Asam-Asam Unit B-4 | G98: Kalimantan | J98: =iferror(vlookup(vlookup(B98,'Co-firing inputs'!B:C,2,false),'Co-firing inputs'!B:G,6,false),"None") -> Commercial/implemented | K98: Sawdust | L98: 0.05 | M98: FTP-1 | N98: operating | O98: operating | P98: operating | Q98: 2000 | T98: =YEAR(today())-Q98 -> 26 | U98: =IF(AND(C98>0,C98<=100),"1",IF(AND(C98>100,C98<=300),"2",IF(AND(C98>300,C98<=600),"3",IF(AND(C98>600,C98<=1000),"4",IF(C98>1000,"5"))))) -> 1 | V98: =IF(T98<=0,"Planned",IF(AND(T98>0,T98<=5),"1",IF(AND(T98>5,T98<=10),"2",IF(AND(T98>10,T98<=15),"3",IF(AND(T98>15,T98<=20),"4",IF(AND(T98>20,T98<=25),"5",IF(AND(T98>25,T98<=30),"6",IF(AND(T98>30,T98<=35),"7",IF(AND(T98>35,T98<=40),"8",IF(T98>40,"9")))))))))) -> 6 | W98: PLN | X98: SubC | Y98: PC | AA98: ESP, Low NOx Burner | AC98: =vlookup(D98,'GCPT Jul 2026'!A:AF,31,false) -> -3.9265336 | AD98: =vlookup(D98,'GCPT Jul 2026'!A:AF,32,false) -> 115.10581 | AH98: 123 | AI98: 323 | AJ98: =average(1, 339) -> 170 | AK98: ppm | AL98: 62.4 | AQ98: https://www.jica.go.jp/english/our_work/evaluation/oda_loan/post/2004/pdf/theme_04-1_full.pdf https://drive.google.com/file/d/1pg5KB5pndXqSZ7J-ZeE1A8J0LMZ-gDb6/view?usp=share_link
B99: Air Anyir Unit 1 | C99: 30 | D99: G100000100508 | E99: G100508 | F99: =vlookup(D99,'GCPT Jul 2026'!A:G,7,false) -> Bangka Baru Unit 1 | G99: Sumatra | J99: =iferror(vlookup(vlookup(B99,'Co-firing inputs'!B:C,2,false),'Co-firing inputs'!B:G,6,false),"None") -> Commercial/implemented | K99: Woodchip | L99: 0.05 | N99: operating | O99: operating | P99: operating | Q99: 2014 | T99: =YEAR(today())-Q99 -> 12 | U99: =IF(AND(C99>0,C99<=100),"1",IF(AND(C99>100,C99<=300),"2",IF(AND(C99>300,C99<=600),"3",IF(AND(C99>600,C99<=1000),"4",IF(C99>1000,"5"))))) -> 1 | V99: =IF(T99<=0,"Planned",IF(AND(T99>0,T99<=5),"1",IF(AND(T99>5,T99<=10),"2",IF(AND(T99>10,T99<=15),"3",IF(AND(T99>15,T99<=20),"4",IF(AND(T99>20,T99<=25),"5",IF(AND(T99>25,T99<=30),"6",IF(AND(T99>30,T99<=35),"7",IF(AND(T99>35,T99<=40),"8",IF(T99>40,"9")))))))))) -> 3 | W99: PLN | X99: SubC | Y99: CFB | AA99: ESP | AC99: =vlookup(D99,'GCPT Jul 2026'!A:AF,31,false) -> -2.079245 | AD99: =vlookup(D99,'GCPT Jul 2026'!A:AF,32,false) -> 106.14962 | AL99: 134 | AO99: 153.15 | AQ99: https://repository.its.ac.id/76043/1/2112100072-Undergraduate_Thesis.pdf
B100: Air Anyir Unit 2 | C100: 30 | D100: G100000100509 | E100: G100509 | F100: =vlookup(D100,'GCPT Jul 2026'!A:G,7,false) -> Bangka Baru Unit 2 | G100: Sumatra | J100: =iferror(vlookup(vlookup(B100,'Co-firing inputs'!B:C,2,false),'Co-firing inputs'!B:G,6,false),"None") -> Commercial/implemented | K100: Woodchip | L100: 0.05 | N100: operating | O100: operating | P100: operating | Q100: 2014 | T100: =YEAR(today())-Q100 -> 12 | U100: =IF(AND(C100>0,C100<=100),"1",IF(AND(C100>100,C100<=300),"2",IF(AND(C100>300,C100<=600),"3",IF(AND(C100>600,C100<=1000),"4",IF(C100>1000,"5"))))) -> 1 | V100: =IF(T100<=0,"Planned",IF(AND(T100>0,T100<=5),"1",IF(AND(T100>5,T100<=10),"2",IF(AND(T100>10,T100<=15),"3",IF(AND(T100>15,T100<=20),"4",IF(AND(T100>20,T100<=25),"5",IF(AND(T100>25,T100<=30),"6",IF(AND(T100>30,T100<=35),"7",IF(AND(T100>35,T100<=40),"8",IF(T100>40,"9")))))))))) -> 3 | W100: PLN | X100: SubC | Y100: CFB | AA100: ESP | AC100: =vlookup(D100,'GCPT Jul 2026'!A:AF,31,false) -> -2.079245 | AD100: =vlookup(D100,'GCPT Jul 2026'!A:AF,32,false) -> 106.14962 | AL100: 134 | AO100: 153.15 | AQ100: https://repository.its.ac.id/76043/1/2112100072-Undergraduate_Thesis.pdf
...

Sheet Captive
A1: GEM Wiki | B1: CFPP name | C1: GEM unit/phase ID | D1: GEM ID | E1: Owner | F1: Captive industry | G1: Capacity (MW) | H1: COD | I1: Status Jul 2026 | J1: Status Jul 2024 | K1: Status Jan 2024 | L1: Status Jun 2023 | M1: Latitude | N1: Longitude | O1: Parent | P1: Province_EN | Q1: Provinsi_ID | R1: RUKN_out Mar 2025_new?
A2: https://www.gem.wiki/PT_IHIP_power_station | B2: PT IHIP Expansion Unit | C2: G100001053834 | D2: (new entry) | E2: Captive | F2: Industrial park | G2: 100 | I2: announced | M2: -2.2578515 | N2: 121.76902 | O2: Huakai Investment Co Ltd; Tongxiang Wushi Trading Co Ltd; unknown; Zhenshi Holding Group Co Ltd | P2: Central Sulawesi | Q2: Sulawesi Tengah | R2: yes
A3: https://www.gem.wiki/Hongshi_Silikon_power_station | B3: Hongshi Silikon | C3: G100001054115 | D3: (new entry) | E3: Captive | F3: Industrial park | G3: 2000 | I3: announced | M3: -6.87203 | N3: 107.59869 | O3: Hongshi Holding Group Co Ltd [100.0%] | P3: West Java | Q3: Jawa Barat | R3: yes
A4: https://www.gem.wiki/AlamTri_Aluminum_Smelter_power_station | B4: AlamTri Aluminum Smelter Phase II Unit 2 | C4: G100001092190 | D4: (new entry) | E4: Captive | F4: Aluminum | G4: 150 | H4: 2026 | I4: announced | M4: 2.4946822 | N4: 117.9002 | O4: PT Alamtri Resources Indonesia Tbk [84.0%]; PT Cita Mineral Investindo Tbk [16.0%] | P4: North Kalimantan | Q4: Kalimantan Utara | R4: yes
A5: https://www.gem.wiki/AlamTri_Aluminum_Smelter_power_station | B5: AlamTri Aluminum Smelter Phase II Unit 3 | C5: G100001092191 | D5: (new entry) | E5: Captive | F5: Aluminum | G5: 380 | H5: 2026 | I5: announced | M5: 2.4946822 | N5: 117.9002 | O5: PT Alamtri Resources Indonesia Tbk [84.0%]; PT Cita Mineral Investindo Tbk [16.0%] | P5: North Kalimantan | Q5: Kalimantan Utara | R5: yes
A6: https://www.gem.wiki/AlamTri_Aluminum_Smelter_power_station | B6: AlamTri Aluminum Smelter Phase II Unit 4 | C6: G100001092192 | D6: (new entry) | E6: Captive | F6: Aluminum | G6: 380 | H6: 2026 | I6: announced | M6: 2.4946822 | N6: 117.9002 | O6: PT Alamtri Resources Indonesia Tbk [84.0%]; PT Cita Mineral Investindo Tbk [16.0%] | P6: North Kalimantan | Q6: Kalimantan Utara | R6: yes
A7: https://www.gem.wiki/Nanshan_Industrial_Park_power_station | B7: Nanshan Industrial Park Phase II Unit 7 | C7: G100001093525 | D7: (new entry) | E7: Captive | F7: Aluminum | G7: 150 | H7: 2027 | I7: announced | M7: 0.911643 | N7: 104.65054 | O7: Nanshan Aluminium International Holdings Ltd [72.7%]; Hong Kong Prime Aluminium Investment Ltd [25.0%]; small shareholder(s) [2.3%] | P7: Riau Islands | Q7: Kepulauan Riau | R7: yes
A8: https://www.gem.wiki/Delong_Nickel_Phase_IV_power_station | B8: Delong Nickel Phase IV Unit 2 | C8: G100001031228 | D8: (new entry) | E8: Captive | F8: Nickel | G8: 330 | I8: construction | M8: -2.0165661 | N8: 121.43118 | O8: Zhongwei Hong Kong Zhengbang New Energy Co Ltd [35.0%]; Jiangsu Delong Nickel Industry Co Ltd [33.0%]; Zhongwei Hong Kong Zhenghong New Energy Co Ltd [25.0%]; Tongren Zhongwei Hongling No. 1 Enterprise Management Consulting Partnership LP [7.0%] | P8: Central Sulawesi | Q8: Sulawesi Tengah | R8: yes
A9: https://www.gem.wiki/AlamTri_Aluminum_Smelter_power_station | B9: AlamTri Aluminum Smelter Phase I Unit 2 | C9: G100001052602 | D9: (new entry) | E9: Captive | F9: Aluminum | G9: 150 | H9: 2026 | I9: construction | M9: 2.4946822 | N9: 117.9002 | O9: PT Alamtri Resources Indonesia Tbk [84.0%]; PT Cita Mineral Investindo Tbk [16.0%] | P9: North Kalimantan | Q9: Kalimantan Utara | R9: yes
A10: https://www.gem.wiki/AlamTri_Aluminum_Smelter_power_station | B10: AlamTri Aluminum Smelter Phase I Unit 3 | C10: G100001052603 | D10: (new entry) | E10: Captive | F10: Aluminum | G10: 380 | H10: 2025 | I10: construction | M10: 2.4946822 | N10: 117.9002 | O10: PT Alamtri Resources Indonesia Tbk [84.0%]; PT Cita Mineral Investindo Tbk [16.0%] | P10: North Kalimantan | Q10: Kalimantan Utara | R10: yes
A11: https://www.gem.wiki/AlamTri_Aluminum_Smelter_power_station | B11: AlamTri Aluminum Smelter Phase I Unit 4 | C11: G100001052604 | D11: (new entry) | E11: Captive | F11: Aluminum | G11: 380 | H11: 2025 | I11: construction | M11: 2.4946822 | N11: 117.9002 | O11: PT Alamtri Resources Indonesia Tbk [84.0%]; PT Cita Mineral Investindo Tbk [16.0%] | P11: North Kalimantan | Q11: Kalimantan Utara | R11: yes
A12: https://www.gem.wiki/Gallant_Venture_power_station | B12: Gallant Venture Phase I Unit 1 | C12: G100001054770 | D12: (new entry) | E12: Captive | F12: Industrial park | G12: 350 | I12: construction | M12: 0.9575588 | N12: 104.04864 | O12: Gallant Venture Ltd [100.0%] | P12: Riau Islands | Q12: Kepulauan Riau | R12: yes
A13: https://www.gem.wiki/Gallant_Venture_power_station | B13: Gallant Venture Phase I Unit 2 | C13: G100001054771 | D13: (new entry) | E13: Captive | F13: Industrial park | G13: 350 | I13: construction | M13: 0.9575588 | N13: 104.04864 | O13: Gallant Venture Ltd [100.0%] | P13: Riau Islands | Q13: Kepulauan Riau | R13: yes
A14: https://www.gem.wiki/Gallant_Venture_power_station | B14: Gallant Venture Phase I Unit 3 | C14: G100001054774 | D14: (new entry) | E14: Captive | F14: Industrial park | G14: 350 | I14: construction | M14: 0.9575588 | N14: 104.04864 | O14: Gallant Venture Ltd [100.0%] | P14: Riau Islands | Q14: Kepulauan Riau | R14: yes
A15: https://www.gem.wiki/Sulawesi_Labota_power_station | B15: Sulawesi Labota Unit 10 | C15: G100001093520 | D15: (new entry) | E15: Captive | F15: Aluminum, nickel | G15: 380 | H15: 2025 | I15: construction | M15: -2.87427 | N15: 122.1777 | O15: Huafon Group Co Ltd [65.0%]; Eternal Tsingshan Group Ltd [35.0%] | P15: Central Sulawesi | Q15: Sulawesi Tengah | R15: yes
A16: https://www.gem.wiki/Sulawesi_Labota_power_station | B16: Sulawesi Labota Unit 11 | C16: G100001093521 | D16: (new entry) | E16: Captive | F16: Aluminum, nickel | G16: 380 | H16: 2025 | I16: construction | M16: -2.87427 | N16: 122.1777 | O16: Huafon Group Co Ltd [65.0%]; Eternal Tsingshan Group Ltd [35.0%] | P16: Central Sulawesi | Q16: Sulawesi Tengah | R16: yes
A17: https://www.gem.wiki/PT_Kalimantan_Alumina_Nusantara_power_station | B17: PT Kalimantan Alumina Nusantara Unit 1 | C17: G100001093590 | D17: (new entry) | E17: Captive | F17: Aluminum | G17: 30 | I17: construction | M17: -0.1238386 | N17: 109.97131 | O17: Press Metal International Resources (HK) Ltd [80.0%]; PT Alakasa Alumina Refineri [17.2%]; small shareholder(s) [2.8%] | P17: West Kalimantan | Q17: Kalimantan Barat | R17: yes
A18: https://www.gem.wiki/PT_Kalimantan_Alumina_Nusantara_power_station | B18: PT Kalimantan Alumina Nusantara Unit 2 | C18: G100001093591 | D18: (new entry) | E18: Captive | F18: Aluminum | G18: 30 | I18: construction | M18: -0.1238386 | N18: 109.97131 | O18: Press Metal International Resources (HK) Ltd [80.0%]; PT Alakasa Alumina Refineri [17.2%]; small shareholder(s) [2.8%] | P18: West Kalimantan | Q18: Kalimantan Barat | R18: yes
A19: https://www.gem.wiki/Toba_Pulp_Lestari_power_station | B19: Toba Pulp Lestari Unit 2 | C19: G100001093598 | D19: (new entry) | E19: Captive | F19: Pulp and paper | G19: 30 | H19: 2014 | I19: mothballed | M19: 2.4636762 | N19: 99.197277 | O19: PT Toba Pulp Lestari Tbk [100.0%] | P19: North Sumatra | Q19: Sumatera Utara | R19: no
A20: https://www.gem.wiki/Perawang_Mill_power_station | B20: Perawang Mill Unit 05 | C20: G100001093579 | D20: (new entry) | E20: Captive | F20: Pulp and paper | G20: 35 | H20: 2008 | I20: operating | M20: 0.68932 | N20: 101.61907 | O20: PT Indah Kiat Pulp & Paper Tbk [100.0%] | P20: Riau | Q20: Riau | R20: no
A21: https://www.gem.wiki/Delong_Nickel_Phase_IV_power_station | B21: Delong Nickel Phase IV Unit 3 | C21: G100001031233 | D21: (new entry) | E21: Captive | F21: Nickel | G21: 330 | H21: 2024 | I21: operating | M21: -2.0165661 | N21: 121.43118 | O21: Zhongwei Hong Kong Zhengbang New Energy Co Ltd [35.0%]; Jiangsu Delong Nickel Industry Co Ltd [33.0%]; Zhongwei Hong Kong Zhenghong New Energy Co Ltd [25.0%]; Tongren Zhongwei Hongling No. 1 Enterprise Management Consulting Partnership LP [7.0%] | P21: Central Sulawesi | Q21: Sulawesi Tengah | R21: no
A22: https://www.gem.wiki/PT_Halmahera_Persada_Lygend_Nickel_Smelter_power_station | B22: PT Halmahera Persada Lygend Nickel Smelter Phase II Unit 5 | C22: G100001031294 | D22: (new entry) | E22: Captive | F22: Nickel | G22: 150 | H22: 2023 | I22: operating | M22: -1.5614331 | N22: 127.42103 | O22: Ningbo Lygend [36.9%]; Harita Group | P22: North Maluku | Q22: Maluku Utara | R22: no
A23: https://www.gem.wiki/PT_Krakatau_Posco_Energy_power_station | B23: PT Krakatau Posco Energy Unit 1 | C23: G100001093557 | D23: (new entry) | E23: Captive | F23: Chemicals, Iron & steel | G23: 100 | H23: 2014 | I23: operating | M23: -6.0068473 | N23: 105.97151 | O23: POSCO International Corp [55.0%]; PT Krakatau Chandra Energi [45.0%] | P23: Banten | Q23: Banten | R23: no
A24: https://www.gem.wiki/PT_Krakatau_Posco_Energy_power_station | B24: PT Krakatau Posco Energy Unit 2 | C24: G100001093558 | D24: (new entry) | E24: Captive | F24: Chemicals, Iron & steel | G24: 100 | H24: 2014 | I24: operating | M24: -6.0068473 | N24: 105.97151 | O24: POSCO International Corp [55.0%]; PT Krakatau Chandra Energi [45.0%] | P24: Banten | Q24: Banten | R24: no
A25: https://www.gem.wiki/Pindo-Deli-Ii_power_station | B25: Pindo-Deli-Ii Unit 3 | C25: G100001093577 | D25: (new entry) | E25: Captive | F25: Pulp and paper | G25: 30.2 | H25: 2007 | I25: operating | M25: -6.385474 | N25: 107.34362 | O25: PT APP Purinusa Ekapersada [99.2%]; small shareholder(s) [0.8%] | P25: West Java | Q25: Jawa Barat | R25: no
A26: https://www.gem.wiki/Pindo-Deli-Ii_power_station | B26: Pindo-Deli-Ii Unit 4 | C26: G100001093578 | D26: (new entry) | E26: Captive | F26: Pulp and paper | G26: 30.2 | H26: 2007 | I26: operating | M26: -6.385474 | N26: 107.34362 | O26: PT APP Purinusa Ekapersada [99.2%]; small shareholder(s) [0.8%] | P26: West Java | Q26: Jawa Barat | R26: no
A27: https://www.gem.wiki/South_Pasific_Viscose_power_station | B27: South Pasific Viscose -- | C27: G100001093582 | D27: (new entry) | E27: Captive | F27: Textile | G27: 30 | H27: 2009 | I27: operating | M27: -6.4981713 | N27: 107.39956 | O27: Lenzing AG [99.9%] | P27: West Java | Q27: Jawa Barat | R27: no
A28: https://www.gem.wiki/Toba_Pulp_Lestari_power_station | B28: Toba Pulp Lestari Unit 1 | C28: G100001093597 | D28: (new entry) | E28: Captive | F28: Pulp and paper | G28: 50 | H28: 2014 | I28: operating | M28: 2.4636762 | N28: 99.197277 | O28: PT Toba Pulp Lestari Tbk [100.0%] | P28: North Sumatra | Q28: Sumatera Utara | R28: no
A29: https://www.gem.wiki/Ketapang_Bangun_Sarana_power_station | B29: Ketapang Bangun Sarana Unit 1 | C29: G100001090979 | D29: (new entry) | E29: Captive | F29: Aluminum | G29: 45 | H29: 2025 | I29: operating | M29: -2.2356003 | N29: 110.10663 | O29: natural person(s) [46.6%]; Zhejiang Hengjia Holding Co Ltd [27.0%]; Hangzhou Yande Industrial Co Ltd [26.3%] | P29: West Kalimantan | Q29: Kalimantan Barat | R29: yes
A30: https://www.gem.wiki/Ketapang_Bangun_Sarana_power_station | B30: Ketapang Bangun Sarana Unit 2 | C30: G100001090980 | D30: (new entry) | E30: Captive | F30: Aluminum | G30: 30 | H30: 2025 | I30: operating | M30: -2.2356003 | N30: 110.10663 | O30: natural person(s) [46.6%]; Zhejiang Hengjia Holding Co Ltd [27.0%]; Hangzhou Yande Industrial Co Ltd [26.3%] | P30: West Kalimantan | Q30: Kalimantan Barat | R30: yes
A31: https://www.gem.wiki/Gallant_Venture_power_station | B31: Gallant Venture Phase II Unit 1 | C31: G100001054772 | D31: (new entry) | E31: Captive | F31: Industrial park | G31: 600 | I31: pre-permit | M31: 0.9575588 | N31: 104.04864 | O31: Gallant Venture Ltd [100.0%] | P31: Riau Islands | Q31: Kepulauan Riau | R31: yes
A32: https://www.gem.wiki/Gallant_Venture_power_station | B32: Gallant Venture Phase II Unit 2 | C32: G100001054773 | D32: (new entry) | E32: Captive | F32: Industrial park | G32: 600 | I32: pre-permit | M32: 0.9575588 | N32: 104.04864 | O32: Gallant Venture Ltd [100.0%] | P32: Riau Islands | Q32: Kepulauan Riau | R32: yes
A33: https://www.gem.wiki/East_Halmahera_power_station | B33: East Halmahera | C33: G100001090880 | D33: (new entry) | E33: Captive | F33: Nickel | G33: 680 | H33: 2028 | I33: pre-permit | M33: 0.84457743 | N33: 128.24938 | O33: PT Petrindo Jaya Kreasi Tbk [90.0%]; unknown [10.0%] | P33: North Maluku | Q33: Maluku Utara | R33: yes
A34: https://www.gem.wiki/Sulawesi_Labota_power_station | B34: Sulawesi Labota Unit 12 | C34: G100001093523 | D34: (new entry) | E34: Captive | F34: Aluminum, nickel | G34: 380 | I34: pre-permit | M34: -2.87427 | N34: 122.1777 | O34: Huafon Group Co Ltd [65.0%]; Eternal Tsingshan Group Ltd [35.0%] | P34: Central Sulawesi | Q34: Sulawesi Tengah | R34: yes
A35: https://www.gem.wiki/Wanxiang_Nickel_Indonesia_power_station | B35: Wanxiang Nickel Indonesia Phase II Unit 1 | C35: G100001093528 | D35: (new entry) | E35: Captive | F35: Nickel | G35: 200 | I35: pre-permit | M35: -2.730952 | N35: 122.03062 | O35: PT Wanxiang Steel Indonesia [100.0%] | P35: Central Sulawesi | Q35: Sulawesi Tengah | R35: yes
A36: https://www.gem.wiki/Wanxiang_Nickel_Indonesia_power_station | B36: Wanxiang Nickel Indonesia Phase II Unit 2 | C36: G100001093529 | D36: (new entry) | E36: Captive | F36: Nickel | G36: 200 | I36: pre-permit | M36: -2.730952 | N36: 122.03062 | O36: PT Wanxiang Steel Indonesia [100.0%] | P36: Central Sulawesi | Q36: Sulawesi Tengah | R36: yes
A37: https://www.gem.wiki/Tanjung_Sauh_power_station | B37: Tanjung Sauh Unit 1 | C37: G100001093559 | D37: (new entry) | E37: Captive | F37: Industrial park | G37: 150 | H37: 2026 | I37: pre-permit | M37: 1.0614475 | N37: 104.17374 | O37: PT Nusatama Properta Panbil | P37: Riau Islands | Q37: Kepulauan Riau | R37: yes
A38: https://www.gem.wiki/Tanjung_Sauh_power_station | B38: Tanjung Sauh Unit 2 | C38: G100001093560 | D38: (new entry) | E38: Captive | F38: Industrial park | G38: 150 | H38: 2027 | I38: pre-permit | M38: 1.0614475 | N38: 104.17374 | O38: PT Nusatama Properta Panbil | P38: Riau Islands | Q38: Kepulauan Riau | R38: yes
A39: https://www.gem.wiki/Mempawah_SGAR_power_station | B39: Mempawah SGAR Unit 1 | C39: G100001094663 | D39: (new entry) | E39: Captive | F39: Aluminum | G39: 200 | H39: 2028 | I39: pre-permit | M39: 0.36455793 | N39: 108.95568 | O39: PT Bukit Asam Tbk [100.0%] | P39: West Kalimantan | Q39: Kalimantan Barat | R39: yes
A40: https://www.gem.wiki/Mempawah_SGAR_power_station | B40: Mempawah SGAR Unit 2 | C40: G100001094664 | D40: (new entry) | E40: Captive | F40: Aluminum | G40: 200 | H40: 2028 | I40: pre-permit | M40: 0.36455793 | N40: 108.95568 | O40: PT Bukit Asam Tbk [100.0%] | P40: West Kalimantan | Q40: Kalimantan Barat | R40: yes
A41: https://www.gem.wiki/Mempawah_SGAR_power_station | B41: Mempawah SGAR Unit 3 | C41: G100001094665 | D41: (new entry) | E41: Captive | F41: Aluminum | G41: 200 | H41: 2028 | I41: pre-permit | M41: 0.36455793 | N41: 108.95568 | O41: PT Bukit Asam Tbk [100.0%] | P41: West Kalimantan | Q41: Kalimantan Barat | R41: yes
A42: https://www.gem.wiki/Mempawah_SGAR_power_station | B42: Mempawah SGAR Unit 4 | C42: G100001094666 | D42: (new entry) | E42: Captive | F42: Aluminum | G42: 200 | H42: 2028 | I42: pre-permit | M42: 0.36455793 | N42: 108.95568 | O42: PT Bukit Asam Tbk [100.0%] | P42: West Kalimantan | Q42: Kalimantan Barat | R42: yes
A43: https://www.gem.wiki/Mempawah_SGAR_power_station | B43: Mempawah SGAR Unit 5 | C43: G100001094667 | D43: (new entry) | E43: Captive | F43: Aluminum | G43: 200 | H43: 2028 | I43: pre-permit | M43: 0.36455793 | N43: 108.95568 | O43: PT Bukit Asam Tbk [100.0%] | P43: West Kalimantan | Q43: Kalimantan Barat | R43: yes
A44: https://www.gem.wiki/Mempawah_SGAR_power_station | B44: Mempawah SGAR Unit 6 | C44: G100001094668 | D44: (new entry) | E44: Captive | F44: Aluminum | G44: 200 | H44: 2028 | I44: pre-permit | M44: 0.36455793 | N44: 108.95568 | O44: PT Bukit Asam Tbk [100.0%] | P44: West Kalimantan | Q44: Kalimantan Barat | R44: yes
A45: https://www.gem.wiki/Andalas_Cement_power_station | B45: Andalas Cement | C45: <30 MW | D45: <30 MW | E45: Captive | F45: Cement | G45: 29 | H45: 2007 | I45: operating | J45: operating | K45: operating | L45: operating | M45: 5.453465 | N45: 95.24653 | O45: PT Semen Indonesia | P45: Aceh | Q45: Aceh | R45: no
A46: https://www.gem.wiki/Ketapang_Smelter_power_station | B46: Ketapang Smelter Phase I, Unit 1 | C46: <30 MW | D46: <30 MW | E46: Captive | F46: Nickel | G46: 25 | H46: 2016 | I46: operating | J46: operating | K46: operating | L46: operating | M46: -2.36618 | N46: 110.1573 | O46: China Hongqiao Group; Harita Group | P46: West Kalimantan | Q46: Kalimantan Barat | R46: no
A47: https://www.gem.wiki/Ketapang_Smelter_power_station | B47: Ketapang Smelter Phase I, Unit 2 | C47: <30 MW | D47: <30 MW | E47: Captive | F47: Nickel | G47: 25 | H47: 2016 | I47: operating | J47: operating | K47: operating | L47: operating | M47: -2.36618 | N47: 110.1573 | O47: China Hongqiao Group; Harita Group | P47: West Kalimantan | Q47: Kalimantan Barat | R47: no
A48: https://www.gem.wiki/Tonasa_Cement_Plant_power_station | B48: Tonasa Cement Plant power station Phase IV Unit 1 | C48: <30 MW | D48: <30 MW | E48: Captive | F48: Cement | G48: 25 | H48: 1996 | I48: operating | J48: operating | K48: operating | L48: operating | M48: -4.81671 | N48: 119.5017 | O48: PT Semen Indonesia | P48: South Sulawesi | Q48: Sulawesi Selatan | R48: no
A49: https://www.gem.wiki/Tonasa_Cement_Plant_power_station | B49: Tonasa Cement Plant power station Phase IV Unit 2 | C49: <30 MW | D49: <30 MW | E49: Captive | F49: Cement | G49: 25 | H49: 1996 | I49: operating | J49: operating | K49: operating | L49: operating | M49: -4.81671 | N49: 119.5017 | O49: PT Semen Indonesia | P49: South Sulawesi | Q49: Sulawesi Selatan | R49: no
A50: https://www.gem.wiki/Xinyi_Group_captive_power_station | B50: Xinyi Group captive | C50: G100001000232 | D50: G100001000232 | E50: Captive | F50: Industrial park | G50: 2500 | I50: announced | J50: announced | K50: announced | L50: announced | M50: 0.86008 | N50: 104.1801 | O50: Xinyi Glass Holdings | P50: Riau Islands | Q50: Kepulauan Riau | R50: yes
A51: https://www.gem.wiki/Weda_Bay_power_station | B51: Weda Bay Unit 13 | C51: G100001000640 | D51: G100001000640 | E51: Captive | F51: Nickel | G51: 380 | H51: 2024 | I51: operating | J51: construction | K51: construction | L51: construction | M51: 0.476161 | N51: 128.0081 | O51: Tsingshan Holding Group Co Ltd | P51: North Maluku | Q51: Maluku Utara | R51: no
A52: https://www.gem.wiki/Weda_Bay_power_station | B52: Weda Bay Unit 14 | C52: G100001000641 | D52: G100001000641 | E52: Captive | F52: Nickel | G52: 380 | H52: 2025 | I52: operating | J52: construction | K52: construction | L52: construction | M52: 0.476161 | N52: 128.0081 | O52: Tsingshan Holding Group Co Ltd | P52: North Maluku | Q52: Maluku Utara | R52: no
A53: https://www.gem.wiki/PT_IHIP_power_station | B53: PT IHIP Unit 1 | C53: G100001000642 | D53: G100001000642 | E53: Captive | F53: Industrial park | G53: 117 | H53: 2024 | I53: operating | J53: construction | K53: construction | L53: construction | M53: -2.28754 | N53: 121.772 | O53: PT Baoshuo Taman Industry Investment Group | P53: Central Sulawesi | Q53: Sulawesi Tengah | R53: no
A54: https://www.gem.wiki/PT_IHIP_power_station | B54: PT IHIP Unit 2 | C54: G100001000643 | D54: G100001000643 | E54: Captive | F54: Industrial park | G54: 117 | H54: 2024 | I54: operating | J54: construction | K54: construction | L54: construction | M54: -2.28754 | N54: 121.772 | O54: PT Baoshuo Taman Industry Investment Group | P54: Central Sulawesi | Q54: Sulawesi Tengah | R54: no
A55: https://www.gem.wiki/PT_IHIP_power_station | B55: PT IHIP Unit 3 | C55: G100001000644 | D55: G100001000644 | E55: Captive | F55: Industrial park | G55: 116 | H55: 2024 | I55: operating | J55: construction | K55: construction | L55: construction | M55: -2.28754 | N55: 121.772 | O55: PT Baoshuo Taman Industry Investment Group | P55: Central Sulawesi | Q55: Sulawesi Tengah | R55: no
A56: https://www.gem.wiki/PT_Tianshan_Alumina_power_station | B56: PT Tianshan Alumina power station | C56: G100001018057 | D56: G100001018057 | E56: Captive | F56: Aluminum | G56: 160 | I56: permitted | J56: pre-permit | K56: unknown | L56: unknown | M56: -0.55415 | N56: 104.4297 | O56: Tianshan Alumina PT | P56: Riau Islands | Q56: Kepulauan Riau | R56: yes
A57: https://www.gem.wiki/Adaro_East_Kalimantan_power_station | B57: Adaro East Kalimantan Unit 1 | C57: G100000100037 | D57: G100037 | E57: Captive | F57: Coal mining - Power generation | G57: 300 | H57: 0 | I57: cancelled | J57: cancelled | K57: cancelled | L57: cancelled | M57: 0.1 | N57: 116.4 | O57: China Energy Investment Corp; PT Adaro Power | P57: East Kalimantan | Q57: Kalimantan Timur | R57: no
A58: https://www.gem.wiki/Adaro_East_Kalimantan_power_station | B58: Adaro East Kalimantan Unit 2 | C58: G100000100038 | D58: G100038 | E58: Captive | F58: Coal mining - Power generation | G58: 300 | H58: 0 | I58: cancelled | J58: cancelled | K58: cancelled | L58: cancelled | M58: 0.1 | N58: 116.4 | O58: China Energy Investment Corp; PT Adaro Power | P58: East Kalimantan | Q58: Kalimantan Timur | R58: no
A59: https://www.gem.wiki/Amamapare_Port_power_station | B59: Amamapare Port Unit 1 | C59: G100000100142 | D59: G100142 | E59: Captive | F59: Gold - Copper | G59: 65 | H59: 1998 | I59: operating | J59: operating | K59: operating | L59: operating | M59: -4.82775 | N59: 136.8391 | O59: FreePort-McMoran Inc [85.7%] | P59: Papua | Q59: Papua | R59: no
A60: https://www.gem.wiki/Amamapare_Port_power_station | B60: Amamapare Port Unit 2 | C60: G100000100143 | D60: G100143 | E60: Captive | F60: Gold - Copper | G60: 65 | H60: 1998 | I60: operating | J60: operating | K60: operating | L60: operating | M60: -4.82775 | N60: 136.8391 | O60: FreePort-McMoran Inc [85.7%] | P60: Papua | Q60: Papua | R60: no
A61: https://www.gem.wiki/Amamapare_Port_power_station | B61: Amamapare Port Unit 3 | C61: G100000100144 | D61: G100144 | E61: Captive | F61: Gold - Copper | G61: 65 | H61: 1999 | I61: operating | J61: operating | K61: operating | L61: operating | M61: -4.82775 | N61: 136.8391 | O61: FreePort-McMoran Inc [85.7%] | P61: Papua | Q61: Papua | R61: no
A62: https://www.gem.wiki/Asahimas_Chemical_power_station | B62: Asahimas Chemical Unit 1 | C62: G100000100367 | D62: G100367 | E62: Captive | F62: Chemicals | G62: 150 | H62: 2019 | I62: operating | J62: operating | K62: operating | L62: operating | M62: -6.02475 | N62: 105.9426 | O62: AGC Inc [52.5%]; Ableman Finance [18.0%]; Rodamas [18.0%]; Mitsubishi Corporation Energy Solutions [11.5%] | P62: Banten | Q62: Banten | R62: no
A63: https://www.gem.wiki/Astratel_power_station | B63: Astratel Phase I | C63: G100000100391 | D63: G100391 | E63: Captive | F63: Coal mining - Power generation | G63: 100 | H63: 0 | I63: cancelled | J63: cancelled | K63: cancelled | L63: cancelled | M63: -2.75 | N63: 103.8333 | O63: Astra International | R63: no
A64: https://www.gem.wiki/Bandung_Indosyntec_power_station | B64: Bandung Indosyntec Unit 1 | C64: G100000100505 | D64: G100505 | E64: Captive | F64: Textile | G64: 30 | H64: 2004 | I64: operating | J64: operating | K64: operating | L64: operating | M64: -6.9705 | N64: 107.6058 | O64: Lucky Height Resources Ltd [27.8%]; Gold Gazelle Profits Corp [19.6%]; PT Panasia Synthetic Abadi [19.4%]; Ortega Management Ltd [10.0%]; Mercury Capital International Inc [9.7%]; Prime Invesco Ltd [9.5%] | P64: West Java | Q64: Jawa Barat | R64: no
A65: https://www.gem.wiki/Batu_Hijau_power_station | B65: Batu Hijau Unit 1 | C65: G100000100662 | D65: G100662 | E65: Captive | F65: Gold - Copper | G65: 31 | H65: 1999 | I65: operating | J65: operating | K65: operating | L65: operating | M65: -8.90117 | N65: 116.7382 | O65: Newmont Corp | P65: West Nusa Tenggara | Q65: Nusa Tenggara Barat | R65: no
A66: https://www.gem.wiki/Batu_Hijau_power_station | B66: Batu Hijau Unit 2 | C66: G100000100663 | D66: G100663 | E66: Captive | F66: Gold - Copper | G66: 31 | H66: 1999 | I66: operating | J66: operating | K66: operating | L66: operating | M66: -8.90117 | N66: 116.7382 | O66: Newmont Corp | P66: West Nusa Tenggara | Q66: Nusa Tenggara Barat | R66: no
A67: https://www.gem.wiki/Batu_Hijau_power_station | B67: Batu Hijau Unit 3 | C67: G100000100664 | D67: G100664 | E67: Captive | F67: Gold - Copper | G67: 31 | H67: 1999 | I67: operating | J67: operating | K67: operating | L67: operating | M67: -8.90117 | N67: 116.7382 | O67: Newmont Corp | P67: West Nusa Tenggara | Q67: Nusa Tenggara Barat | R67: no
A68: https://www.gem.wiki/Batu_Hijau_power_station | B68: Batu Hijau Unit 4 | C68: G100000100665 | D68: G100665 | E68: Captive | F68: Gold - Copper | G68: 31 | H68: 1999 | I68: operating | J68: operating | K68: operating | L68: operating | M68: -8.90117 | N68: 116.7382 | O68: Newmont Corp | P68: West Nusa Tenggara | Q68: Nusa Tenggara Barat | R68: no
A69: https://www.gem.wiki/Cikarang_Babelan_power_station | B69: Cikarang Babelan Unit 1 | C69: G100000101579 | D69: G101579 | E69: Captive | F69: Power generation | G69: 140 | H69: 2017 | I69: operating | J69: operating | K69: operating | L69: operating | M69: -6.11607 | N69: 107.052 | O69: PT Cikarang Listrindo [100.0%] | P69: West Java | Q69: Jawa Barat | R69: no
A70: https://www.gem.wiki/Cikarang_Babelan_power_station | B70: Cikarang Babelan Unit 2 | C70: G100000101580 | D70: G101580 | E70: Captive | F70: Power generation | G70: 140 | H70: 2017 | I70: operating | J70: operating | K70: operating | L70: operating | M70: -6.11607 | N70: 107.052 | O70: PT Cikarang Listrindo [100.0%] | P70: West Java | Q70: Jawa Barat | R70: no
A71: https://www.gem.wiki/Gresik_AKR_power_station | B71: Gresik AKR Unit 1 | C71: G100000103134 | D71: G103134 | E71: Captive | F71: Industrial park | G71: 330 | H71: 0 | I71: cancelled | J71: cancelled | K71: cancelled | L71: cancelled | M71: -7.159 | N71: 112.642 | O71: AKR Corp | P71: East Java | Q71: Jawa Timur | R71: no
A72: https://www.gem.wiki/Gresik_AKR_power_station | B72: Gresik AKR Unit 2 | C72: G100000103135 | D72: G103135 | E72: Captive | F72: Industrial park | G72: 330 | H72: 0 | I72: cancelled | J72: cancelled | K72: cancelled | L72: cancelled | M72: -7.159 | N72: 112.642 | O72: AKR Corp | P72: East Java | Q72: Jawa Timur | R72: no
A73: https://www.gem.wiki/Indarung_Cement_power_station | B73: Indarung Cement | C73: G100000104834 | D73: G104834 | E73: Captive | F73: Cement | G73: 100 | H73: 0 | I73: cancelled | J73: cancelled | K73: cancelled | L73: cancelled | M73: -0.95006 | N73: 100.4695 | O73: PT Semen Indonesia | P73: West Sumatra | Q73: Sumatra Barat | R73: no
A74: https://www.gem.wiki/Jababeka_KIP_power_station | B74: Jababeka KIP | C74: G100000104935 | D74: G104935 | E74: Captive | F74: Industrial park | G74: 660 | H74: 0 | I74: cancelled | J74: cancelled | K74: cancelled | L74: cancelled | M74: -6.89575 | N74: 110.2403 | O74: Jababeka; Sembcorp Industries Ltd | P74: Central Java | Q74: Jawa Tengah | R74: no
A75: https://www.gem.wiki/Jambi_Tebo_power_station | B75: Jambi Tebo Unit 1 | C75: G100000104953 | D75: G104953 | E75: Captive | F75: Coal mining - Power generation | G75: 200 | H75: 0 | I75: cancelled | J75: cancelled | K75: cancelled | L75: cancelled | M75: -1.39 | N75: 102.42 | O75: Korea Electric Power Corp [100.0%] | P75: Jambi | Q75: Jambi | R75: no
... A247: https://www.gem.wiki/PT_Halmahera_Persada_Lygend_Nickel_Smelter_power_station | B247: PT Halmahera Persada Lygend Nickel Smelter Phase III, Unit 6 | C247: G100000115356 | D247: G115356 | E247: Captive | F247: Nickel | G247: 380 | H247: 2025 | I247: operating | J247: construction | K247: pre-permit | L247: pre-permit | M247: -1.56143 | N247: 127.421 | O247: Harita Group [63.1%]; Ningbo Lygend [36.9%] | P247: Maluku | Q247: Maluku | R247: no
A248: https://www.gem.wiki/PT_Halmahera_Persada_Lygend_Nickel_Smelter_power_station | B248: PT Halmahera Persada Lygend Nickel Smelter Phase III Unit 3 | C248: G100000115357 | D248: G115357 | E248: Captive | F248: Nickel | G248: 380 | I248: construction | J248: construction | K248: pre-permit | L248: pre-permit | M248: -1.5614331 | N248: 127.42103 | O248: Ningbo Lygend [36.9%]; Harita Group | P248: Maluku | Q248: Maluku | R248: no
A249: https://www.gem.wiki/PT_Halmahera_Persada_Lygend_Nickel_Smelter_power_station | B249: PT Halmahera Persada Lygend Nickel Smelter Phase III Unit 4 | C249: G100000115358 | D249: G115358 | E249: Captive | F249: Nickel | G249: 380 | I249: construction | J249: pre-permit | K249: pre-permit | L249: pre-permit | M249: -1.5614331 | N249: 127.42103 | O249: Ningbo Lygend [36.9%]; Harita Group | P249: Maluku | Q249: Maluku | R249: no
A250: https://www.gem.wiki/PT_Halmahera_Persada_Lygend_Nickel_Smelter_power_station | B250: PT Halmahera Persada Lygend Nickel Smelter Phase I, Unit 3 | C250: G100000115359 | D250: G115359 | E250: Captive | F250: Nickel | G250: 60 | H250: 2023 | I250: operating | J250: construction | K250: construction | L250: construction | M250: -1.53615 | N250: 127.416 | O250: Harita Group [63.1%]; Ningbo Lygend [36.9%] | P250: Maluku | Q250: Maluku | R250: no
A251: https://www.gem.wiki/Sulawesi_Labota_power_station | B251: Sulawesi Labota Unit 7 | C251: G100000115360 | D251: G115360 | E251: Captive | F251: Nickel | G251: 380 | H251: 2023 | I251: operating | J251: operating | K251: operating | L251: operating | M251: -2.86883 | N251: 122.1693 | O251: Dingxin Group [55.0%]; PT Bintang Delapan Group [45.0%] | P251: Central Sulawesi | Q251: Sulawesi Tengah | R251: no
A252: https://www.gem.wiki/Sulawesi_Labota_power_station | B252: Sulawesi Labota Unit 8 | C252: G100000115361 | D252: G115361 | E252: Captive | F252: Nickel | G252: 380 | H252: 2024 | I252: operating | J252: operating | K252: construction | L252: construction | M252: -2.86883 | N252: 122.1693 | O252: Dingxin Group [55.0%]; PT Bintang Delapan Group [45.0%] | P252: Central Sulawesi | Q252: Sulawesi Tengah | R252: no
A253: https://www.gem.wiki/Sulawesi_Labota_power_station | B253: Sulawesi Labota Unit 9 | C253: G100000115362 | D253: G115362 | E253: Captive | F253: Nickel | G253: 380 | H253: 2024 | I253: operating | J253: construction | K253: construction | L253: construction | M253: -2.86883 | N253: 122.1693 | O253: Dingxin Group [55.0%]; PT Bintang Delapan Group [45.0%] | P253: Central Sulawesi | Q253: Sulawesi Tengah | R253: no
A254: https://www.gem.wiki/Sulawesi_Mining_power_station | B254: Sulawesi Mining Unit 9 | C254: G100000115363 | D254: G115363 | E254: Captive | F254: Nickel | G254: 250 | H254: 2020 | I254: operating | J254: operating | K254: operating | L254: operating | M254: -2.82738 | N254: 122.1553 | O254: Eternal Tsingshan Group | P254: Central Sulawesi | Q254: Sulawesi Tengah | R254: no
A255: https://www.gem.wiki/Weda_Bay_power_station | B255: Weda Bay Unit 12 | C255: G100000115364 | D255: G115364 | E255: Captive | F255: Nickel | G255: 380 | H255: 2024 | I255: operating | J255: construction | K255: construction | L255: construction | M255: 0.476161 | N255: 128.0081 | O255: Tsingshan Holding Group Co Ltd | P255: North Maluku | Q255: Maluku Utara | R255: no
A256: https://www.gem.wiki/FAJAR_power_station | B256: FAJAR Unit 1 | C256: G100000115737 | D256: G115737 | E256: Captive | F256: Pulp and paper | G256: 55 | H256: 2017 | I256: operating | J256: operating | K256: operating | L256: operating | M256: -6.27265 | N256: 107.124 | O256: PT Fajar Surya Wisesa [100.0%] | P256: West Java | Q256: Jawa Barat | R256: no
A257: https://www.gem.wiki/AlamTri_Aluminum_Smelter_power_station | B257: AlamTri Aluminum Smelter Phase I Unit 1 | C257: G100000115748 | D257: G115748 | E257: Captive | F257: Aluminum | G257: 150 | H257: 2026 | I257: construction | J257: pre-permit | K257: pre-permit | L257: pre-permit | M257: 2.4946822 | N257: 117.9002 | O257: PT Alamtri Resources Indonesia Tbk [84.0%]; PT Cita Mineral Investindo Tbk [16.0%] | P257: North Kalimantan | Q257: Kalimantan Utara | R257: no
A258: https://www.gem.wiki/AlamTri_Aluminum_Smelter_power_station | B258: AlamTri Aluminum Smelter Phase II Unit 1 | C258: G100000115905 | D258: G115905 | E258: Captive | F258: Aluminum | G258: 150 | H258: 2026 | I258: construction | J258: announced | K258: announced | L258: announced | M258: 2.4946822 | N258: 117.9002 | O258: PT Alamtri Resources Indonesia Tbk [84.0%]; PT Cita Mineral Investindo Tbk [16.0%] | P258: North Kalimantan | Q258: Kalimantan Utara | R258: no
A259: https://www.gem.wiki/Amman_Mineral_power_station | B259: Amman Mineral Unit 5 | C259: G100001053499 | D259: G1053499 | E259: Captive | F259: Gold - Copper | G259: 150 | H259: 2024 | I259: cancelled | J259: cancelled | K259: cancelled | L259: cancelled | M259: -8.90122 | N259: 116.7393 | O259: Amman Mineral Nusa Tenggara [100.0%] | P259: West Nusa Tenggara | Q259: Nusa Tenggara Barat | R259: no
A260: https://www.gem.wiki/Amman_Mineral_power_station | B260: Amman Mineral Unit 6 | C260: G100001053501 | D260: G1053501 | E260: Captive | F260: Gold - Copper | G260: 150 | H260: 2024 | I260: cancelled | J260: cancelled | K260: cancelled | L260: cancelled | M260: -8.90122 | N260: 116.7393 | O260: Amman Mineral Nusa Tenggara [100.0%] | P260: West Nusa Tenggara | Q260: Nusa Tenggara Barat | R260: no

Sheet <30 MW_captive
A1: Plant name | B1: Unit name | C1: Capacity (MW) | D1: Status | E1: Fuel | F1: Owner | G1: Start year | H1: Captive | I1: Subnational unit (province, state) | J1: Coordinates | K1: Location accuracy | L1: Source link(s)
A2: Lati power station | B2: Unit 1 | C2: 7 | D2: Operating | E2: Coal | F2: PT Indo Pusaka Berau | G2: 2004 | H2: Mining | I2: East Kalimantan | J2: 2.2146149973028324, 117.6189402665326 | K2: Exact | L2: https://ipb.co.id/sekilas-indo-pusaka-berau/
A3: Lati power station | B3: Unit 2 | C3: 7 | D3: Operating | E3: Coal | F3: PT Indo Pusaka Berau | G3: 2004 | H3: Mining | I3: East Kalimantan | J3: 2.2146149973028324, 117.6189402665326 | K3: Exact | L3: https://ipb.co.id/sekilas-indo-pusaka-berau/
A4: Lati power station | B4: Unit 3 | C4: 7 | D4: Operating | E4: Coal | F4: PT Indo Pusaka Berau | G4: 2004 | H4: Mining | I4: East Kalimantan | J4: 2.2146149973028324, 117.6189402665326 | K4: Exact | L4: https://ipb.co.id/sekilas-indo-pusaka-berau/
A5: PT BAI power station | B5: Unit 1 | C5: 25 | E5: Coal | F5: PT Borneo Alumina Indonesia | H5: Aluminum | I5: West Kalimantan | J5: 0.5153512864353804, 108.95264585235861 | K5: Exact | L5: https://indonesiabusinesspost.com/104/Politics/inalum-operating-to-go-public-in-2023
A6: PT BAI power station | B6: Unit 2 | C6: 25 | E6: Coal | F6: PT Borneo Alumina Indonesia | H6: Aluminum | I6: West Kalimantan | J6: 0.5153512864353804, 108.95264585235861 | K6: Exact | L6: https://indonesiabusinesspost.com/104/Politics/inalum-operating-to-go-public-in-2023
A7: PT BAI power station | B7: Unit 3 | C7: 25 | E7: Coal | F7: PT Borneo Alumina Indonesia | H7: Aluminum | I7: West Kalimantan | J7: 0.5153512864353804, 108.95264585235861 | K7: Exact | L7: https://indonesiabusinesspost.com/104/Politics/inalum-operating-to-go-public-in-2023
A8: PT Berkah Manis Makmur power station | B8: Unit 1 | C8: 6 | D8: Operating | E8: Coal | F8: PT Berkah Manis Makmur | H8: Sugar | I8: Banten | J8: -6.209590332005053, 106.3723391354899 | K8: Exact | L8: https://maps.app.goo.gl/dMXiqBD5jMwnxuCu7
A9: PT Berkah Manis Makmur power station | B9: Unit 2 | C9: 6 | D9: Operating | E9: Coal | F9: PT Berkah Manis Makmur | H9: Sugar | I9: Banten | J9: -6.209590332005053, 106.3723391354899 | K9: Exact | L9: https://maps.app.goo.gl/dMXiqBD5jMwnxuCu7
A10: PT CKP power station | B10: Unit 1 | C10: 18 | D10: Operating | E10: Coal | F10: PT Citra Kusuma Perdana | G10: 2017 | H10: Mining | I10: West Java | J10: -6.486950239812899, 107.38873800556564 | K10: Exact | L10: https://economictimes.indiatimes.com/industry/energy/power/bhel-commissions-coal-fired-power-plant-in-indonesia/articleshow/62038372.cms?from=mdr
A11: PT CKP power station | B11: Unit 2 | C11: 18 | D11: Operating | E11: Coal | F11: PT Citra Kusuma Perdana | G11: 2017 | H11: Mining | I11: West Java | J11: -6.486950239812899, 107.38873800556564 | K11: Exact | L11: https://economictimes.indiatimes.com/industry/energy/power/bhel-commissions-coal-fired-power-plant-in-indonesia/articleshow/62038372.cms?from=mdr
A12: PT CKP power station | B12: Unit 3 | C12: 18 | D12: Operating | E12: Coal | F12: PT Citra Kusuma Perdana | G12: 2017 | H12: Mining | I12: West Java | J12: -6.486950239812899, 107.38873800556564 | K12: Exact | L12: https://economictimes.indiatimes.com/industry/energy/power/bhel-commissions-coal-fired-power-plant-in-indonesia/articleshow/62038372.cms?from=mdr
A13: PT CNSC power station | B13: Unit 1 | C13: 20 | D13: Operating | E13: Coal | F13: PT Conch North Sulawesi Cement | G13: 2018 | H13: Cement | I13: North Sulawesi | J13: 0.8976684446698492, 124.08053192411424 | K13: Exact | L13: https://www.scribd.com/document/739409086/MCC-Company-Profile#content=query:20%20mw,pageNum:55,indexOnPage:0,bestMatch:false, https://maps.app.goo.gl/nQ6mAnaS2Po323h56
A14: PT CNSC power station | B14: Unit 2 | C14: 20 | D14: Operating | E14: Coal | F14: PT Conch North Sulawesi Cement | G14: 2018 | H14: Cement | I14: North Sulawesi | J14: 0.8976684446698492, 124.08053192411424 | K14: Exact | L14: https://www.scribd.com/document/739409086/MCC-Company-Profile#content=query:20%20mw,pageNum:55,indexOnPage:0,bestMatch:false, https://maps.app.goo.gl/nQ6mAnaS2Po323h56
A15: PT CSKC power station | B15: Unit 1 | C15: 18 | D15: Operating | E15: Coal | F15: PT Conch South Kalimantan Cement | H15: Cement | I15: South Kalimantan | J15: -2.063045781373437, 115.56997664034856 | K15: Exact | L15: https://maps.app.goo.gl/GYBRt9AkFkKAEaPa7
A16: PT CSKC power station | B16: Unit 2 | C16: 18 | D16: Operating | E16: Coal | F16: PT Conch South Kalimantan Cement | H16: Cement | I16: South Kalimantan | J16: -2.063045781373437, 115.56997664034856 | K16: Exact | L16: https://maps.app.goo.gl/GYBRt9AkFkKAEaPa7
A17: PT CSKC power station | B17: Unit 3 | C17: 18 | D17: Operating | E17: Coal | F17: PT Conch South Kalimantan Cement | H17: Cement | I17: South Kalimantan | J17: -2.063045781373437, 115.56997664034856 | K17: Exact | L17: https://maps.app.goo.gl/GYBRt9AkFkKAEaPa7
A18: PT EPN power station | B18: Unit 1 | C18: 15 | D18: Operating | E18: Coal | F18: PT Energia Prima Nusantar | G18: 2018 | H18: Mining | I18: Central Kalimantan | J18: -0.9954357012215257, 114.39114537500676 | K18: Exact | L18: https://epnusantara.com/company-history/
A19: PT EPN power station | B19: Unit 2 | C19: 15 | D19: Operating | E19: Coal | F19: PT Energia Prima Nusantar | G19: 2018 | H19: Mining | I19: Central Kalimantan | J19: -0.9954357012215257, 114.39114537500676 | K19: Exact | L19: https://epnusantara.com/company-history/
A20: PT IFI power station | B20: Unit 1 | C20: 7.5 | D20: Operating | E20: Coal | F20: PT Indonesia Fibreboard Industry | H20: Pulp & paper | I20: South Sumatra | J20: -2.0688236398133064, 103.73635866849679 | K20: Exact | L20: https://www.idx.co.id/media/7839/ifii_prospektus-ipo-2019.pdf
A21: PT IFI power station | B21: Unit 2 | C21: 7.5 | D21: Operating | E21: Coal | F21: PT Indonesia Fibreboard Industry | H21: Pulp & paper | I21: South Sumatra | J21: -2.0688236398133064, 103.73635866849679 | K21: Exact | L21: https://www.idx.co.id/media/7839/ifii_prospektus-ipo-2019.pdf
A22: PT IM power station | B22: Unit 1 | C22: 7 | D22: Operating | E22: Coal | F22: PT Indominco Mandiri | H22: Mining | I22: East Kalimantan | J22: 0.019679561884603212, 117.47574777189999 | K22: Exact | L22: https://www.jogmec.go.jp/content/300304623.pdf
A23: PT IM power station | B23: Unit 2 | C23: 7 | D23: Operating | E23: Coal | F23: PT Indominco Mandiri | H23: Mining | I23: East Kalimantan | J23: 0.019679561884603212, 117.47574777189999 | K23: Exact | L23: https://www.jogmec.go.jp/content/300304623.pdf
A24: PT Kalimantan Powerindo power station | B24: Unit 1 | C24: 7.5 | D24: Operating | E24: Coal | F24: PT Kalimantan Powerindo | H24: Industrial area | I24: East Kalimantan | J24: -0.31945212078978413, 116.83824946721947 | K24: Exact | L24: https://prudensi.com/teror-limbah-pt-kalimantan-powerindo/
A25: PT Kalimantan Powerindo power station | B25: Unit 2 | C25: 7.5 | D25: Operating | E25: Coal | F25: PT Kalimantan Powerindo | H25: Industrial area | I25: East Kalimantan | J25: -0.31945212078978413, 116.83824946721947 | K25: Exact | L25: https://prudensi.com/teror-limbah-pt-kalimantan-powerindo/
A26: PT Kariangau Power power station | B26: Unit 1 | C26: 15 | D26: Operating | E26: Coal | F26: PT Kariangau Power | H26: Industrial area | I26: East Kalimantan | J26: -1.1988773899788665, 116.80160393318629 | K26: Exact | L26: https://info.kariangauterminal.co.id/en/kawasan-pendukung/
A27: PT Kariangau Power power station | B27: Unit 2 | C27: 15 | D27: Operating | E27: Coal | F27: PT Kariangau Power | H27: Industrial area | I27: East Kalimantan | J27: -1.1988773899788665, 116.80160393318629 | K27: Exact | L27: https://info.kariangauterminal.co.id/en/kawasan-pendukung/
A28: PT KPC power station | B28: Unit 1 | C28: 5 | D28: Operating | E28: Coal | F28: PT Kaltim Prima Coal | H28: Mining | I28: East Kalimantan | J28: 0.5492382568811944, 117.51048519074317 | K28: Approximate | L28: https://kaltimprimacoal.co.id/id/operasi/
A29: PT KPC power station | B29: Unit 2 | C29: 5 | D29: Operating | E29: Coal | F29: PT Kaltim Prima Coal | H29: Mining | I29: East Kalimantan | J29: 0.5492382568811944, 117.51048519074317 | K29: Approximate | L29: https://kaltimprimacoal.co.id/id/operasi/
A30: PT KRN power station | B30: Unit 1 | C30: 25 | D30: Operating | E30: Coal | F30: PT Kutai Refinery Nusantara | H30: Agriculture | I30: East Kalimantan | J30: -1.174668512105652, 116.79409967135324 | K30: Exact | L30: https://sda.pu.go.id/assets/uploads/files/2023_RPSDA%20WS%20Mahakam.pdf
A31: PT KRN power station | B31: Unit 2 | C31: 25 | D31: Operating | E31: Coal | F31: PT Kutai Refinery Nusantara | H31: Agriculture | I31: East Kalimantan | J31: -1.174668512105652, 116.79409967135324 | K31: Exact | L31: https://sda.pu.go.id/assets/uploads/files/2023_RPSDA%20WS%20Mahakam.pdf
A32: PT LPI power station | B32: Unit 1 | C32: 6 | F32: PT Laju Perdana Indah | H32: Sugar | I32: South Sumatra | J32: -3.857870914950383, 104.74865141111111 | K32: Exact | L32: https://maps.app.goo.gl/qKQ2mcmjAqCsABsR7
A33: PT LPI power station | B33: Unit 2 | C33: 6 | F33: PT Laju Perdana Indah | H33: Sugar | I33: South Sumatra | J33: -3.857870914950383, 104.74865141111111 | K33: Exact | L33: https://maps.app.goo.gl/qKQ2mcmjAqCsABsR7
A34: PT Makassar Tene power station | B34: Unit 1 | C34: 6 | D34: Operating | E34: Coal | F34: PT Makassar Tene | H34: Sugar | I34: South Sulawesi | J34: -5.09792814562423, 119.4743892932916 | K34: Exact | L34: https://www.scribd.com/document/414980296/PT-Makassar-Tene, https://maps.app.goo.gl/75Fp6a3VGeGMHdL19
A35: PT Makassar Tene power station | B35: Unit 2 | C35: 6 | D35: Operating | E35: Coal | F35: PT Makassar Tene | H35: Sugar | I35: South Sulawesi | J35: -5.09792814562423, 119.4743892932916 | K35: Exact | L35: https://www.scribd.com/document/414980296/PT-Makassar-Tene, https://maps.app.goo.gl/75Fp6a3VGeGMHdL19
A36: PT MSE power station | B36: Unit 1 | C36: 7.5 | D36: Operating | E36: Coal | F36: PT Mega Surya Eratama | H36: Pulp & paper | I36: East Java | J36: -7.530255608672717, 112.61923104151148 | K36: Exact | L36: https://www.msepaper.com/post/item/35/About-Us
A37: PT MSE power station | B37: Unit 2 | C37: 7.5 | D37: Operating | E37: Coal | F37: PT Mega Surya Eratama | H37: Pulp & paper | I37: East Java | J37: -7.530255608672717, 112.61923104151148 | K37: Exact | L37: https://www.msepaper.com/post/item/35/About-Us
A38: PT PAG power station | B38: Unit 1 | C38: 12 | E38: Coal | F38: PT Prima Alam Gemilang | H38: Sugar | I38: Southeast Sulawesi | J38: -4.578985004440909, 121.88151949474315 | K38: Exact | L38: https://dpmptsp.sultraprov.go.id/berita/hasil_dari_mendapingi_bkpm_ke__pt_prima_alam_gemilang_17_november_2020
A39: PT PDSU power station | B39: Unit 1 | C39: 7 | F39: PT Permata Dunia Sukses Utama | H39: Sugar | I39: Banten | J39: -6.018186378107977, 105.97565227124318 | K39: Exact | L39: https://maps.app.goo.gl/LpdSzALxAifhbPf77
A40: PT PDSU power station | B40: Unit 2 | C40: 7 | F40: PT Permata Dunia Sukses Utama | H40: Sugar | I40: Banten | J40: -6.018186378107977, 105.97565227124318 | K40: Exact | L40: https://maps.app.goo.gl/LpdSzALxAifhbPf77
A41: PT PDSU power station | B41: Unit 3 | C41: 7 | F41: PT Permata Dunia Sukses Utama | H41: Sugar | I41: Banten | J41: -6.018186378107977, 105.97565227124318 | K41: Exact | L41: https://maps.app.goo.gl/LpdSzALxAifhbPf77
A42: PT PS Guntung power station | B42: Unit 1 | C42: 7 | D42: Operating | E42: Coal | F42: PT Pulau Sambu | H42: Agriculture | I42: Riau | J42: 0.30760134405412215, 103.60605003445318 | K42: Exact | L42: https://repository.uin-suska.ac.id/62964/1/LAPORAN%20TA.pdf
A43: PT PS Kuala Enok power station | B43: Unit 1 | C43: 7 | D43: Operating | E43: Coal | F43: PT Pulau Sambu | H43: Agriculture | I43: Riau | J43: -0.5033784693027057, 103.38460321177213 | K43: Exact | L43: https://repository.uin-suska.ac.id/62964/1/LAPORAN%20TA.pdf
A44: PT Pura power station | B44: Unit 1 | C44: 7.5 | D44: Operating | E44: Coal | F44: PT Pura | H44: Pulp & paper | I44: Central Java | J44: -6.834109888305331, 110.81906222081425 | K44: Exact | L44: https://maps.app.goo.gl/QuBxewL7whe9LrX96, https://pdfcoffee.com/shandong-machinery-pdf-free.html
A45: PT Pura power station | B45: Unit 2 | C45: 7.5 | D45: Operating | E45: Coal | F45: PT Pura | H45: Pulp & paper | I45: Central Java | J45: -6.834109888305331, 110.81906222081425 | K45: Exact | L45: https://maps.app.goo.gl/QuBxewL7whe9LrX96, https://pdfcoffee.com/shandong-machinery-pdf-free.html
A46: PT PUSRI power station | B46: Unit 1 | C46: 11.5 | D46: Operating | E46: Coal | F46: PT Pupuk Sriwidjaja Palembang | G46: 2016 | H46: Fertilizer | I46: South Sumatra | J46: -2.9784011826312593, 104.80739123557292 | K46: Exact | L46: https://pusri.co.id/id/news/detail/pt-pusri-kaji-revitalisasi-pabrik-pupuk
A47: PT PUSRI power station | B47: Unit 2 | C47: 11.5 | D47: Operating | E47: Coal | F47: PT Pupuk Sriwidjaja Palembang | G47: 2016 | H47: Fertilizer | I47: South Sumatra | J47: -2.9784011826312593, 104.80739123557292 | K47: Exact | L47: https://pusri.co.id/id/news/detail/pt-pusri-kaji-revitalisasi-pabrik-pupuk
A48: PT RSUP power station | B48: Unit 1 | C48: 7 | D48: Operating | E48: Coal | F48: PT Pulau Sambu | H48: Agriculture | I48: Riau | J48: 0.4203329131172641, 103.54941887192622 | K48: Exact | L48: https://repository.uin-suska.ac.id/62964/1/LAPORAN%20TA.pdf
A49: PT RUM power station | B49: Unit 1 | C49: 15 | D49: Mothballed | E49: Coal | F49: PT Rayon Utama Makmur | H49: Textiles | I49: Central Java | J49: -7.728319037282294, 110.89947049926074 | K49: Exact | L49: https://ariefsyams.blogspot.com/2015/06/pt-rayon-usaha-makmur.html, https://www.tempo.co/lingkungan/pabrik-rayon-untuk-sritex-disebut-stop-operasi-2-tahun-terakhir-masih-sebar-bau-tak-sedap-1162056
A50: PT RUM power station | B50: Unit 2 | C50: 15 | D50: Mothballed | E50: Coal | F50: PT Rayon Utama Makmur | H50: Textiles | I50: Central Java | J50: -7.728319037282294, 110.89947049926074 | K50: Exact | L50: https://ariefsyams.blogspot.com/2015/06/pt-rayon-usaha-makmur.html, https://www.tempo.co/lingkungan/pabrik-rayon-untuk-sritex-disebut-stop-operasi-2-tahun-terakhir-masih-sebar-bau-tak-sedap-1162056
A51: PT SBI power station | B51: Unit 1 | C51: 7.5 | D51: Operating | E51: Coal | F51: PT Surya Borneo Industri | H51: Agriculture | I51: Central Kalimantan | J51: -2.713404423385079, 111.75316393944806 | K51: Exact | L51: https://maps.app.goo.gl/W7iqxrV8ztCNkWzD9
A52: PT SBI power station | B52: Unit 2 | C52: 7.5 | D52: Operating | E52: Coal | F52: PT Surya Borneo Industri | H52: Agriculture | I52: Central Kalimantan | J52: -2.713404423385079, 111.75316393944806 | K52: Exact | L52: https://maps.app.goo.gl/W7iqxrV8ztCNkWzD9
A53: PT SDO power station | B53: Unit 1 | C53: 16 | D53: Operating | E53: Coal | F53: PT Sari Dumai Oleo | H53: Agriculture | I53: Riau | J53: 1.7866821870124683, 101.352726505208 | K53: Exact | L53: https://eprints.polbeng.ac.id/id/eprint/2318/4/4.%20KP-5404211376-Full%20Text.pdf
A54: PT SDO power station | B54: Unti 2 | C54: 16 | D54: Operating | E54: Coal | F54: PT Sari Dumai Oleo | H54: Agriculture | I54: Riau | J54: 1.7866821870124683, 101.352726505208 | K54: Exact | L54: https://eprints.polbeng.ac.id/id/eprint/2318/4/4.%20KP-5404211376-Full%20Text.pdf
A55: PT SDS power station | B55: Unit 1 | C55: 18 | D55: Operating | F55: PT Sari Dumai Sejati | H55: Agriculture | I55: Riau | J55: 1.7590804028410088, 101.36002185236417 | K55: Exact | L55: https://maps.app.goo.gl/KR5VtuCa8tF1vpcV9
A56: PT SDS power station | B56: Unit 2 | C56: 18 | D56: Operating | F56: PT Sari Dumai Sejati | H56: Agriculture | I56: Riau | J56: 1.7590804028410088, 101.36002185236417 | K56: Exact | L56: https://maps.app.goo.gl/KR5VtuCa8tF1vpcV9
A57: PT SDS power station | B57: Unit 3 | C57: 18 | D57: Operating | F57: PT Sari Dumai Sejati | H57: Agriculture | I57: Riau | J57: 1.7590804028410088, 101.36002185236417 | K57: Exact | L57: https://maps.app.goo.gl/KR5VtuCa8tF1vpcV9
A58: PT Sinergy Power Source power station | B58: Unit 1 | C58: 10 | D58: Operating | E58: Coal | F58: PT Sinergy Power Source | H58: Pulp & paper | I58: East Java | J58: -7.515664274705495, 112.60027856669646 | K58: Exact | L58: https://journal2.um.ac.id/index.php/fespe/article/view/29377/10200, https://maps.app.goo.gl/LktEHg7TCxpkNa9x6
A59: PT Sinergy Power Source power station | B59: Unit 2 | C59: 10 | D59: Operating | E59: Coal | F59: PT Sinergy Power Source | H59: Pulp & paper | I59: East Java | J59: -7.515664274705495, 112.60027856669646 | K59: Exact | L59: https://journal2.um.ac.id/index.php/fespe/article/view/29377/10200, https://maps.app.goo.gl/LktEHg7TCxpkNa9x6
A60: PT Sinergy Power Source power station | B60: Unit 3 | C60: 10 | D60: Operating | E60: Coal | F60: PT Sinergy Power Source | H60: Pulp & paper | I60: East Java | J60: -7.515664274705495, 112.60027856669646 | K60: Exact | L60: https://journal2.um.ac.id/index.php/fespe/article/view/29377/10200, https://maps.app.goo.gl/LktEHg7TCxpkNa9x6
A61: PT Suparma power station | B61: Unit 1 | C61: 27 | D61: Operating | F61: PT Suparma | G61: 1997 | H61: Pulp & paper | I61: East Java | J61: -7.344634314830135, 112.6746560268386 | K61: Exact | L61: https://www.mvbindonesia.com/post/pt-suparma-tbk-environmentally-friendly-company, https://maps.app.goo.gl/iusKztqX5JQiwnq26
A62: PT Wilmar Nabati Indonesia power station | B62: Unit 1 | C62: 3 | D62: Operating | E62: Coal | F62: PT Wilmar Nabati Indonesia | H62: Agriculture | I62: East Java | J62: -7.178049662183172, 112.66659596202389 | K62: Exact | L62: https://maps.app.goo.gl/8QGJ3GPPxwpA68EX7
A63: PT Wilmar Nabati Indonesia power station | B63: Unit 2 | C63: 10 | D63: Operating | E63: Coal | F63: PT Wilmar Nabati Indonesia | H63: Agriculture | I63: East Java | J63: -7.178049662183172, 112.66659596202389 | K63: Exact | L63: https://maps.app.goo.gl/8QGJ3GPPxwpA68EX7

Sheet <30 MW_PLN
A1: GEM unit/phase ID | B1: Owner | C1: Capacity (MW) | D1: COD | E1: Latitude | F1: Longitude | G1: Parent | H1: Status Jul 2025
A3: Kendari Unit 2 | B3: PLN | C3: 10 | D3: 2012 | E3: -3.895018 | F3: 122.53721 | G3: PLN | H3: operating
A4: Ende Unit 1 | B4: PLN | C4: 7 | D4: 2013 | E4: -8.8786 | F4: 121.7051 | G4: PLN | H4: operating
A5: Ende Unit 2 | B5: PLN | C5: 7 | D5: 2013 | E5: -8.8786 | F5: 121.7051 | G5: PLN | H5: operating
A6: Bolok Unit 1 | B6: PLN | C6: 16.5 | D6: 2013 | E6: -10.239179 | F6: 123.49025 | G6: PLN | H6: operating
A7: Bolok Unit 2 | B7: PLN | C7: 16.5 | D7: 2013 | E7: -10.239179 | F7: 123.49025 | G7: PLN | H7: operating
A8: Kendari Unit 1 | B8: PLN | C8: 10 | D8: 2014 | E8: -3.895018 | F8: 122.53721 | G8: PLN | H8: operating
A9: Kendari Unit 3 | B9: PLN | C9: 10 | D9: 2014 | E9: -3.895018 | F9: 122.53721 | G9: PLN | H9: operating
A10: Tembilok Unit 1 | B10: IPP | C10: 6 | D10: 2020 | E10: -1.7814812 | F10: 109.9524 | G10: PT Ketapang Arya Power | H10: operating
A11: Tembilok Unit 2 | B11: IPP | C11: 6 | D11: 2020 | E11: -1.7814812 | F11: 109.9524 | G11: PT Ketapang Arya Power | H11: operating
A12: Tanjung Batu Unit 1 | B12: PLN | C12: 4 | D12: 2015 | E12: 2.175861 | F12: 117.48461 | G12: PT PLN (Persero) | H12: operating
A13: Tanjung Batu Unit 2 | B13: PLN | C13: 4 | D13: 2016 | E13: 2.175861 | F13: 117.48461 | G13: PT PLN (Persero) | H13: operating
A14: Tanjung Redep Unit 1 | B14: PLN | C14: 7 | D14: 2014 | E14: 2.185 | F14: 117.52 | G14: PT Indo Pusaka Berau | H14: operating
... A21: Tanjung Pinang Unit 2 | B21: PLN | C21: 15 | D21: 2012 | E21: 0.909722 | F21: 104.62917 | G21: PT PLN (Persero) / PLN Nusantara Power | H21: operating

Sheet Sheet16
A1: Alor Unit 1 | B1: =vlookup(A1,#REF!,1,false) -> #REF!
A2: Alor Unit 2 | B2: =vlookup(A2,#REF!,1,false) -> #REF!
A3: Ampana Unit 1 | B3: =vlookup(A3,#REF!,1,false) -> #REF!
A4: Ampana Unit 2 | B4: =vlookup(A4,#REF!,1,false) -> #REF!
A5: Atambua Unit 1 | B5: =vlookup(A5,#REF!,1,false) -> #REF!
A6: Atambua Unit 2 | B6: =vlookup(A6,#REF!,1,false) -> #REF!
A7: Atambua Unit 3 | B7: =vlookup(A7,#REF!,1,false) -> #REF!
A8: Atambua Unit 4 | B8: =vlookup(A8,#REF!,1,false) -> #REF!
A9: Berau Unit 1 | B9: =vlookup(A9,#REF!,1,false) -> #REF!
A10: Berau Unit 2 | B10: =vlookup(A10,#REF!,1,false) -> #REF!
A11: Bima Unit 1 | B11: =vlookup(A11,#REF!,1,false) -> #REF!
A12: Bima Unit 2 | B12: =vlookup(A12,#REF!,1,false) -> #REF!
... A86: Tidore Unit 2 | B86: =vlookup(A86,#REF!,1,false) -> #REF!

Sheet GCPT Jul 2026
A1: GEM unit/phase ID | B1: GEM location ID | C1: Country/Area | D1: Wiki URL | E1: Plant name | F1: Unit name | G1: ref | H1: Plant name (other) | I1: Plant name (local) | J1: Owner | K1: Owner GEM Entity ID | L1: Parent | M1: Parent GEM Entity ID | N1: Capacity (MW) | O1: Status | P1: Start year | Q1: Retired year | R1: Planned retirement | S1: Combustion technology | T1: Coal type | U1: Coal source | V1: Conversion to (fuel) | W1: Conversion to (GEM unit ID) | X1: Alternate Fuel | Y1: Location | Z1: Local area (taluk, county) | AA1: Major area (prefecture, district) | AB1: Subnational unit (province, state) | AC1: Subregion | AD1: Region | AE1: Latitude | AF1: Longitude | AG1: Location accuracy | AH1: Permits | AI1: Permit Date | AJ1: Permit Parsed | AK1: Captive | AL1: Captive industry use | AM1: Captive residential use | AN1: CCS | AO1: CHP
A2: G100000100037 | B2: L100000102733 | C2: Indonesia | D2: https://www.gem.wiki/Adaro_East_Kalimantan_power_station | E2: Adaro East Kalimantan power station | F2: Unit 1 | G2: Adaro East Kalimantan Unit 1 | H2: Kaltim?, East Kuktai | J2: China Shenhua Overseas Development and Investment Co Ltd; PT Adaro Power; PT Bhakti Energi Persada [100%] | K2: E100000120029; E100001013153 [100%]; E100002007614 | L2: unknown [81.5%]; PT Alamtri Resources Indonesia Tbk [18.5%]; China Shenhua Energy Co Ltd | M2: E100000132388 [81.5%]; E100001000782 [18.5%]; E100000000175 | N2: 300 | O2: cancelled | S2: unknown | T2: unknown | U2: mine-mouth | AB2: Kalimantan | AC2: South-eastern Asia | AD2: Asia | AE2: 0.1 | AF2: 116.4 | AG2: approximate | AN2: no
A3: G100000100038 | B3: L100000102733 | C3: Indonesia | D3: https://www.gem.wiki/Adaro_East_Kalimantan_power_station | E3: Adaro East Kalimantan power station | F3: Unit 2 | G3: Adaro East Kalimantan Unit 2 | H3: Kaltim?, East Kuktai | J3: China Shenhua Overseas Development and Investment Co Ltd; PT Adaro Power; PT Bhakti Energi Persada [100%] | K3: E100000120029; E100001013153 [100%]; E100002007614 | L3: unknown [81.5%]; PT Alamtri Resources Indonesia Tbk [18.5%]; China Shenhua Energy Co Ltd | M3: E100000132388 [81.5%]; E100001000782 [18.5%]; E100000000175 | N3: 300 | O3: cancelled | S3: unknown | T3: unknown | U3: mine-mouth | AB3: Kalimantan | AC3: South-eastern Asia | AD3: Asia | AE3: 0.1 | AF3: 116.4 | AG3: approximate | AN3: no
A4: G100000100040 | B4: L100000102708 | C4: Indonesia | D4: https://www.gem.wiki/Adipala_power_station | E4: Adipala power station | F4: Unit 1 | G4: Adipala Unit 1 | H4: 印尼国电阿迪帕拉电站, Pembangkit Listrik Tenaga Uap Adipala | J4: PT PLN (Persero) [100%] | K4: E100000000537 [100%] | L4: PT PLN (Persero) [100.0%] | M4: E100000000537 [100.0%] | N4: 660 | O4: operating | P4: 2015 | S4: supercritical | T4: subbituminous [96%] | X4: bioenergy | Y4: Bunton | Z4: Adipala | AA4: Cilacap | AB4: Jawa | AC4: South-eastern Asia | AD4: Asia | AE4: -7.685942 | AF4: 109.13756 | AG4: exact | AN4: no
A5: G100000114904 | B5: L100000104619 | C5: Indonesia | D5: https://www.gem.wiki/Nanshan_Industrial_Park_power_station | E5: Nanshan Industrial Park power station | F5: Phase II Unit 1 | G5: Nanshan Industrial Park Phase II Unit 1 | H5: 公司印尼宾坦岛卡朗巴唐经济特区动力中心4×150MW电站项目 (Phase II), 南山宾坦工业园自备电厂 | J5: PT Bintan Alumina Indonesia [100%] | K5: E100000120999 [100%] | L5: Nanshan Aluminium International Holdings Ltd [72.7%]; Hong Kong Prime Aluminium Investment Ltd [25.0%]; small shareholder(s) [2.3%] | M5: E100002015281 [72.7%]; E100002015282 [25.0%]; E100001015587 [2.3%] | N5: 150 | O5: construction | P5: 2027 | S5: unknown | T5: unknown | Z5: Galang Batang | AA5: Bintan | AB5: Sumatera | AC5: South-eastern Asia | AD5: Asia | AE5: 0.911643 | AF5: 104.65054 | AG5: exact | AK5: aluminum | AL5: power | AN5: no
A6: G100000114905 | B6: L100000104619 | C6: Indonesia | D6: https://www.gem.wiki/Nanshan_Industrial_Park_power_station | E6: Nanshan Industrial Park power station | F6: Phase II Unit 2 | G6: Nanshan Industrial Park Phase II Unit 2 | H6: 公司印尼宾坦岛卡朗巴唐经济特区动力中心4×150MW电站项目 (Phase II), 南山宾坦工业园自备电厂 | J6: PT Bintan Alumina Indonesia [100%] | K6: E100000120999 [100%] | L6: Nanshan Aluminium International Holdings Ltd [72.7%]; Hong Kong Prime Aluminium Investment Ltd [25.0%]; small shareholder(s) [2.3%] | M6: E100002015281 [72.7%]; E100002015282 [25.0%]; E100001015587 [2.3%] | N6: 150 | O6: construction | P6: 2027 | S6: unknown | T6: unknown | Z6: Galang Batang | AA6: Bintan | AB6: Sumatera | AC6: South-eastern Asia | AD6: Asia | AE6: 0.911643 | AF6: 104.65054 | AG6: exact | AK6: aluminum | AL6: power | AN6: no
A7: G100000115357 | B7: L100000104831 | C7: Indonesia | D7: https://www.gem.wiki/PT_Halmahera_Persada_Lygend_Nickel_Smelter_power_station | E7: PT Halmahera Persada Lygend Nickel Smelter power station | F7: Phase III Unit 3 | G7: PT Halmahera Persada Lygend Nickel Smelter Phase III Unit 3 | H7: PLTU Obi Sinar Timur (Phase III), 宁波力勤印尼镍铁项目自备电厂 | J7: PT Obi Nickel Cobalt [100%] | K7: E100000121047 [100%] | L7: Ningbo Lygend [36.9%]; Harita Group | M7: E100000120928 [36.9%]; E100000120543 | N7: 380 | O7: construction | S7: unknown | T7: unknown | Y7: Kawasi | Z7: Obi | AA7: South Halmahera | AB7: Maluku | AC7: South-eastern Asia | AD7: Asia | AE7: -1.5614331 | AF7: 127.42103 | AG7: exact | AK7: nickel | AL7: power | AN7: no
A8: G100000115358 | B8: L100000104831 | C8: Indonesia | D8: https://www.gem.wiki/PT_Halmahera_Persada_Lygend_Nickel_Smelter_power_station | E8: PT Halmahera Persada Lygend Nickel Smelter power station | F8: Phase III Unit 4 | G8: PT Halmahera Persada Lygend Nickel Smelter Phase III Unit 4 | H8: PLTU Obi Sinar Timur (Phase III), 宁波力勤印尼镍铁项目自备电厂 | J8: PT Obi Nickel Cobalt [100%] | K8: E100000121047 [100%] | L8: Ningbo Lygend [36.9%]; Harita Group | M8: E100000120928 [36.9%]; E100000120543 | N8: 380 | O8: construction | S8: unknown | T8: unknown | Y8: Kawasi | Z8: Obi | AA8: South Halmahera | AB8: Maluku | AC8: South-eastern Asia | AD8: Asia | AE8: -1.5614331 | AF8: 127.42103 | AG8: exact | AK8: nickel | AL8: power | AN8: no
A9: G100000115748 | B9: L100000104979 | C9: Indonesia | D9: https://www.gem.wiki/AlamTri_Aluminum_Smelter_power_station | E9: AlamTri Aluminum Smelter power station | F9: Phase I Unit 1 | G9: AlamTri Aluminum Smelter Phase I Unit 1 | H9: PT Kalimantan Industrial Park Indonesia power station, Adaro Aluminum Smelter power station | J9: PT Kaltara Power Indonesia [100%] | K9: E100000120702 [100%] | L9: PT Alamtri Resources Indonesia Tbk [84.0%]; PT Cita Mineral Investindo Tbk [16.0%] | M9: E100001000782 [84.0%]; E100002018990 [16.0%] | N9: 150 | O9: construction | P9: 2026 | S9: unknown | T9: unknown | Z9: Tanah Kuning | AA9: Bulungan | AB9: Kalimantan | AC9: South-eastern Asia | AD9: Asia | AE9: 2.4946822 | AF9: 117.9002 | AG9: exact | AK9: aluminum | AL9: power | AN9: no
A10: G100001092190 | B10: L100000104979 | C10: Indonesia | D10: https://www.gem.wiki/AlamTri_Aluminum_Smelter_power_station | E10: AlamTri Aluminum Smelter power station | F10: Phase II Unit 2 | G10: AlamTri Aluminum Smelter Phase II Unit 2 | H10: PT Kalimantan Industrial Park Indonesia power station, Adaro Aluminum Smelter power station | J10: PT Kaltara Power Indonesia [100%] | K10: E100000120702 [100%] | L10: PT Alamtri Resources Indonesia Tbk [84.0%]; PT Cita Mineral Investindo Tbk [16.0%] | M10: E100001000782 [84.0%]; E100002018990 [16.0%] | N10: 150 | O10: announced | P10: 2026 | S10: unknown | T10: unknown | Z10: Tanah Kuning | AA10: Bulungan | AB10: Kalimantan | AC10: South-eastern Asia | AD10: Asia | AE10: 2.4946822 | AF10: 117.9002 | AG10: exact | AK10: aluminum | AL10: power | AN10: no
A11: G100001092191 | B11: L100000104979 | C11: Indonesia | D11: https://www.gem.wiki/AlamTri_Aluminum_Smelter_power_station | E11: AlamTri Aluminum Smelter power station | F11: Phase II Unit 3 | G11: AlamTri Aluminum Smelter Phase II Unit 3 | H11: PT Kalimantan Industrial Park Indonesia power station, Adaro Aluminum Smelter power station | J11: PT Kaltara Power Indonesia [100%] | K11: E100000120702 [100%] | L11: PT Alamtri Resources Indonesia Tbk [84.0%]; PT Cita Mineral Investindo Tbk [16.0%] | M11: E100001000782 [84.0%]; E100002018990 [16.0%] | N11: 380 | O11: announced | P11: 2026 | S11: unknown | T11: unknown | Z11: Tanah Kuning | AA11: Bulungan | AB11: Kalimantan | AC11: South-eastern Asia | AD11: Asia | AE11: 2.4946822 | AF11: 117.9002 | AG11: exact | AK11: aluminum | AL11: power | AN11: no
A12: G100001092192 | B12: L100000104979 | C12: Indonesia | D12: https://www.gem.wiki/AlamTri_Aluminum_Smelter_power_station | E12: AlamTri Aluminum Smelter power station | F12: Phase II Unit 4 | G12: AlamTri Aluminum Smelter Phase II Unit 4 | H12: PT Kalimantan Industrial Park Indonesia power station, Adaro Aluminum Smelter power station | J12: PT Kaltara Power Indonesia [100%] | K12: E100000120702 [100%] | L12: PT Alamtri Resources Indonesia Tbk [84.0%]; PT Cita Mineral Investindo Tbk [16.0%] | M12: E100001000782 [84.0%]; E100002018990 [16.0%] | N12: 380 | O12: announced | P12: 2026 | S12: unknown | T12: unknown | Z12: Tanah Kuning | AA12: Bulungan | AB12: Kalimantan | AC12: South-eastern Asia | AD12: Asia | AE12: 2.4946822 | AF12: 117.9002 | AG12: exact | AK12: aluminum | AL12: power | AN12: no
A13: G100000100142 | B13: L100000102773 | C13: Indonesia | D13: https://www.gem.wiki/Amamapare_Port_power_station | E13: Amamapare Port power station | F13: Unit 1 | G13: Amamapare Port Unit 1 | J13: PT Freeport Indonesia [100%] | K13: E100000003755 [100%] | L13: FreePort-McMoran Inc [48.8%]; PT Mineral Industri Indonesia (Persero) | M13: E100000001220 [48.8%]; E100001011088 | N13: 65 | O13: operating | P13: 1998 | R13: 2027 | S13: subcritical | T13: unknown | U13: Pinang coal deposit | Y13: Amamapare | Z13: Mimika Timur Jauh | AA13: Mimika | AB13: Papua | AC13: South-eastern Asia | AD13: Asia | AE13: -4.827752 | AF13: 136.83908 | AG13: exact | AK13: other metals & mining | AL13: power | AN13: no
A14: G100000100143 | B14: L100000102773 | C14: Indonesia | D14: https://www.gem.wiki/Amamapare_Port_power_station | E14: Amamapare Port power station | F14: Unit 2 | G14: Amamapare Port Unit 2 | J14: PT Freeport Indonesia [100%] | K14: E100000003755 [100%] | L14: FreePort-McMoran Inc [48.8%]; PT Mineral Industri Indonesia (Persero) | M14: E100000001220 [48.8%]; E100001011088 | N14: 65 | O14: operating | P14: 1998 | R14: 2027 | S14: subcritical | T14: unknown | U14: Pinang coal deposit | Y14: Amamapare | Z14: Mimika Timur Jauh | AA14: Mimika | AB14: Papua | AC14: South-eastern Asia | AD14: Asia | AE14: -4.827752 | AF14: 136.83908 | AG14: exact | AK14: other metals & mining | AL14: power | AN14: no
A15: G100000100144 | B15: L100000102773 | C15: Indonesia | D15: https://www.gem.wiki/Amamapare_Port_power_station | E15: Amamapare Port power station | F15: Unit 3 | G15: Amamapare Port Unit 3 | J15: PT Freeport Indonesia [100%] | K15: E100000003755 [100%] | L15: FreePort-McMoran Inc [48.8%]; PT Mineral Industri Indonesia (Persero) | M15: E100000001220 [48.8%]; E100001011088 | N15: 65 | O15: operating | P15: 1999 | R15: 2027 | S15: subcritical | T15: unknown | U15: Pinang coal deposit | Y15: Amamapare | Z15: Mimika Timur Jauh | AA15: Mimika | AB15: Papua | AC15: South-eastern Asia | AD15: Asia | AE15: -4.827752 | AF15: 136.83908 | AG15: exact | AK15: other metals & mining | AL15: power | AN15: no
A16: G100000100152 | B16: L100000102757 | C16: Indonesia | D16: https://www.gem.wiki/Ambon-2_power_station | E16: Ambon-2 power station | F16: Unit 1 | G16: Ambon-2 Unit 1 | J16: PT PLN (Persero) [100%] | K16: E100000000537 [100%] | L16: PT PLN (Persero) [100.0%] | M16: E100000000537 [100.0%] | N16: 50 | O16: cancelled | S16: subcritical | T16: unknown | AB16: Maluku | AC16: South-eastern Asia | AD16: Asia | AE16: -3.586516 | AF16: 128.17111 | AG16: approximate | AN16: no
A17: G100000100153 | B17: L100000102757 | C17: Indonesia | D17: https://www.gem.wiki/Ambon-2_power_station | E17: Ambon-2 power station | F17: Unit 2 | G17: Ambon-2 Unit 2 | J17: PT PLN (Persero) [100%] | K17: E100000000537 [100%] | L17: PT PLN (Persero) [100.0%] | M17: E100000000537 [100.0%] | N17: 50 | O17: cancelled | S17: subcritical | T17: unknown | AB17: Maluku | AC17: South-eastern Asia | AD17: Asia | AE17: -3.586516 | AF17: 128.17111 | AG17: approximate | AN17: no
A18: G100000100180 | B18: L100000102759 | C18: Indonesia | D18: https://www.gem.wiki/Amurang_power_station | E18: Amurang power station | F18: Unit 1 | G18: Amurang Unit 1 | H18: Sulut 2 | J18: PT PLN (Persero) [100%] | K18: E100000000537 [100%] | L18: PT PLN (Persero) [100.0%] | M18: E100000000537 [100.0%] | N18: 30 | O18: operating | P18: 2012 | S18: subcritical | T18: subbituminous | X18: bioenergy | Y18: Amurang | AA18: South Minahasa | AB18: Sulawesi | AC18: South-eastern Asia | AD18: Asia | AE18: 1.182502 | AF18: 124.48056 | AG18: exact | AN18: no
A19: G100000100181 | B19: L100000102759 | C19: Indonesia | D19: https://www.gem.wiki/Amurang_power_station | E19: Amurang power station | F19: Unit 2 | G19: Amurang Unit 2 | H19: Sulut 2 | J19: PT PLN (Persero) [100%] | K19: E100000000537 [100%] | L19: PT PLN (Persero) [100.0%] | M19: E100000000537 [100.0%] | N19: 30 | O19: operating | P19: 2012 | S19: subcritical | T19: subbituminous | X19: bioenergy | Y19: Amurang | AA19: South Minahasa | AB19: Sulawesi | AC19: South-eastern Asia | AD19: Asia | AE19: 1.182502 | AF19: 124.48056 | AG19: exact | AN19: no
A20: G100000113971 | B20: L100000104535 | C20: Indonesia | D20: https://www.gem.wiki/Amurang-2_power_station | E20: Amurang-2 power station | F20: Unit 1 | G20: Amurang-2 Unit 1 | J20: PT PLN (Persero) [100%] | K20: E100000000537 [100%] | L20: PT PLN (Persero) [100.0%] | M20: E100000000537 [100.0%] | N20: 30 | O20: operating | P20: 2018 | S20: subcritical | T20: unknown | Y20: Amurang | AA20: South Minahasa | AB20: Sulawesi | AC20: South-eastern Asia | AD20: Asia | AE20: 1.182502 | AF20: 124.48056 | AG20: exact | AN20: no
A21: G100000113972 | B21: L100000104535 | C21: Indonesia | D21: https://www.gem.wiki/Amurang-2_power_station | E21: Amurang-2 power station | F21: Unit 2 | G21: Amurang-2 Unit 2 | J21: PT PLN (Persero) [100%] | K21: E100000000537 [100%] | L21: PT PLN (Persero) [100.0%] | M21: E100000000537 [100.0%] | N21: 30 | O21: operating | P21: 2018 | S21: subcritical | T21: unknown | Y21: Amurang | AA21: South Minahasa | AB21: Sulawesi | AC21: South-eastern Asia | AD21: Asia | AE21: 1.182502 | AF21: 124.48056 | AG21: exact | AN21: no
A22: G100000100367 | B22: L100000102695 | C22: Indonesia | D22: https://www.gem.wiki/Asahimas_Chemical_power_station | E22: Asahimas Chemical power station | F22: Unit 1 | G22: Asahimas Chemical Unit 1 | H22: 日本旭硝子玻璃公司自备电厂 | J22: PT Asahimas Chemical [100%] | K22: E100000120082 [100%] | L22: AGC Inc [52.5%]; PT Rodamas [18.0%]; Mitsubishi Corp [11.5%]; natural person(s) | M22: E100000133539 [52.5%]; E100000121184 [18.0%]; E100000000650 [11.5%]; E100000123261 | N22: 150 | O22: operating | P22: 2019 | S22: unknown | T22: unknown | X22: bioenergy | AA22: Cilegon | AB22: Jawa | AC22: South-eastern Asia | AD22: Asia | AE22: -6.024754 | AF22: 105.94263 | AG22: exact | AK22: chemicals | AL22: power | AN22: no
A23: G100000112731 | B23: L100000102695 | C23: Indonesia | D23: https://www.gem.wiki/Asahimas_Chemical_power_station | E23: Asahimas Chemical power station | F23: Unit 2 | G23: Asahimas Chemical Unit 2 | H23: 日本旭硝子玻璃公司自备电厂 | J23: PT Asahimas Chemical [100%] | K23: E100000120082 [100%] | L23: AGC Inc [52.5%]; PT Rodamas [18.0%]; Mitsubishi Corp [11.5%]; natural person(s) | M23: E100000133539 [52.5%]; E100000121184 [18.0%]; E100000000650 [11.5%]; E100000123261 | N23: 150 | O23: operating | P23: 2019 | S23: unknown | T23: unknown | X23: bioenergy | AA23: Cilegon | AB23: Jawa | AC23: South-eastern Asia | AD23: Asia | AE23: -6.024754 | AF23: 105.94263 | AG23: exact | AK23: chemicals | AL23: power | AN23: no
A24: G100000105482 | B24: L100000102783 | C24: Indonesia | D24: https://www.gem.wiki/Asam-Asam_power_station | E24: Asam-Asam power station | F24: Unit 1 | G24: Asam-Asam Unit 1 | H24: Kalselteng-2 | J24: PT PLN (Persero) [100%] | K24: E100000000537 [100%] | L24: PT PLN (Persero) [100.0%] | M24: E100000000537 [100.0%] | N24: 65 | O24: operating | P24: 2013 | S24: unknown | T24: lignite | X24: bioenergy | Y24: Asam-Asam | Z24: Jorong | AA24: Tanah Laut | AB24: Kalimantan | AC24: South-eastern Asia | AD24: Asia | AE24: -3.9265336 | AF24: 115.10581 | AG24: exact | AN24: no
A25: G100000105483 | B25: L100000102783 | C25: Indonesia | D25: https://www.gem.wiki/Asam-Asam_power_station | E25: Asam-Asam power station | F25: Unit 2 | G25: Asam-Asam Unit 2 | H25: Kalselteng-2 | J25: PT PLN (Persero) [100%] | K25: E100000000537 [100%] | L25: PT PLN (Persero) [100.0%] | M25: E100000000537 [100.0%] | N25: 65 | O25: operating | P25: 2013 | S25: unknown | T25: lignite | X25: bioenergy | Y25: Asam-Asam | Z25: Jorong | AA25: Tanah Laut | AB25: Kalimantan | AC25: South-eastern Asia | AD25: Asia | AE25: -3.9265336 | AF25: 115.10581 | AG25: exact | AN25: no
A26: G100000100515 | B26: L100000102783 | C26: Indonesia | D26: https://www.gem.wiki/Asam-Asam_power_station | E26: Asam-Asam power station | F26: Unit 5 | G26: Asam-Asam Unit 5 | H26: Kalselteng-2 | J26: PT PLN (Persero) [100%] | K26: E100000000537 [100%] | L26: PT PLN (Persero) [100.0%] | M26: E100000000537 [100.0%] | N26: 100 | O26: operating | P26: 2024 | S26: subcritical | T26: lignite | Z26: Jorong | AA26: Tanah Laut | AB26: Kalimantan | AC26: South-eastern Asia | AD26: Asia | AE26: -3.9265336 | AF26: 115.10581 | AG26: exact | AN26: no
A27: G100000100516 | B27: L100000102783 | C27: Indonesia | D27: https://www.gem.wiki/Asam-Asam_power_station | E27: Asam-Asam power station | F27: Unit 6 | G27: Asam-Asam Unit 6 | H27: Kalselteng-2 | J27: PT PLN (Persero) [100%] | K27: E100000000537 [100%] | L27: PT PLN (Persero) [100.0%] | M27: E100000000537 [100.0%] | N27: 100 | O27: operating | P27: 2025 | S27: subcritical | T27: lignite | Z27: Jorong | AA27: Tanah Laut | AB27: Kalimantan | AC27: South-eastern Asia | AD27: Asia | AE27: -3.9265336 | AF27: 115.10581 | AG27: exact | AN27: no
A28: G100000100517 | B28: L100000102783 | C28: Indonesia | D28: https://www.gem.wiki/Asam-Asam_power_station | E28: Asam-Asam power station | F28: Unit B-3 | G28: Asam-Asam Unit B-3 | H28: Kalselteng-2 | J28: PT PLN (Persero) [100%] | K28: E100000000537 [100%] | L28: PT PLN (Persero) [100.0%] | M28: E100000000537 [100.0%] | N28: 65 | O28: operating | P28: 2000 | S28: subcritical | T28: lignite | X28: bioenergy | Y28: Asam-Asam | Z28: Jorong | AA28: Tanah Laut | AB28: Kalimantan | AC28: South-eastern Asia | AD28: Asia | AE28: -3.9265336 | AF28: 115.10581 | AG28: exact | AN28: no
A29: G100000100518 | B29: L100000102783 | C29: Indonesia | D29: https://www.gem.wiki/Asam-Asam_power_station | E29: Asam-Asam power station | F29: Unit B-4 | G29: Asam-Asam Unit B-4 | H29: Kalselteng-2 | J29: PT PLN (Persero) [100%] | K29: E100000000537 [100%] | L29: PT PLN (Persero) [100.0%] | M29: E100000000537 [100.0%] | N29: 65 | O29: operating | P29: 2000 | S29: subcritical | T29: lignite | X29: bioenergy | Y29: Asam-Asam | Z29: Jorong | AA29: Tanah Laut | AB29: Kalimantan | AC29: South-eastern Asia | AD29: Asia | AE29: -3.9265336 | AF29: 115.10581 | AG29: exact | AN29: no
A30: G100000100391 | B30: L100000102750 | C30: Indonesia | D30: https://www.gem.wiki/Astratel_power_station | E30: Astratel power station | F30: Phase I | G30: Astratel Phase I | J30: Astratel Nusantara [100%] | K30: E100000120093 [100%] | L30: PT Astra International Tbk [100.0%] | M30: E100001010578 [100.0%] | N30: 100 | O30: cancelled | S30: subcritical | T30: unknown | AB30: Sumatera | AC30: South-eastern Asia | AD30: Asia | AE30: -2.75 | AF30: 103.83333 | AG30: approximate | AN30: no
A31: G100000100455 | B31: L100000102734 | C31: Indonesia | D31: https://www.gem.wiki/Bakrie_Sangatta_power_station | E31: Bakrie Sangatta power station | F31: Unit 1 | G31: Bakrie Sangatta Unit 1 | H31: Sangatta Mines | J31: PT Bakrie Indo Infrastructure [100%] | K31: E100000120993 [100%] | L31: PT Bakrie & Brothers Tbk [100.0%] | M31: E100001015677 [100.0%] | N31: 100 | O31: cancelled | S31: subcritical | T31: unknown | U31: Kaltim Prima Coal Sangatta coal mine | Y31: Sangatta Mining Area | AA31: East Kutai (Kutai Timur) | AB31: Kalimantan | AC31: South-eastern Asia | AD31: Asia | AE31: 0.605 | AF31: 117.481 | AG31: approximate | AN31: no
A32: G100000100456 | B32: L100000102734 | C32: Indonesia | D32: https://www.gem.wiki/Bakrie_Sangatta_power_station | E32: Bakrie Sangatta power station | F32: Unit 2 | G32: Bakrie Sangatta Unit 2 | H32: Sangatta Mines | J32: PT Bakrie Indo Infrastructure [100%] | K32: E100000120993 [100%] | L32: PT Bakrie & Brothers Tbk [100.0%] | M32: E100001015677 [100.0%] | N32: 100 | O32: cancelled | S32: subcritical | T32: unknown | U32: Kaltim Prima Coal Sangatta coal mine | Y32: Sangatta Mining Area | AA32: East Kutai (Kutai Timur) | AB32: Kalimantan | AC32: South-eastern Asia | AD32: Asia | AE32: 0.605 | AF32: 117.481 | AG32: approximate | AN32: no
A33: G100000113818 | B33: L100000104395 | C33: Indonesia | D33: https://www.gem.wiki/Bali_Power_Station | E33: Bali Power Station | F33: Unit 1 | G33: Bali Unit 1 | J33: PT PLN (Persero) [100%] | K33: E100000000537 [100%] | L33: PT PLN (Persero) [100.0%] | M33: E100000000537 [100.0%] | N33: 135 | O33: cancelled | S33: unknown | T33: unknown | AB33: Nusa Tenggara | AC33: South-eastern Asia | AD33: Asia | AE33: -8.447602 | AF33: 115.12221 | AG33: approximate | AN33: no
A34: G100000100505 | B34: L100000102812 | C34: Indonesia | D34: https://www.gem.wiki/Bandung_Indosyntec_power_station | E34: Bandung Indosyntec power station | F34: Unit 1 | G34: Bandung Indosyntec Unit 1 | J34: PT Panasia Indo Resources Tbk [100%] | K34: E100000121053 [100%] | L34: Lucky Height Resources Ltd [27.8%]; Gold Gazelle Profits Corp [19.6%]; PT Panasia Synthetic Abadi [19.4%]; Ortega Management Ltd [10.0%]; Mercury Capital International Inc [9.7%]; Prime Invesco Ltd [9.5%]; small shareholder(s) [4.0%] | M34: E100001011652 [27.8%]; E100001011651 [19.6%]; E100001011654 [19.4%]; E100001011653 [10.0%]; E100001011655 [9.7%]; E100001011656 [9.5%]; E100001015587 [4.0%] | N34: 30 | O34: operating | P34: 2004 | S34: subcritical | T34: unknown | Y34: Kab Bandung | AB34: Jawa | AC34: South-eastern Asia | AD34: Asia | AE34: -6.970501 | AF34: 107.60578 | AG34: exact | AK34: textiles | AN34: no
A35: G100000100508 | B35: L100000102693 | C35: Indonesia | D35: https://www.gem.wiki/Bangka_Baru_power_station | E35: Bangka Baru power station | F35: Unit 1 | G35: Bangka Baru Unit 1 | H35: PLTU Ba-Bel | J35: PT PLN Wilayah Bangka Belitung [100%] | K35: E100000121049 [100%] | L35: PT PLN (Persero) | M35: E100000000537 | N35: 30 | O35: operating | P35: 2014 | S35: subcritical | T35: unknown | U35: Domestic | X35: bioenergy | Y35: Air Anyir | AB35: Sumatera | AC35: South-eastern Asia | AD35: Asia | AE35: -2.079245 | AF35: 106.14962 | AG35: exact | AN35: no
A36: G100000100509 | B36: L100000102693 | C36: Indonesia | D36: https://www.gem.wiki/Bangka_Baru_power_station | E36: Bangka Baru power station | F36: Unit 2 | G36: Bangka Baru Unit 2 | H36: PLTU Ba-Bel | J36: PT PLN Wilayah Bangka Belitung [100%] | K36: E100000121049 [100%] | L36: PT PLN (Persero) | M36: E100000000537 | N36: 30 | O36: operating | P36: 2014 | S36: subcritical | T36: unknown | U36: Domestic | X36: bioenergy | Y36: Air Anyir | AB36: Sumatera | AC36: South-eastern Asia | AD36: Asia | AE36: -2.079245 | AF36: 106.14962 | AG36: exact | AN36: no
A37: G100000112734 | B37: L100000102694 | C37: Indonesia | D37: https://www.gem.wiki/Bangka-1_power_station | E37: Bangka-1 power station | F37: Unit 1 | G37: Bangka-1 Unit 1 | J37: PT PLN (Persero) [100%] | K37: E100000000537 [100%] | L37: PT PLN (Persero) [100.0%] | M37: E100000000537 [100.0%] | N37: 200 | O37: cancelled | P37: 2027 | S37: subcritical | T37: unknown | AB37: Sumatera | AC37: South-eastern Asia | AD37: Asia | AE37: -2.133333 | AF37: 106.11667 | AG37: approximate | AN37: no
A38: G100000112735 | B38: L100000102694 | C38: Indonesia | D38: https://www.gem.wiki/Bangka-1_power_station | E38: Bangka-1 power station | F38: Unit 2 | G38: Bangka-1 Unit 2 | J38: PT PLN (Persero) [100%] | K38: E100000000537 [100%] | L38: PT PLN (Persero) [100.0%] | M38: E100000000537 [100.0%] | N38: 200 | O38: cancelled | P38: 2027 | S38: subcritical | T38: unknown | AB38: Sumatera | AC38: South-eastern Asia | AD38: Asia | AE38: -2.133333 | AF38: 106.11667 | AG38: approximate | AN38: no
A39: G100000114203 | B39: L100000104581 | C39: Indonesia | D39: https://www.gem.wiki/Bangka-1A_power_station | E39: Bangka-1A power station | F39: Unit 1 | G39: Bangka-1A Unit 1 | J39: PT PLN (Persero) [100%] | K39: E100000000537 [100%] | L39: PT PLN (Persero) [100.0%] | M39: E100000000537 [100.0%] | N39: 50 | O39: cancelled | P39: 2022 | S39: unknown | T39: unknown | Y39: Air Anyir | AB39: Sumatera | AC39: South-eastern Asia | AD39: Asia | AE39: -2.079245 | AF39: 106.14962 | AG39: approximate | AN39: no
A40: G100000114204 | B40: L100000104581 | C40: Indonesia | D40: https://www.gem.wiki/Bangka-1A_power_station | E40: Bangka-1A power station | F40: Unit 2 | G40: Bangka-1A Unit 2 | J40: PT PLN (Persero) [100%] | K40: E100000000537 [100%] | L40: PT PLN (Persero) [100.0%] | M40: E100000000537 [100.0%] | N40: 50 | O40: cancelled | P40: 2023 | S40: unknown | T40: unknown | Y40: Air Anyir | AB40: Sumatera | AC40: South-eastern Asia | AD40: Asia | AE40: -2.079245 | AF40: 106.14962 | AG40: approximate | AN40: no
A41: G100000100510 | B41: L100000102794 | C41: Indonesia | D41: https://www.gem.wiki/Bangko_Tengah_power_station | E41: Bangko Tengah power station | F41: Unit 1 | G41: Bangko Tengah Unit 1 | H41: Sumsel-8 (SS-8), 华电玻雅电站, PLTU Tanjung Lalang | J41: PT Huadian Bukit Asam Power [100%] | K41: E100000120575 [100%] | L41: China Huadian Corp Ltd [55.0%]; PT Bukit Asam Tbk [45.0%] | M41: E100000000170 [55.0%]; E100001000746 [45.0%] | N41: 660 | O41: operating | P41: 2023 | S41: supercritical | T41: unknown | U41: mine-mouth | Y41: Tanjung Enim coal mine | AA41: Muara Lenim / Lahat | AB41: Sumatera | AC41: South-eastern Asia | AD41: Asia | AE41: -3.838679 | AF41: 103.80413 | AG41: exact | AN41: no
A42: G100000100511 | B42: L100000102794 | C42: Indonesia | D42: https://www.gem.wiki/Bangko_Tengah_power_station | E42: Bangko Tengah power station | F42: Unit 2 | G42: Bangko Tengah Unit 2 | H42: Sumsel-8 (SS-8), 华电玻雅电站, PLTU Tanjung Lalang | J42: PT Huadian Bukit Asam Power [100%] | K42: E100000120575 [100%] | L42: China Huadian Corp Ltd [55.0%]; PT Bukit Asam Tbk [45.0%] | M42: E100000000170 [55.0%]; E100001000746 [45.0%] | N42: 660 | O42: operating | P42: 2023 | S42: supercritical | T42: unknown | U42: mine-mouth | Y42: Tanjung Enim coal mine | AA42: Muara Lenim / Lahat | AB42: Sumatera | AC42: South-eastern Asia | AD42: Asia | AE42: -3.838679 | AF42: 103.80413 | AG42: exact | AN42: no
A43: G100000100512 | B43: L100000102794 | C43: Indonesia | D43: https://www.gem.wiki/Bangko_Tengah_power_station | E43: Bangko Tengah power station | F43: Unit 3 | G43: Bangko Tengah Unit 3 | H43: Sumsel-8 (SS-8), 华电玻雅电站, PLTU Tanjung Lalang | J43: PT Huadian Bukit Asam Power [100%] | K43: E100000120575 [100%] | L43: China Huadian Corp Ltd [55.0%]; PT Bukit Asam Tbk [45.0%] | M43: E100000000170 [55.0%]; E100001000746 [45.0%] | N43: 660 | O43: cancelled | S43: unknown | T43: unknown | U43: mine-mouth | Y43: Tanjung Enim coal mine | AA43: Muara Lenim / Lahat | AB43: Sumatera | AC43: South-eastern Asia | AD43: Asia | AE43: -3.734 | AF43: 103.759 | AG43: approximate | AN43: no
A44: G100000100513 | B44: L100000102794 | C44: Indonesia | D44: https://www.gem.wiki/Bangko_Tengah_power_station | E44: Bangko Tengah power station | F44: Unit 4 | G44: Bangko Tengah Unit 4 | H44: Sumsel-8 (SS-8), 华电玻雅电站, PLTU Tanjung Lalang | J44: PT Huadian Bukit Asam Power [100%] | K44: E100000120575 [100%] | L44: China Huadian Corp Ltd [55.0%]; PT Bukit Asam Tbk [45.0%] | M44: E100000000170 [55.0%]; E100001000746 [45.0%] | N44: 660 | O44: cancelled | S44: unknown | T44: unknown | U44: mine-mouth | Y44: Tanjung Enim coal mine | AA44: Muara Lenim / Lahat | AB44: Sumatera | AC44: South-eastern Asia | AD44: Asia | AE44: -3.734 | AF44: 103.759 | AG44: approximate | AN44: no
A45: G100000100519 | B45: L100000102795 | C45: Indonesia | D45: https://www.gem.wiki/Banjarsari_power_station | E45: Banjarsari power station | F45: Unit 1 | G45: Banjarsari Unit 1 | J45: PT Bukit Pembangkit Innovative [100%] | K45: E100000121001 [100%] | L45: PT Bukit Asam Tbk [59.8%]; PT PLN (Persero) [37.3%]; unknown [3.0%] | M45: E100001000746 [59.8%]; E100000000537 [37.3%]; E100000132388 [3.0%] | N45: 110 | O45: operating | P45: 2015 | S45: subcritical | T45: subbituminous | Z45: East Merapi (Merapi Timur) | AA45: Lahat | AB45: Sumatera | AC45: South-eastern Asia | AD45: Asia | AE45: -3.72507 | AF45: 103.69039 | AG45: exact | AN45: no
A46: G100000100520 | B46: L100000102795 | C46: Indonesia | D46: https://www.gem.wiki/Banjarsari_power_station | E46: Banjarsari power station | F46: Unit 2 | G46: Banjarsari Unit 2 | J46: PT Bukit Pembangkit Innovative [100%] | K46: E100000121001 [100%] | L46: PT Bukit Asam Tbk [59.8%]; PT PLN (Persero) [37.3%]; unknown [3.0%] | M46: E100001000746 [59.8%]; E100000000537 [37.3%]; E100000132388 [3.0%] | N46: 110 | O46: operating | P46: 2015 | S46: subcritical | T46: subbituminous | Z46: East Merapi (Merapi Timur) | AA46: Lahat | AB46: Sumatera | AC46: South-eastern Asia | AD46: Asia | AE46: -3.72507 | AF46: 103.69039 | AG46: exact | AN46: no
A47: G100000114349 | B47: L100000104618 | C47: Indonesia | D47: https://www.gem.wiki/Bantaeng_BSE_power_station | E47: Bantaeng BSE power station | F47: Unit 1 | G47: Bantaeng BSE Unit 1 | H47: 班塔恩燃煤电站 | J47: PT Bantaeng Sigma Energy [100%] | K47: E100000120994 [100%] | L47: BTN Power; PT Biidznillah Tambang Nusantara | M47: E100000120119; E100000120997 | N47: 300 | O47: cancelled | P47: 2023 | S47: subcritical | T47: unknown | Y47: Papangloe Village | Z47: Pajukkukang District | AA47: Bantaeng Regency | AB47: Sulawesi | AC47: South-eastern Asia | AD47: Asia | AE47: -5.51695 | AF47: 120.02061 | AG47: approximate | AN47: no
A48: G100000114350 | B48: L100000104618 | C48: Indonesia | D48: https://www.gem.wiki/Bantaeng_BSE_power_station | E48: Bantaeng BSE power station | F48: Unit 2 | G48: Bantaeng BSE Unit 2 | H48: 班塔恩燃煤电站 | J48: PT Bantaeng Sigma Energy [100%] | K48: E100000120994 [100%] | L48: BTN Power; PT Biidznillah Tambang Nusantara | M48: E100000120119; E100000120997 | N48: 300 | O48: cancelled | P48: 2023 | S48: subcritical | T48: unknown | Y48: Papangloe Village | Z48: Pajukkukang District | AA48: Bantaeng Regency | AB48: Sulawesi | AC48: South-eastern Asia | AD48: Asia | AE48: -5.51695 | AF48: 120.02061 | AG48: approximate | AN48: no
A49: G100000100530 | B49: L100000102696 | C49: Indonesia | D49: https://www.gem.wiki/Banten_Labuan_power_station | E49: Banten Labuan power station | F49: Unit 1 | G49: Banten Labuan Unit 1 | H49: 拉布湾电站 | J49: PT PLN Indonesia Power [100%] | K49: E100000003758 [100%] | L49: PT PLN (Persero) [100.0%] | M49: E100000000537 [100.0%] | N49: 300 | O49: operating | P49: 2009 | S49: subcritical | T49: unknown | X49: bioenergy | Y49: Labuan | Z49: Labuan | AA49: Pandeglang | AB49: Jawa | AC49: South-eastern Asia | AD49: Asia | AE49: -6.392179 | AF49: 105.82778 | AG49: exact | AN49: no
A50: G100000100531 | B50: L100000102696 | C50: Indonesia | D50: https://www.gem.wiki/Banten_Labuan_power_station | E50: Banten Labuan power station | F50: Unit 2 | G50: Banten Labuan Unit 2 | H50: 拉布湾电站 | J50: PT PLN Indonesia Power [100%] | K50: E100000003758 [100%] | L50: PT PLN (Persero) [100.0%] | M50: E100000000537 [100.0%] | N50: 300 | O50: operating | P50: 2010 | S50: subcritical | T50: unknown | X50: bioenergy | Y50: Labuan | Z50: Labuan | AA50: Pandeglang | AB50: Jawa | AC50: South-eastern Asia | AD50: Asia | AE50: -6.392179 | AF50: 105.82778 | AG50: exact | AN50: no
A51: G100000100532 | B51: L100000102697 | C51: Indonesia | D51: https://www.gem.wiki/Banten_Lontar_power_station | E51: Banten Lontar power station | F51: Unit 1 | G51: Banten Lontar Unit 1 | H51: 龙湾电站 | J51: PT PLN (Persero) [100%] | K51: E100000000537 [100%] | L51: PT PLN (Persero) [100.0%] | M51: E100000000537 [100.0%] | N51: 315 | O51: operating | P51: 2011 | S51: subcritical | T51: unknown | X51: bioenergy | Z51: Kemiri | AA51: Tangerang Regency | AB51: Jawa | AC51: South-eastern Asia | AD51: Asia | AE51: -6.058874 | AF51: 106.4643 | AG51: exact | AN51: no
